Workbook
Name celpeCEE: '[1]@Referência'!$K$16:$K$18
Name ListaSimNao: '[1]@Referência'!$A$30:$A$31
Name Modalidade: '[1]@Referência'!$J$2:$J$6
Name tipoCELPE: '[1]@Referência'!$N$14:$N$18

Sheet Tabela de Transferência
A1: Campo | B1: Página | C1: Endereço.tex | D1: chave | E1: valor
A2: Inserir Mome do RT | B2: Capa | C2: TCC_Final_CCEE.tex | D2: <<nomeRt>> | E2: =IFERROR(UC_DADOS!B7,0) -> 71 9935-2628
A3: NOME DA UNIDADE CONSUMIDORA DA PMS | B3: Capa | C3: TCC_Final_CCEE.tex | D3: <<nomeUc>> | E3: =IFERROR(UC_DADOS!B1,0) -> MUNICIPIO DE SALVADOR 744 CMEI OLGA BENARIO
A4: Data | B4: Capa | C4: TCC_Final_CCEE.tex | D4: <<data>> | E4: =IFERROR(UC_DADOS!B8,0) -> 46086
A5: Inserir Mome do RT | B5: Contra Capa | C5: TCC_Final_CCEE.tex | D5: <<nomeRt>> | E5: =IFERROR(E2,0) -> 71 9935-2628
A6: NOME DA UNIDADE CONSUMIDORA DA PMS | B6: Contra Capa | C6: TCC_Final_CCEE.tex | D6: <<nomeUc>> | E6: =IFERROR(E3,0) -> MUNICIPIO DE SALVADOR 744 CMEI OLGA BENARIO
A7: Nome da UC | B7: Contra Capa | C7: TCC_Final_CCEE.tex | D7: <<nomeUc>> | E7: =IFERROR(E6,0) -> MUNICIPIO DE SALVADOR 744 CMEI OLGA BENARIO
A8: Data | B8: Contra Capa | C8: TCC_Final_CCEE.tex | D8: <<data>> | E8: =IFERROR(E4,0) -> 46086
A9: Nome da Unidade | B9: 6 | C9: capitulo1.tex | D9: <<nomeUc>> | E9: =IFERROR(E3,0) -> MUNICIPIO DE SALVADOR 744 CMEI OLGA BENARIO
A10: Código da UC | B10: 6 | C10: capitulo1.tex | D10: <<codigoUc>> | E10: =IFERROR(UC_DADOS!B2,0) -> 7041435180
A11: Tipo de Atividade | B11: 6 | C11: capitulo1.tex | D11: <<tipoAtividade>> | E11: =IFERROR(UC_DADOS!B3,0) -> Escola
A12: Endereço Completo | B12: 6 | C12: capitulo1.tex | D12: <<endereco>> | E12: =IFERROR(UC_DADOS!B4,0) -> Rua Fernando São Paulo, Dóron
A13: Responsável / Cargo | B13: 6 | C13: capitulo1.tex | D13: <<responsavel>> | E13: =IFERROR(UC_DADOS!B6,0) -> Silvia
A14: Telefone para Contato | B14: 6 | C14: capitulo1.tex | D14: <<telefone>> | E14: =IFERROR(UC_DADOS!B7,0) -> 71 9935-2628
A15: E-mail Institucional | B15: 6 | C15: capitulo1.tex | D15: <<email>> | E15: =IFERROR(UC_DADOS!B9,0) -> educacao@prefs.com.br
A16: Adcionar Localidade | B16: 8 | C16: capitulo3.tex | D16: <<localidade>> | E16: =IFERROR(UC_DADOS!B5,0) -> Dóron, Salvador-BA
A17: Iluminação / Medida Proposta | B17: 11 | C17: capitulo4.tex | D17: <<propIluminacao>> | E17: =IFERROR(TABELAS_RESUMO!B12,0) -> Substituição por LED e sensores
A18: Climatização / Medida Proposta | B18: 11 | C18: capitulo4.tex | D18: <<propClimatizacao>> | E18: =IFERROR(TABELAS_RESUMO!B13,0) -> Troca de aparelhos de ar-condicionado e automação
A19: Motores / Medida Proposta | B19: 11 | C19: capitulo4.tex | D19: <<propMotores>> | E19: =IFERROR(TABELAS_RESUMO!B14,0) -> Substituição por motores de alto rendimento
A20: Refrigeração / Medida Proposta | B20: 11 | C20: capitulo4.tex | D20: <<propRefrigeracao>> | E20: =IFERROR(TABELAS_RESUMO!B15,0) -> Troca de refrigeradores comerciais ineficientes
A21: Fotovoltaico / Medida Proposta | B21: 11 | C21: capitulo4.tex | D21: <<propFotovoltaico>> | E21: =IFERROR(TABELAS_RESUMO!B16,0) -> Sistema conectado à rede (GD)
A22: Iluminação / Economia (MWh/ano) | B22: 11 | C22: capitulo4.tex | D22: <<iluEconomia>> | E22: =IFERROR(TABELAS_RESUMO!C12,0) -> 0
A23: Climatização / Economia (MWh/ano) | B23: 11 | C23: capitulo4.tex | D23: <<cliEconomia>> | E23: =IFERROR(TABELAS_RESUMO!C13,0) -> 0
A24: Motores / Economia (MWh/ano) | B24: 11 | C24: capitulo4.tex | D24: <<motEconomia>> | E24: =IFERROR(TABELAS_RESUMO!C14,0) -> 0
A25: Refrigeração / Economia (MWh/ano) | B25: 11 | C25: capitulo4.tex | D25: <<refEconomia>> | E25: =IFERROR(TABELAS_RESUMO!C15,0) -> 0
A26: Fotovoltaico / Economia (MWh/ano) | B26: 11 | C26: capitulo4.tex | D26: <<fotEconomia>> | E26: =IFERROR(TABELAS_RESUMO!C16,0) -> 0
A27: Total / Economia (MWh/ano) | B27: 11 | C27: capitulo4.tex | D27: <<totEconomia>> | E27: =IFERROR(TABELAS_RESUMO!C17,0) -> 0
A28: Iluminação / Invest. Total (R$) | B28: 11 | C28: capitulo4.tex | D28: <<iluInvestimento>> | E28: =IFERROR(TABELAS_RESUMO!D12,0) -> 0
A29: Climatização / Invest. Total (R$) | B29: 11 | C29: capitulo4.tex | D29: <<cliInvestimento>> | E29: =IFERROR(TABELAS_RESUMO!D13,0) -> 0
A30: Motores / Invest. Total (R$) | B30: 11 | C30: capitulo4.tex | D30: <<motInvestimento>> | E30: =IFERROR(TABELAS_RESUMO!D14,0) -> 0
A31: Refrigeração / Invest. Total (R$) | B31: 11 | C31: capitulo4.tex | D31: <<refInvestimento>> | E31: =IFERROR(TABELAS_RESUMO!D15,0) -> 0
A32: Fotovoltaico / Invest. Total (R$) | B32: 11 | C32: capitulo4.tex | D32: <<fotInvestimento>> | E32: =IFERROR(TABELAS_RESUMO!D16,0) -> 0
A33: Total / Invest. Total (R$) | B33: 11 | C33: capitulo4.tex | D33: <<totInvestimento>> | E33: =IFERROR(TABELAS_RESUMO!D17,0) -> 0
A34: Iluminação / PB | B34: 11 | C34: capitulo4.tex | D34: <<iluPayBack>> | E34: =IFERROR(TABELAS_RESUMO!E12,0) -> 0
A35: Climatização / PB | B35: 11 | C35: capitulo4.tex | D35: <<cliPayBack>> | E35: =IFERROR(TABELAS_RESUMO!E13,0) -> 0
A36: Motores / PB | B36: 11 | C36: capitulo4.tex | D36: <<motPayBack>> | E36: =IFERROR(TABELAS_RESUMO!E14,0) -> 0
A37: Refrigeração / PB | B37: 11 | C37: capitulo4.tex | D37: <<refPayBack>> | E37: =IFERROR(TABELAS_RESUMO!E15,0) -> 0
A38: Fotovoltaico / PB | B38: 11 | C38: capitulo4.tex | D38: <<fotPayBack>> | E38: =IFERROR(TABELAS_RESUMO!E16,0) -> 0
A39: Total / PB | B39: 11 | C39: capitulo4.tex | D39: <<totPayBack>> | E39: =IFERROR(TABELAS_RESUMO!E17,0) -> 0
A40: Nome da Unidade | B40: 12 | C40: capitulo5.tex | D40: <<nomeUc>> | E40: =IFERROR(E3,0) -> MUNICIPIO DE SALVADOR 744 CMEI OLGA BENARIO
A41: Gurpo de Tensão | B41: 20 | C41: capitulo6.tex | D41: <<grupoTensao>> | E41: =IFERROR(UC_DADOS!B29,0) -> Grupo A
A42: Modalidade tarifária | B42: 20 | C42: capitulo6.tex | D42: <<modalidadeTarifaria>> | E42: =IFERROR(UC_DADOS!B18,0) -> Alta Tensão - Verde
A43: Demanda contratada | B43: 20 | C43: capitulo6.tex | D43: <<demandaContratada>> | E43: =IFERROR(UC_DADOS!B19,0) -> 80
A44: Número da instalação na distribuidora | B44: 20 | C44: capitulo6.tex | D44: <<codInstalacao>> | E44: =IFERROR(UC_DADOS!B20,0) -> 11039337
A45: Código da unidade consumidora | B45: 20 | C45: capitulo6.tex | D45: <<codigoUc>> | E45: =IFERROR(UC_DADOS!B21,0) -> 7041435180
A46: Classe de consumo | B46: 20 | C46: capitulo6.tex | D46: <<classeConsumo>> | E46: =IFERROR(UC_DADOS!B22,0) -> A4 Horo-sazonal Verde PODER PUBLICO MUNICIPAL
A47: Consumo/Iluminação kWh | B47: 21 | C47: capitulo6.tex | D47: <<consumoIluminacao>> | E47: =IFERROR(CONSUMO_EQP!$B$2,0) -> 4.2745438 | F47: Grafico 1
A48: Consumo/Climatização kWh | B48: 21 | C48: capitulo6.tex | D48: <<consumoClimatizacao>> | E48: =IFERROR(CONSUMO_EQP!$B$3,0) -> 38.194308
A49: Consumo/Sistema Motrizes kWh | B49: 21 | C49: capitulo6.tex | D49: <<consumoMotores>> | E49: =IFERROR(CONSUMO_EQP!$B$4,0) -> 0
A50: Consumo/Refrigeração kWh | B50: 21 | C50: capitulo6.tex | D50: <<consumoRefrigeracao>> | E50: =IFERROR(CONSUMO_EQP!$B$5,0) -> 5.330016
A51: Consumo/Outros kWh | B51: 21 | C51: capitulo6.tex | D51: <<consumoOutros>> | E51: =IFERROR(CONSUMO_EQP!$B$6,0) -> 0.154
A52: Consumo/Total kWh | B52: 21 | C52: capitulo6.tex | D52: <<consumoTotal>> | E52: =IFERROR(CONSUMO_EQP!$B$7,0) -> 47.952868
A53: Fig. 7 Distribuição estimada do consumo de energia elétrica por uso final | B53: 21 | C53: capitulo6.tex | D53: Figuras/Grafico 1.png | E53: Grafico 1
A54: Parâmetro | B54: 22 | C54: capitulo7.tex | D54: <<parametro>> | E54: =IFERROR(UC_DADOS!A12,0) -> Alunos
A55: Dado do Parâmetro | B55: 22 | C55: capitulo7.tex | D55: <<dadoParametro>> | E55: =IFERROR(UC_DADOS!B12,0) -> 275
A56: Consumo médio mensal | B56: 22 | C56: capitulo7.tex | D56: <<consMedio>> | E56: =IFERROR(UC_DADOS!B13,0) -> 2342.81
A57: Consumo específico estimado | B57: 22 | C57: capitulo7.tex | D57: <<dadoConsEspecifico>> | E57: =IFERROR(UC_DADOS!B14,0) -> 8.5193091
A58: Grupo A ou B | B58: 23 | C58: capitulo8.tex | D58: <<grupoTensao>> | E58: =IFERROR(UC_DADOS!B29,0) -> Grupo A
A59: Modalidade tarifária | B59: 23 | C59: capitulo8.tex | D59: <<modalidadeTarifaria>> | E59: =IFERROR(E42,0) -> Alta Tensão - Verde
A60: Demanda contratada vigente | B60: 23 | C60: capitulo8.tex | D60: <<demandaContratada>> | E60: =IFERROR(E43,0) -> 80
A61: Primeiro mês analisado | B61: 23 | C61: capitulo8.tex | D61: <<mesInicial>> | E61: =IFERROR(UC_DADOS!D37,0) -> mai/25
A62: Ultimo mês analisado | B62: 23 | C62: capitulo8.tex | D62: <<mesFinal>> | E62: =IFERROR(UC_DADOS!D48,0) -> Sem Histórico Disponível
A63: Distribuidora | B63: 23 | C63: capitulo8.tex | D63: <<distribuidora>> | E63: =IFERROR(UC_DADOS!B33,0) -> Neoenergia Coelba - Bahia
A64: Preço da energia no ultimo mês | B64: 23 | C64: capitulo8.tex | D64: <<precoRecente>> | E64: =IFERROR(UC_DADOS!B32,0) -> 4707.45
A65: Mês / Ano 1 | B65: 23 | C65: capitulo8.tex | D65: <<mesUm>> | E65: =IFERROR(UC_DADOS!D37,0) -> mai/25
A66: Mês / Ano 2 | B66: 23 | C66: capitulo8.tex | D66: <<mesDois>> | E66: =IFERROR(UC_DADOS!D38,0) -> jul/25
A67: Mês / Ano 3 | B67: 23 | C67: capitulo8.tex | D67: <<mesTres>> | E67: =IFERROR(UC_DADOS!D39,0) -> out/25
A68: Mês / Ano 4 | B68: 23 | C68: capitulo8.tex | D68: <<mesQuatro>> | E68: =IFERROR(UC_DADOS!D40,0) -> nov/25
A69: Mês / Ano 5 | B69: 23 | C69: capitulo8.tex | D69: <<mesCinco>> | E69: =IFERROR(UC_DADOS!D41,0) -> dez/25
A70: Mês / Ano 6 | B70: 23 | C70: capitulo8.tex | D70: <<mesSeis>> | E70: =IFERROR(UC_DADOS!D42,0) -> jan/26
A71: Mês / Ano 7 | B71: 23 | C71: capitulo8.tex | D71: <<mesSete>> | E71: =IFERROR(UC_DADOS!D43,0) -> fev/26
A72: Mês / Ano 8 | B72: 23 | C72: capitulo8.tex | D72: <<mesOito>> | E72: =IFERROR(UC_DADOS!D44,0) -> mar/26
A73: Mês / Ano 9 | B73: 23 | C73: capitulo8.tex | D73: <<mesNove>> | E73: =IFERROR(UC_DADOS!D45,0) -> Sem Histórico Disponível
A74: Mês / Ano 10 | B74: 23 | C74: capitulo8.tex | D74: <<mesDez>> | E74: =IFERROR(UC_DADOS!D46,0) -> Sem Histórico Disponível
A75: Mês / Ano 11 | B75: 23 | C75: capitulo8.tex | D75: <<mesOnze>> | E75: =IFERROR(UC_DADOS!D47,0) -> Sem Histórico Disponível
A76: Mês / Ano 12 | B76: 23 | C76: capitulo8.tex | D76: <<mesDoze>> | E76: =IFERROR(UC_DADOS!D48,0) -> Sem Histórico Disponível
A77: Consumo Ponta 1 | B77: 23 | C77: capitulo8.tex | D77: <<ConsumoPontaUm>> | E77: =IFERROR(UC_DADOS!E37,0) -> 60.57
A78: Consumo Ponta 2 | B78: 23 | C78: capitulo8.tex | D78: <<ConsumoPontaDois>> | E78: =IFERROR(UC_DADOS!E38,0) -> 75.72
A79: Consumo Ponta 3 | B79: 23 | C79: capitulo8.tex | D79: <<ConsumoPontaTres>> | E79: =IFERROR(UC_DADOS!E39,0) -> 92.14
A80: Consumo Ponta 4 | B80: 23 | C80: capitulo8.tex | D80: <<ConsumoPontaQuatro>> | E80: =IFERROR(UC_DADOS!E40,0) -> 74.97
A81: Consumo Ponta 5 | B81: 23 | C81: capitulo8.tex | D81: <<ConsumoPontaCinco>> | E81: =IFERROR(UC_DADOS!E41,0) -> 82.05
A82: Consumo Ponta 6 | B82: 23 | C82: capitulo8.tex | D82: <<ConsumoPontaSeis>> | E82: =IFERROR(UC_DADOS!E42,0) -> 86.34
A83: Consumo Ponta 7 | B83: 23 | C83: capitulo8.tex | D83: <<ConsumoPontaSete>> | E83: =IFERROR(UC_DADOS!E43,0) -> 50.19
A84: Consumo Ponta 8 | B84: 23 | C84: capitulo8.tex | D84: <<ConsumoPontaOito>> | E84: =IFERROR(UC_DADOS!E44,0) -> 82.92
A85: Consumo Ponta 9 | B85: 23 | C85: capitulo8.tex | D85: <<ConsumoPontaNove>> | E85: =IFERROR(UC_DADOS!E45,0) -> 0
A86: Consumo Ponta 10 | B86: 23 | C86: capitulo8.tex | D86: <<ConsumoPontaDez>> | E86: =IFERROR(UC_DADOS!E46,0) -> 0
A87: Consumo Ponta 11 | B87: 23 | C87: capitulo8.tex | D87: <<ConsumoPontaOnze>> | E87: =IFERROR(UC_DADOS!E47,0) -> 0
A88: Consumo Ponta 12 | B88: 23 | C88: capitulo8.tex | D88: <<ConsumoPontaDoze>> | E88: =IFERROR(UC_DADOS!E48,0) -> 0
A89: Consumo Fora Ponta 1 | B89: 23 | C89: capitulo8.tex | D89: <<ConsumoForaPontaUm>> | E89: =IFERROR(UC_DADOS!F37,0) -> 936.03
A90: Consumo Fora Ponta 2 | B90: 23 | C90: capitulo8.tex | D90: <<ConsumoForaPontaDois>> | E90: =IFERROR(UC_DADOS!F38,0) -> 1367.76
A91: Consumo Fora Ponta 3 | B91: 23 | C91: capitulo8.tex | D91: <<ConsumoForaPontaTres>> | E91: =IFERROR(UC_DADOS!F39,0) -> 2113.14
A92: Consumo Fora Ponta 4 | B92: 23 | C92: capitulo8.tex | D92: <<ConsumoForaPontaQuatro>> | E92: =IFERROR(UC_DADOS!F40,0) -> 3172.17
A93: Consumo Fora Ponta 5 | B93: 23 | C93: capitulo8.tex | D93: <<ConsumoForaPontaCinco>> | E93: =IFERROR(UC_DADOS!F41,0) -> 3480.9
A94: Consumo Fora Ponta 6 | B94: 23 | C94: capitulo8.tex | D94: <<ConsumoForaPontaSeis>> | E94: =IFERROR(UC_DADOS!F42,0) -> 2788.41
A95: Consumo Fora Ponta 7 | B95: 23 | C95: capitulo8.tex | D95: <<ConsumoForaPontaSete>> | E95: =IFERROR(UC_DADOS!F43,0) -> 997.53
A96: Consumo Fora Ponta 8 | B96: 23 | C96: capitulo8.tex | D96: <<ConsumoForaPontaOito>> | E96: =IFERROR(UC_DADOS!F44,0) -> 3281.64
A97: Consumo Fora Ponta 9 | B97: 23 | C97: capitulo8.tex | D97: <<ConsumoForaPontaNove>> | E97: =IFERROR(UC_DADOS!F45,0) -> 0
A98: Consumo Fora Ponta 10 | B98: 23 | C98: capitulo8.tex | D98: <<ConsumoForaPontaDez>> | E98: =IFERROR(UC_DADOS!F46,0) -> 0
A99: Consumo Fora Ponta 11 | B99: 23 | C99: capitulo8.tex | D99: <<ConsumoForaPontaOnze>> | E99: =IFERROR(UC_DADOS!F47,0) -> 0
A100: Consumo Fora Ponta 12 | B100: 23 | C100: capitulo8.tex | D100: <<ConsumoForaPontaDoze>> | E100: =IFERROR(UC_DADOS!F48,0) -> 0
...

Sheet FATURAS
A1: id_fatura | B1: status_pagamento | C1: status_leitura | D1: nome_empresa_cliente | E1: valor_total_em_reais | F1: nome_uc | G1: tipo_uc | H1: nome_grupo_uc | I1: tipo_instalacao | J1: nome_distribuidora_energia | K1: data_emissao | L1: data_vencimento | M1: periodo_referencia | N1: proxima_leitura_fatura | O1: leitura_atual_fatura | P1: ultima_leitura_fatura | Q1: numero_dias | R1: consumo_minimo | S1: id_ultima_fatura | T1: periodo_referencia_ultima_fatura | U1: demanda_contratada | V1: demanda_contratada_ponta | W1: demanda_contratada_fora_ponta | X1: nome_classe | Y1: descricao_classe | Z1: tipo_fornecimento | AA1: codigo_cliente | AB1: codigo_instalacao | AC1: consumo_total | AD1: consumo_total_com_perda_transformacao | AE1: consumo_compensado_total | AF1: consumo_faturado_total | AG1: energia_total_injetada | AH1: consumo_ponta | AI1: consumo_ponta_com_perda_transformacao | AJ1: consumo_fora_ponta | AK1: consumo_fora_ponta_com_perda_transformacao | AL1: consumo_intermediario | AM1: consumo_intermediario_com_perda_transformacao | AN1: consumo_compensado_ponta | AO1: consumo_compensado_fora_ponta | AP1: consumo_compensado_intermediário | AQ1: consumo_faturado_ponta | AR1: consumo_faturado_fora_ponta | AS1: consumo_faturado_intermediario | AT1: demanda_maxima | AU1: demanda_maxima_ponta | AV1: demanda_maxima_fora_ponta | AW1: demanda_de_ultrapassagem | AX1: demanda_de_ultrapassagem_ponta | AY1: demanda_de_ultrapassagem_fora_ponta | AZ1: demanda_faturada | BA1: demanda_faturada_ponta | BB1: demanda_faturada_fora_ponta | BC1: consumo_reativo_total | BD1: consumo_reativo_ponta | BE1: consumo_reativo_fora_ponta | BF1: consumo_reativo_excedente_total | BG1: consumo_reativo_excedente_ponta | BH1: consumo_reativo_excedente_fora_ponta | BI1: demanda_reativa_excedente | BJ1: demanda_reativa_excedente_ponta | BK1: demanda_reativa_excedente_fora_ponta | BL1: fator_carga_ponta | BM1: fator_carga_fora_ponta | BN1: percentual_perda_transformacao | BO1: creditos_acumulados_anterior | BP1: creditos_acumulados | BQ1: movimentacao_creditos_mes | BR1: tarifa_consumo_ponta | BS1: tarifa_consumo_fora_ponta | BT1: tarifa_consumo_intermediario | BU1: tarifa_consumo_convencional | BV1: tarifa_demanda_maxima | BW1: tarifa_demanda_de_ultrapassagem | BX1: tarifa_demanda_de_ultrapassagem_ponta | BY1: tarifa_demanda_de_ultrapassagem_fora_ponta | BZ1: tarifa_demanda_maxima_ponta | CA1: tarifa_demanda_maxima_fora_ponta | CB1: tarifa_consumo_reativo_excedente | CC1: tarifa_demanda_reativa_excedente | CD1: tarifa_calculada_demanda_ultrapassada | CE1: tarifa_calculada_demanda_de_ultrapassagem_ponta | CF1: tarifa_calculada_demanda_de_ultrapassagem_fora_ponta | CG1: tarifa_efetiva_de_consumo | CH1: valor_total_icms | CI1: base_calculo_icms | CJ1: aliquota_icms | CK1: valor_total_pis | CL1: base_calculo_pis | CM1: aliquota_pis | CN1: valor_total_cofins | CO1: base_calculo_cofins | CP1: aliquota_cofins | CQ1: numero_nota_fiscal | CR1: url_nota_fiscal | CS1: chave_acesso_nota_fiscal | CT1: arquivo_anexo | CU1: potencial_de_economia_mensal | CV1: potencial_de_economia_anual | CW1: potencial_de_economia_12_meses
A2: efd0aaeb-5a6f-4882-94c5-f68fdc24c33f | B2: Pendente | C2: Sucesso | D2: Prefeitura de Salvador | E2: 4707.45 | F2: MUNICIPIO DE SALVADOR 744 CMEI OLGA BENARIO | G2: Consumidora | H2: - | I2: - | J2: Neoenergia Coelba - Bahia | K2: 46140 | L2: 46170 | M2: 46082 | N2: 46142 | O2: 46112 | P2: 46081 | Q2: 31 | R2: 0 | S2: - | T2: - | U2: 80 | V2: - | W2: - | X2: Alta Tensão - Verde | Y2: A4 Horo-sazonal Verde PODER PUBLICO MUNICIPAL | Z2: Trifásico | AA2: 7041435180 | AB2: 11039337 | AC2: 3282.5 | AD2: 3364.57 | AE2: 0 | AF2: 3364.56 | AG2: - | AH2: 80.9 | AI2: 82.93 | AJ2: 3201.6 | AK2: 3281.64 | AL2: - | AM2: - | AN2: 0 | AO2: 0 | AP2: - | AQ2: 82.92 | AR2: 3281.64 | AS2: - | AT2: 34.08 | AU2: 2.3 | AV2: 34.08 | AW2: 0 | AX2: - | AY2: - | AZ2: 80 | BA2: - | BB2: - | BC2: 0 | BD2: 0 | BE2: 0 | BF2: 82.41 | BG2: 0 | BH2: 82.41 | BI2: 0 | BJ2: - | BK2: - | BL2: 0.53 | BM2: 0.14 | BN2: 2.5 | BO2: - | BP2: - | BQ2: - | BR2: 3.3227706 | BS2: 0.38957284 | BT2: - | BU2: - | BV2: 41.333904 | BW2: - | BX2: - | BY2: - | BZ2: - | CA2: - | CB2: 0.29679905 | CC2: 41.333904 | CD2: 82.667809 | CE2: - | CF2: - | CG2: 0.46186399 | CH2: 0 | CI2: 0 | CJ2: 0.205 | CK2: 57.15 | CL2: 4885.11 | CM2: 0.0117 | CN2: 264.77 | CO2: 4885.11 | CP2: 0.0542 | CQ2: 958129091 | CR2: https://dfe-portal.svrs.rs.gov.br/Nf3e/consulta | CS2: 2926 0415 1396 2900 0194 6600 0958 1290 9110 6404 5386 | CT2: collective-invoice-deea8a88-456f-4091-a6e6-d5784cc86269-35.pdf | CU2: 0 | CV2: 0 | CW2: 0
A3: 837ac22a-067c-4438-a24a-7b6f34bf5707 | B3: Em atraso | C3: Sucesso | D3: Prefeitura de Salvador | E3: 3697.51 | F3: MUNICIPIO DE SALVADOR 744 CMEI OLGA BENARIO | G3: Consumidora | H3: - | I3: - | J3: Neoenergia Coelba - Bahia | K3: 46108 | L3: 46140 | M3: 46054 | N3: 46112 | O3: 46081 | P3: 46053 | Q3: 28 | R3: 0 | S3: - | T3: - | U3: 80 | V3: - | W3: - | X3: Alta Tensão - Verde | Y3: A4 Horo-sazonal Verde PODER PUBLICO MUNICIPAL | Z3: Trifásico | AA3: 7041435180 | AB3: 11039337 | AC3: 1022.17 | AD3: 1047.73 | AE3: 0 | AF3: 1047.72 | AG3: - | AH3: 48.97 | AI3: 50.2 | AJ3: 973.2 | AK3: 997.53 | AL3: - | AM3: - | AN3: 0 | AO3: 0 | AP3: - | AQ3: 50.19 | AR3: 997.53 | AS3: - | AT3: 11.71 | AU3: 1.2 | AV3: 11.71 | AW3: 0 | AX3: - | AY3: - | AZ3: 80 | BA3: - | BB3: - | BC3: 0 | BD3: 0 | BE3: 0 | BF3: 109.47 | BG3: 0 | BH3: 109.47 | BI3: 0 | BJ3: - | BK3: - | BL3: 0.76 | BM3: 0.13 | BN3: 2.5 | BO3: - | BP3: - | BQ3: - | BR3: 3.2949045 | BS3: 0.38630572 | BT3: - | BU3: - | BV3: 40.987261 | BW3: - | BX3: - | BY3: - | BZ3: - | CA3: - | CB3: 0.29430997 | CC3: 40.987261 | CD3: 81.974522 | CE3: - | CF3: - | CG3: 0.52565053 | CH3: 0 | CI3: 0 | CJ3: 0.205 | CK3: 39.77 | CL3: 3861.9 | CM3: 0.0103 | CN3: 184.21 | CO3: 3861.9 | CP3: 0.0477 | CQ3: 950416389 | CR3: https://dfe-portal.svrs.rs.gov.br/Nf3e/consulta | CS3: 2926 0315 1396 2900 0194 6600 0950 4163 8910 8451 8124 | CT3: collective-invoice-12601260-bf07-4e7f-b254-7e6122f0dd9f-25.pdf | CU3: 1917.61 | CV3: 3808.37 | CW3: 3808.37
A4: 8e6595e3-396c-4675-8e1b-22789a865feb | B4: Em atraso | C4: Sucesso | D4: Prefeitura de Salvador | E4: 4517.9 | F4: MUNICIPIO DE SALVADOR 744 CMEI OLGA BENARIO | G4: Consumidora | H4: - | I4: - | J4: Neoenergia Coelba - Bahia | K4: 46079 | L4: 46111 | M4: 46023 | N4: 46081 | O4: 46053 | P4: 46022 | Q4: 31 | R4: 0 | S4: - | T4: - | U4: 80 | V4: - | W4: - | X4: Alta Tensão - Verde | Y4: A4 Horo-sazonal Verde PODER PUBLICO PUBLICO | Z4: Trifásico | AA4: 7041435180 | AB4: 11039337 | AC4: 2804.63 | AD4: 2874.74 | AE4: 0 | AF4: 2874.75 | AG4: - | AH4: 84.23 | AI4: 86.33 | AJ4: 2720.4 | AK4: 2788.41 | AL4: - | AM4: - | AN4: 0 | AO4: 0 | AP4: - | AQ4: 86.34 | AR4: 2788.41 | AS4: - | AT4: 33.98 | AU4: 2.69 | AV4: 33.98 | AW4: 0 | AX4: - | AY4: - | AZ4: 80 | BA4: - | BB4: - | BC4: 0 | BD4: 0 | BE4: 0 | BF4: 104.55 | BG4: 0 | BH4: 104.55 | BI4: 0 | BJ4: - | BK4: - | BL4: 0.5 | BM4: 0.12 | BN4: 2.5 | BO4: - | BP4: - | BQ4: - | BR4: 3.3100138 | BS4: 0.3880772 | BT4: - | BU4: - | BV4: 41.175216 | BW4: - | BX4: - | BY4: - | BZ4: - | CA4: - | CB4: 0.29565959 | CC4: 41.175216 | CD4: 82.350432 | CE4: - | CF4: - | CG4: 0.47583021 | CH4: 0 | CI4: 0 | CJ4: 0.205 | CK4: 52.09 | CL4: 4692.8 | CM4: 0.0111 | CN4: 240.27 | CO4: 4692.8 | CP4: 0.0512 | CQ4: 942948518 | CR4: https://dfe-portal.svrs.rs.gov.br/Nf3e/consulta | CS4: 2926 0215 1396 2900 0194 6600 0942 9485 1810 0630 5937 | CT4: collective-invoice-daced704-b68a-4dd6-8470-e22789ce44ea-15.pdf | CU4: 1842.59 | CV4: 1842.59 | CW4: 1842.59
A5: 2f4256a8-45ef-440c-bfb5-5d569ca2fd29 | B5: Em atraso | C5: Sucesso | D5: Prefeitura de Salvador | E5: 4873.8 | F5: MUNICIPIO DE SALVADOR 744 CMEI OLGA BENARIO | G5: Consumidora | H5: - | I5: - | J5: Neoenergia Coelba - Bahia | K5: 46051 | L5: 46083 | M5: 45992 | N5: 46053 | O5: 46022 | P5: 45991 | Q5: 31 | R5: 0 | S5: - | T5: - | U5: 80 | V5: - | W5: - | X5: Alta Tensão - Verde | Y5: A4 Horo-sazonal Verde PODER PUBLICO MUNICIPAL | Z5: Trifásico | AA5: 7041435180 | AB5: 11039337 | AC5: 3476.05 | AD5: 3562.95 | AE5: 0 | AF5: 3562.95 | AG5: - | AH5: 80.05 | AI5: 82.05 | AJ5: 3396 | AK5: 3480.9 | AL5: - | AM5: - | AN5: 0 | AO5: 0 | AP5: - | AQ5: 82.05 | AR5: 3480.9 | AS5: - | AT5: 33.22 | AU5: 2.3 | AV5: 33.22 | AW5: 0 | AX5: - | AY5: - | AZ5: 80 | BA5: - | BB5: - | BC5: 0 | BD5: 0 | BE5: 0 | BF5: 138 | BG5: 0 | BH5: 138 | BI5: 0 | BJ5: - | BK5: - | BL5: 0.53 | BM5: 0.15 | BN5: 2.5 | BO5: - | BP5: - | BQ5: - | BR5: 3.3458159 | BS5: 0.41010392 | BT5: - | BU5: - | BV5: 41.369335 | BW5: - | BX5: - | BY5: - | BZ5: - | CA5: - | CB5: 0.29705346 | CC5: 41.369335 | CD5: 82.738669 | CE5: - | CF5: - | CG5: 0.47771047 | CH5: 0 | CI5: 0 | CJ5: 0.205 | CK5: 60.13 | CL5: 5053.59 | CM5: 0.0119 | CN5: 276.93 | CO5: 5053.59 | CP5: 0.0548 | CQ5: 935272040 | CR5: https://dfe-portal.svrs.rs.gov.br/Nf3e/consulta | CS5: 2926 0115 1396 2900 0194 6600 0935 2720 4010 3357 0648 | CT5: collective-invoice-7b320f96-ced8-4aaa-9885-ebb0fb4b5884-25.pdf | CU5: 1850.82 | CV5: 6895.52 | CW5: 6895.52
A6: d322cff7-3df0-46fd-ba6d-c3350bb8d5ab | B6: Em atraso | C6: Sucesso | D6: Prefeitura de Salvador | E6: 4877.45 | F6: MUNICIPIO DE SALVADOR 744 CMEI OLGA BENARIO | G6: Consumidora | H6: - | I6: - | J6: Neoenergia Coelba - Bahia | K6: 46020 | L6: 46050 | M6: 45962 | N6: 46022 | O6: 45991 | P6: 45961 | Q6: 30 | R6: 0 | S6: - | T6: - | U6: 80 | V6: - | W6: - | X6: Alta Tensão - Verde | Y6: A4 Horo-sazonal Verde PODER PUBLICO MUNICIPAL | Z6: Trifásico | AA6: 7041435180 | AB6: 11039337 | AC6: 3167.94 | AD6: 3247.14 | AE6: 0 | AF6: 3247.14 | AG6: - | AH6: 73.14 | AI6: 74.97 | AJ6: 3094.8 | AK6: 3172.17 | AL6: - | AM6: - | AN6: 0 | AO6: 0 | AP6: - | AQ6: 74.97 | AR6: 3172.17 | AS6: - | AT6: 34.37 | AU6: 2.11 | AV6: 34.37 | AW6: 0 | AX6: - | AY6: - | AZ6: 80 | BA6: - | BB6: - | BC6: 0 | BD6: 0 | BE6: 0 | BF6: 186.96 | BG6: 0 | BH6: 186.96 | BI6: 0 | BJ6: - | BK6: - | BL6: 0.61 | BM6: 0.14 | BN6: 2.5 | BO6: - | BP6: - | BQ6: - | BR6: 3.4084984 | BS6: 0.44227562 | BT6: - | BU6: - | BV6: 41.799285 | BW6: - | BX6: - | BY6: - | BZ6: - | CA6: - | CB6: 0.30014073 | CC6: 41.799285 | CD6: 83.598571 | CE6: - | CF6: - | CG6: 0.51075846 | CH6: 0 | CI6: 0 | CJ6: 0.205 | CK6: 68.79 | CL6: 5058.54 | CM6: 0.0136 | CN6: 317.17 | CO6: 5058.54 | CP6: 0.0627 | CQ6: 927319924 | CR6: https://dfe-portal.svrs.rs.gov.br/Nf3e/consulta | CS6: 2925 1215 1396 2900 0194 6600 0927 3199 2410 4836 4427 | CT6: collective-invoice-04e96beb-34a5-455b-8925-28e515dab6e7-16.pdf | CU6: 2010.35 | CV6: 5044.7 | CW6: 5044.7
A7: 92da71dc-128d-4227-9458-1c77a714807c | B7: Em atraso | C7: Sucesso | D7: Prefeitura de Salvador | E7: 4412.8 | F7: MUNICIPIO DE SALVADOR 744 CMEI OLGA BENARIO | G7: Consumidora | H7: - | I7: - | J7: Neoenergia Coelba - Bahia | K7: 45988 | L7: 46020 | M7: 45931 | N7: 45991 | O7: 45961 | P7: 45930 | Q7: 31 | R7: 0 | S7: - | T7: - | U7: 80 | V7: - | W7: - | X7: Alta Tensão - Verde | Y7: A4 Horo-sazonal Verde PODER PUBLICO MUNICIPAL | Z7: Trifásico | AA7: 7041435180 | AB7: 11039337 | AC7: 2151.49 | AD7: 2205.28 | AE7: 0 | AF7: 2205.28 | AG7: - | AH7: 89.89 | AI7: 92.14 | AJ7: 2061.6 | AK7: 2113.14 | AL7: - | AM7: - | AN7: 0 | AO7: 0 | AP7: - | AQ7: 92.14 | AR7: 2113.14 | AS7: - | AT7: 29.23 | AU7: 2.54 | AV7: 29.23 | AW7: 0 | AX7: - | AY7: - | AZ7: 80 | BA7: - | BB7: - | BC7: 469.39 | BD7: 42.19 | BE7: 427.2 | BF7: 96.8 | BG7: 9.47 | BH7: 87.33 | BI7: 0 | BJ7: - | BK7: - | BL7: 0.51 | BM7: 0.1 | BN7: 2.5 | BO7: - | BP7: - | BQ7: - | BR7: 3.3832259 | BS7: 0.43899634 | BT7: - | BU7: - | BV7: 41.489362 | BW7: - | BX7: - | BY7: - | BZ7: - | CA7: - | CB7: 0.29791532 | CC7: 41.489362 | CD7: 82.978723 | CE7: - | CF7: - | CG7: 0.56200727 | CH7: 0 | CI7: 0 | CJ7: 0.205 | CK7: 56.88 | CL7: 4587.34 | CM7: 0.0124 | CN7: 261.47 | CO7: 4587.34 | CP7: 0.057 | CQ7: 919897917 | CR7: https://dfe-portal.svrs.rs.gov.br/Nf3e/consulta | CS7: 2925 1115 1396 2900 0194 6600 0919 8979 1710 7891 5848 | CT7: collective-invoice-f044ebe1-ba65-449c-a53f-a4be3e0b6f2d-19.pdf | CU7: 2167.54 | CV7: 4260.78 | CW7: 4260.78
A8: 27c161b1-fce1-41c6-98a7-d1c850a87e70 | B8: Em atraso | C8: Sucesso | D8: Prefeitura de Salvador | E8: 4004.54 | F8: MUNICIPIO DE SALVADOR 744 CMEI OLGA BENARIO | G8: Consumidora | H8: - | I8: - | J8: Neoenergia Coelba - Bahia | K8: 45897 | L8: 45929 | M8: 45839 | N8: 45900 | O8: 45869 | P8: 45838 | Q8: 31 | R8: 0 | S8: - | T8: - | U8: 80 | V8: - | W8: - | X8: Alta Tensão - Verde | Y8: A4 Horo-sazonal Verde PODER PUBLICO MUNICIPAL | Z8: Trifásico | AA8: 7041435180 | AB8: 11039337 | AC8: 1408.27 | AD8: 1443.48 | AE8: 0 | AF8: 1443.48 | AG8: - | AH8: 73.87 | AI8: 75.72 | AJ8: 1334.4 | AK8: 1367.76 | AL8: - | AM8: - | AN8: 0 | AO8: 0 | AP8: - | AQ8: 75.72 | AR8: 1367.76 | AS8: - | AT8: 25.97 | AU8: 1.58 | AV8: 25.97 | AW8: 0 | AX8: - | AY8: - | AZ8: 80 | BA8: - | BB8: - | BC8: 731.51 | BD8: 67.91 | BE8: 663.6 | BF8: 89.54 | BG8: 18.2 | BH8: 71.34 | BI8: 0 | BJ8: - | BK8: - | BL8: 0.68 | BM8: 0.08 | BN8: 2.5 | BO8: - | BP8: - | BQ8: - | BR8: 3.3597588 | BS8: 0.43595133 | BT8: - | BU8: - | BV8: 41.201579 | BW8: - | BX8: - | BY8: - | BZ8: - | CA8: - | CB8: 0.29584889 | CC8: 41.201579 | CD8: 82.403159 | CE8: - | CF8: - | CG8: 0.58931799 | CH8: 0 | CI8: 0 | CJ8: 0.205 | CK8: 47.15 | CL8: 4173.26 | CM8: 0.0113 | CN8: 215.34 | CO8: 4173.26 | CP8: 0.0516 | CQ8: 897725540 | CR8: https://dfe-portal.svrs.rs.gov.br/Nf3e/consulta | CS8: 2925 0815 1396 2900 0194 6600 0897 7255 4010 5396 8812 | CT8: collective-invoice-b190c713-d90a-47e1-a98e-3287700ea656-15.pdf | CU8: 2237.68 | CV8: 0 | CW8: 0
A9: d7800376-f027-41fe-a21e-e0f0d067ca41 | B9: Em atraso | C9: Sucesso | D9: Prefeitura de Salvador | E9: 1726.23 | F9: MUNICIPIO DE SALVADOR 744 CMEI OLGA BENARIO | G9: Consumidora | H9: - | I9: - | J9: Neoenergia Coelba - Bahia | K9: 45834 | L9: 45866 | M9: 45778 | N9: 45838 | O9: 45808 | P9: 45777 | Q9: 31 | R9: 0 | S9: - | T9: - | U9: 80 | V9: - | W9: - | X9: Alta Tensão - Verde | Y9: A4 Horo-sazonal Verde PODER PUBLICO MUNICIPAL | Z9: Trifásico | AA9: 7041435180 | AB9: 11039337 | AC9: 972.29 | AD9: 996.6 | AE9: 0 | AF9: 996.6 | AG9: - | AH9: 59.09 | AI9: 60.57 | AJ9: 913.2 | AK9: 936.03 | AL9: - | AM9: - | AN9: 0 | AO9: 0 | AP9: - | AQ9: 60.57 | AR9: 936.03 | AS9: - | AT9: 14.45 | AU9: 2.21 | AV9: 14.45 | AW9: 0 | AX9: - | AY9: - | AZ9: 30 | BA9: - | BB9: - | BC9: 708.1 | BD9: 63.7 | BE9: 644.4 | BF9: 0 | BG9: 0 | BH9: 0 | BI9: 0 | BJ9: - | BK9: - | BL9: 0.42 | BM9: 0.09 | BN9: 2.5 | BO9: - | BP9: - | BQ9: - | BR9: 3.27975 | BS9: 0.40200608 | BT9: - | BU9: - | BV9: 40.552463 | BW9: - | BX9: - | BY9: - | BZ9: - | CA9: - | CB9: 0.2911879 | CC9: 40.552463 | CD9: 81.104926 | CE9: - | CF9: - | CG9: 0.57689823 | CH9: 0 | CI9: 0 | CJ9: 0.205 | CK9: 15.4 | CL9: 1791.5 | CM9: 0.0086 | CN9: 70.4 | CO9: 1791.5 | CP9: 0.0393 | CQ9: 882088156 | CR9: https://dfe-portal.svrs.rs.gov.br/Nf3e/consulta | CS9: 2925 0615 1396 2900 0194 5610 | CT9: collective-invoice-ca7fdeb6-dc41-433e-ba48-909609345d55-22.pdf | CU9: 587.45 | CV9: 0 | CW9: 0

Sheet UC_DADOS
A1: Nome da Unidade | B1: =_xlfn.XLOOKUP(MAX(FATURAS!M:M), FATURAS!M:M, FATURAS!F:F,,-1) -> MUNICIPIO DE SALVADOR 744 CMEI OLGA BENARIO
A2: Código da UC | B2: =_xlfn.XLOOKUP(MAX(FATURAS!M:M), FATURAS!M:M, FATURAS!AA:AA,,-1) -> 7041435180
A3: Tipo de Atividade | B3: Escola
A4: Endereço Completo | B4: Rua Fernando São Paulo, Dóron
A5: Localidade | B5: Dóron, Salvador-BA
A6: Responsável / Cargo | B6: Silvia
A7: Telefone para Contato | B7: 71 9935-2628
A8: Data | B8: 46086
A9: E-mail institucional | B9: educacao@prefs.com.br
A12: Alunos | B12: 275
A13: Consumo médio mensal (kWh/mês) | B13: =AVERAGE(FATURAS!AF:AF) -> 2342.81
A14: Consumo específico estimado | B14: =(B13/B12) -> 8.5193091
A18: Modalidade tarifária | B18: =_xlfn.XLOOKUP(MAX(FATURAS!M:M), FATURAS!M:M, FATURAS!X:X,,-1) -> Alta Tensão - Verde
A19: Demanda contratada | B19: =_xlfn.XLOOKUP(MAX(FATURAS!M:M), FATURAS!M:M, FATURAS!U:U,,-1) -> 80
A20: Número da instalação na distribuidora | B20: =_xlfn.XLOOKUP(MAX(FATURAS!M:M),FATURAS!M:M,FATURAS!AB:AB) -> 11039337
A21: Código da unidade consumidora | B21: =B2 -> 7041435180
A22: Classe de consumo | B22: =_xlfn.XLOOKUP(MAX(FATURAS!M:M), FATURAS!M:M, FATURAS!Y:Y,,-1) -> A4 Horo-sazonal Verde PODER PUBLICO MUNICIPAL
A28: Resnposável Técnico | B28: Luiz Carlos Alves Lima
A29: Grupo | B29: =IF(LEFT(B22,1)="A","Grupo A",IF(LEFT(B22,1)="B","Grupo B","")) -> Grupo A
A32: Preço da Energia do Ultimo Mês | B32: =SUMIF(FATURAS!M:M,MAX(FATURAS!M:M),FATURAS!E:E) -> 4707.45
A33: Distribuidora de Energia | B33: =FATURAS!J2 -> Neoenergia Coelba - Bahia
A34: Maior Consumo Registrado (kWh) | B34: =MAX(G37:G48) -> 3562.95
A35: Mês/Ano do Maior Consumo | B35: =INDEX(D37:D48,MATCH(MAX(G37:G48),G37:G48,0)) -> dez/25
A36: Mês/Ano do Menor Consumo | B36: =INDEX(D37:D48,MATCH(MIN(G37:G48),G37:G48,0)) -> Sem Histórico Disponível | D36: Mês / Ano | E36: Consumo Ponta (kWh) | F36: Consumo Fora Ponta (kWh) | G36: Consumo Total (kW) | H36: Demanda Ponta (kW) | I36: Demanda Fora Ponta (kW)
A37: Custo anual de energia elétrica (R$) | B37: =SUMIFS(FATURAS!E:E,FATURAS!M:M,">="&DATE(YEAR(TODAY()),1,1),FATURAS!M:M,"<="&DATE(YEAR(TODAY()),12,31)) -> 12922.86 | D37: =IFERROR(TEXT(SMALL(_xlfn.UNIQUE(FATURAS!M:M),1),"MMM/AA"),"") -> mai/25 | E37: =SUMIFS(FATURAS!AQ:AQ, FATURAS!M:M, SMALL(_xlfn.UNIQUE(FATURAS!M:M),1)) -> 60.57 | F37: =SUMIFS(FATURAS!AR:AR, FATURAS!M:M, SMALL(_xlfn.UNIQUE(FATURAS!M:M),1)) -> 936.03 | G37: =SUM(E37+F37) -> 996.6 | H37: {=SUMPRODUCT( (FATURAS!M2:M5000=SMALL(_xlfn.UNIQUE(FATURAS!M2:M5000),1))* FATURAS!AU2:AU5000* IF(ISNUMBER(FATURAS!BN2:BN5000),1+(FATURAS!BN2:BN5000/100),1))} -> 2.26525 | I37: {=SUMPRODUCT((FATURAS!M2:M5000=SMALL(_xlfn.UNIQUE(FATURAS!M2:M5000),1))*FATURAS!AV2:AV5000*IF(ISNUMBER(FATURAS!BN2:BN5000),1+(FATURAS!BN2:BN5000/100),1))} -> 14.81125
A38: Fator de carga médio estimado | B38: {=IFERROR(SUMPRODUCT(IFERROR(FATURAS!AD2:AD13/(FATURAS!AV2:AV13*FATURAS!Q2:Q13*24),0))/SUMPRODUCT((FATURAS!AV2:AV13<>0)*(FATURAS!Q2:Q13<>0)),0)} -> 0.11546735 | D38: =IFERROR(TEXT(SMALL(_xlfn.UNIQUE(FATURAS!M:M),2),"MMM/AA"),"") -> jul/25 | E38: =SUMIFS(FATURAS!AQ:AQ, FATURAS!M:M, SMALL(_xlfn.UNIQUE(FATURAS!M:M),2)) -> 75.72 | F38: =SUMIFS(FATURAS!AR:AR, FATURAS!M:M, SMALL(_xlfn.UNIQUE(FATURAS!M:M),2)) -> 1367.76 | G38: =SUM(E38+F38) -> 1443.48 | H38: {=SUMPRODUCT( (FATURAS!M2:M5000=SMALL(_xlfn.UNIQUE(FATURAS!M2:M5000),2))* FATURAS!AU2:AU5000* IF(ISNUMBER(FATURAS!BN2:BN5000),1+(FATURAS!BN2:BN5000/100),1))} -> 1.6195 | I38: {=SUMPRODUCT((FATURAS!M2:M5000=SMALL(_xlfn.UNIQUE(FATURAS!M2:M5000),2))*FATURAS!AV2:AV5000*IF(ISNUMBER(FATURAS!BN2:BN5000),1+(FATURAS!BN2:BN5000/100),1))} -> 26.61925
A39: Faturas Disponíveis | B39: Ausência de faturas no período dos últimos 12 meses analisados | D39: =IFERROR(TEXT(SMALL(_xlfn.UNIQUE(FATURAS!M:M),3),"MMM/AA"),"") -> out/25 | E39: =SUMIFS(FATURAS!AQ:AQ, FATURAS!M:M, SMALL(_xlfn.UNIQUE(FATURAS!M:M),3)) -> 92.14 | F39: =SUMIFS(FATURAS!AR:AR, FATURAS!M:M, SMALL(_xlfn.UNIQUE(FATURAS!M:M),3)) -> 2113.14 | G39: =SUM(E39+F39) -> 2205.28 | H39: {=SUMPRODUCT( (FATURAS!M2:M5000=SMALL(_xlfn.UNIQUE(FATURAS!M2:M5000),3))* FATURAS!AU2:AU5000* IF(ISNUMBER(FATURAS!BN2:BN5000),1+(FATURAS!BN2:BN5000/100),1))} -> 2.6035 | I39: {=SUMPRODUCT((FATURAS!M2:M5000=SMALL(_xlfn.UNIQUE(FATURAS!M2:M5000),3))*FATURAS!AV2:AV5000*IF(ISNUMBER(FATURAS!BN2:BN5000),1+(FATURAS!BN2:BN5000/100),1))} -> 29.96075
D40: =IFERROR(TEXT(SMALL(_xlfn.UNIQUE(FATURAS!M:M),4),"MMM/AA"),"") -> nov/25 | E40: =SUMIFS(FATURAS!AQ:AQ, FATURAS!M:M, SMALL(_xlfn.UNIQUE(FATURAS!M:M),4)) -> 74.97 | F40: =SUMIFS(FATURAS!AR:AR, FATURAS!M:M, SMALL(_xlfn.UNIQUE(FATURAS!M:M),4)) -> 3172.17 | G40: =SUM(E40+F40) -> 3247.14 | H40: {=SUMPRODUCT( (FATURAS!M2:M5000=SMALL(_xlfn.UNIQUE(FATURAS!M2:M5000),4))* FATURAS!AU2:AU5000* IF(ISNUMBER(FATURAS!BN2:BN5000),1+(FATURAS!BN2:BN5000/100),1))} -> 2.16275 | I40: {=SUMPRODUCT((FATURAS!M2:M5000=SMALL(_xlfn.UNIQUE(FATURAS!M2:M5000),4))*FATURAS!AV2:AV5000*IF(ISNUMBER(FATURAS!BN2:BN5000),1+(FATURAS!BN2:BN5000/100),1))} -> 35.22925
D41: =IFERROR(TEXT(SMALL(_xlfn.UNIQUE(FATURAS!M:M),5),"MMM/AA"),"") -> dez/25 | E41: =SUMIFS(FATURAS!AQ:AQ, FATURAS!M:M, SMALL(_xlfn.UNIQUE(FATURAS!M:M),5)) -> 82.05 | F41: =SUMIFS(FATURAS!AR:AR, FATURAS!M:M, SMALL(_xlfn.UNIQUE(FATURAS!M:M),5)) -> 3480.9 | G41: =SUM(E41+F41) -> 3562.95 | H41: {=SUMPRODUCT( (FATURAS!M2:M5000=SMALL(_xlfn.UNIQUE(FATURAS!M2:M5000),5))* FATURAS!AU2:AU5000* IF(ISNUMBER(FATURAS!BN2:BN5000),1+(FATURAS!BN2:BN5000/100),1))} -> 2.3575 | I41: {=SUMPRODUCT((FATURAS!M2:M5000=SMALL(_xlfn.UNIQUE(FATURAS!M2:M5000),5))*FATURAS!AV2:AV5000*IF(ISNUMBER(FATURAS!BN2:BN5000),1+(FATURAS!BN2:BN5000/100),1))} -> 34.0505
D42: =IFERROR(TEXT(SMALL(_xlfn.UNIQUE(FATURAS!M:M),6),"MMM/AA"),"") -> jan/26 | E42: =SUMIFS(FATURAS!AQ:AQ, FATURAS!M:M, SMALL(_xlfn.UNIQUE(FATURAS!M:M),6)) -> 86.34 | F42: =SUMIFS(FATURAS!AR:AR, FATURAS!M:M, SMALL(_xlfn.UNIQUE(FATURAS!M:M),6)) -> 2788.41 | G42: =SUM(E42+F42) -> 2874.75 | H42: {=SUMPRODUCT( (FATURAS!M2:M5000=SMALL(_xlfn.UNIQUE(FATURAS!M2:M5000),6))* FATURAS!AU2:AU5000* IF(ISNUMBER(FATURAS!BN2:BN5000),1+(FATURAS!BN2:BN5000/100),1))} -> 2.75725 | I42: {=SUMPRODUCT((FATURAS!M2:M5000=SMALL(_xlfn.UNIQUE(FATURAS!M2:M5000),6))*FATURAS!AV2:AV5000*IF(ISNUMBER(FATURAS!BN2:BN5000),1+(FATURAS!BN2:BN5000/100),1))} -> 34.8295
D43: =IFERROR(TEXT(SMALL(_xlfn.UNIQUE(FATURAS!M:M),7),"MMM/AA"),"") -> fev/26 | E43: =SUMIFS(FATURAS!AQ:AQ, FATURAS!M:M, SMALL(_xlfn.UNIQUE(FATURAS!M:M),7)) -> 50.19 | F43: =SUMIFS(FATURAS!AR:AR, FATURAS!M:M, SMALL(_xlfn.UNIQUE(FATURAS!M:M),7)) -> 997.53 | G43: =SUM(E43+F43) -> 1047.72 | H43: {=SUMPRODUCT( (FATURAS!M2:M5000=SMALL(_xlfn.UNIQUE(FATURAS!M2:M5000),7))* FATURAS!AU2:AU5000* IF(ISNUMBER(FATURAS!BN2:BN5000),1+(FATURAS!BN2:BN5000/100),1))} -> 1.23 | I43: {=SUMPRODUCT((FATURAS!M2:M5000=SMALL(_xlfn.UNIQUE(FATURAS!M2:M5000),7))*FATURAS!AV2:AV5000*IF(ISNUMBER(FATURAS!BN2:BN5000),1+(FATURAS!BN2:BN5000/100),1))} -> 12.00275
D44: =IFERROR(TEXT(SMALL(_xlfn.UNIQUE(FATURAS!M:M),8),"MMM/AA"),"") -> mar/26 | E44: =SUMIFS(FATURAS!AQ:AQ, FATURAS!M:M, SMALL(_xlfn.UNIQUE(FATURAS!M:M),8)) -> 82.92 | F44: =SUMIFS(FATURAS!AR:AR, FATURAS!M:M, SMALL(_xlfn.UNIQUE(FATURAS!M:M),8)) -> 3281.64 | G44: =SUM(E44+F44) -> 3364.56 | H44: {=SUMPRODUCT( (FATURAS!M2:M5000=SMALL(_xlfn.UNIQUE(FATURAS!M2:M5000),8))* FATURAS!AU2:AU5000* IF(ISNUMBER(FATURAS!BN2:BN5000),1+(FATURAS!BN2:BN5000/100),1))} -> 2.3575 | I44: {=SUMPRODUCT((FATURAS!M2:M5000=SMALL(_xlfn.UNIQUE(FATURAS!M2:M5000),8))*FATURAS!AV2:AV5000*IF(ISNUMBER(FATURAS!BN2:BN5000),1+(FATURAS!BN2:BN5000/100),1))} -> 34.932
D45: Sem Histórico Disponível | E45: =SUMIFS(FATURAS!AQ:AQ, FATURAS!M:M, SMALL(_xlfn.UNIQUE(FATURAS!M:M),9)) -> 0 | F45: =SUMIFS(FATURAS!AR:AR, FATURAS!M:M, SMALL(_xlfn.UNIQUE(FATURAS!M:M),9)) -> 0 | G45: =SUM(E45+F45) -> 0 | H45: {=SUMPRODUCT( (FATURAS!M2:M5000=SMALL(_xlfn.UNIQUE(FATURAS!M2:M5000),9))* FATURAS!AU2:AU5000* IF(ISNUMBER(FATURAS!BN2:BN5000),1+(FATURAS!BN2:BN5000/100),1))} -> #NUM! | I45: {=SUMPRODUCT((FATURAS!M2:M5000=SMALL(_xlfn.UNIQUE(FATURAS!M2:M5000),9))*FATURAS!AV2:AV5000*IF(ISNUMBER(FATURAS!BN2:BN5000),1+(FATURAS!BN2:BN5000/100),1))} -> #NUM!
D46: Sem Histórico Disponível | E46: =SUMIFS(FATURAS!AQ:AQ, FATURAS!M:M, SMALL(_xlfn.UNIQUE(FATURAS!M:M),10)) -> 0 | F46: =SUMIFS(FATURAS!AR:AR, FATURAS!M:M, SMALL(_xlfn.UNIQUE(FATURAS!M:M),10)) -> 0 | G46: =SUM(E46+F46) -> 0 | H46: {=SUMPRODUCT( (FATURAS!M2:M5000=SMALL(_xlfn.UNIQUE(FATURAS!M2:M5000),10))* FATURAS!AU2:AU5000* IF(ISNUMBER(FATURAS!BN2:BN5000),1+(FATURAS!BN2:BN5000/100),1))} -> #NUM! | I46: {=SUMPRODUCT((FATURAS!M2:M5000=SMALL(_xlfn.UNIQUE(FATURAS!M2:M5000),10))*FATURAS!AV2:AV5000*IF(ISNUMBER(FATURAS!BN2:BN5000),1+(FATURAS!BN2:BN5000/100),1))} -> #NUM!
D47: Sem Histórico Disponível | E47: =SUMIFS(FATURAS!AQ:AQ, FATURAS!M:M, SMALL(_xlfn.UNIQUE(FATURAS!M:M),11)) -> 0 | F47: =SUMIFS(FATURAS!AR:AR, FATURAS!M:M, SMALL(_xlfn.UNIQUE(FATURAS!M:M),11)) -> 0 | G47: =SUM(E47+F47) -> 0 | H47: {=SUMPRODUCT( (FATURAS!M2:M5000=SMALL(_xlfn.UNIQUE(FATURAS!M2:M5000),11))* FATURAS!AU2:AU5000* IF(ISNUMBER(FATURAS!BN2:BN5000),1+(FATURAS!BN2:BN5000/100),1))} -> #NUM! | I47: {=SUMPRODUCT((FATURAS!M2:M5000=SMALL(_xlfn.UNIQUE(FATURAS!M2:M5000),11))*FATURAS!AV2:AV5000*IF(ISNUMBER(FATURAS!BN2:BN5000),1+(FATURAS!BN2:BN5000/100),1))} -> #NUM!
D48: Sem Histórico Disponível | E48: =SUMIFS(FATURAS!AQ:AQ, FATURAS!M:M, SMALL(_xlfn.UNIQUE(FATURAS!M:M),12)) -> 0 | F48: =SUMIFS(FATURAS!AR:AR, FATURAS!M:M, SMALL(_xlfn.UNIQUE(FATURAS!M:M),12)) -> 0 | G48: =SUM(E48+F48) -> 0 | H48: {=SUMPRODUCT( (FATURAS!M2:M5000=SMALL(_xlfn.UNIQUE(FATURAS!M2:M5000),12))* FATURAS!AU2:AU5000* IF(ISNUMBER(FATURAS!BN2:BN5000),1+(FATURAS!BN2:BN5000/100),1))} -> #NUM! | I48: {=SUMPRODUCT((FATURAS!M2:M5000=SMALL(_xlfn.UNIQUE(FATURAS!M2:M5000),12))*FATURAS!AV2:AV5000*IF(ISNUMBER(FATURAS!BN2:BN5000),1+(FATURAS!BN2:BN5000/100),1))} -> #NUM!
D49: TOTAIS | G49: =SUM(G37:G48) -> 18742.48
G50: =G49/1000 -> 18.74248

Sheet Sistemas de Cond. Ambiental
A1: UNIDADE CONSUMIDORA | D1: SITUAÇÃO ATUAL | U1: SISTEMA PROPOSTO | AM1: RESULTADOS ESPERADOS | AP1: RESULTADO AUTOMAÇÃO (10%) | AQ1: AUTOMAÇÃO + TROCA DE EQUIPAMENTO
A2: Unidade consumidora (Número da conta contrato) | B2: Pavimento | C2: Ambiente | D2: Descrição do sistema | E2: Tipo de equipamento / tecnologia | F2: Classificação Inmetro | G2: Potência nominal de refrigeração (BTU/h) | H2: Coefiente de eficiência energética (W/W) | I2: Quantidade | J2: Potência instalada (kW) | K2: Fator de utilização | L2: Potência média utilizada (kW) | M2: Funcionamento (h/dia) | N2: Funcionamento (h/ano) | O2: Meses no ano, de utilização do Sistema | P2: Dias úteis no mês, de utilização do Sistema | Q2: Horas por dia, de utilização do Sistema no horário de Ponta (horas) | R2: Fator de coincidência na ponta | S2: Energia consumida (MWh/ano) | T2: Demanda média na ponta (kW) | U2: Tipo de equipamento / tecnologia | V2: Classificação Inmetro | W2: Potência nominal de refrigeração (BTU/h) | X2: Coefiente de eficiência energética (W/W) | Y2: Preço Unitário (R$) | Z2: Quantidade | AA2: Potência instalada (kW) | AB2: Fator de utilização | AC2: Potência média utilizada (kW) | AD2: Funcionamento (h/dia) | AE2: Funcionamento (h/ano) | AF2: Meses no ano, de utilização do Sistema no horário de Ponta (meses) | AG2: Dias úteis no mês, de utilização do Sistema no horário de Ponta (dia) | AH2: Horas por dia, de utilização do Sistema no horário de Ponta (horas) | AI2: Fator de coincidência na ponta | AJ2: Energia consumida (MWh/ano) | AK2: Demanda média na ponta (kW) | AL2: Redução de demanda na ponta (kW) | AM2: Energia economizada (MWh/ano) | AN2: Investimento (R$) | AO2: Redução de consumo proposto em relação ao consumo total da UC (%) | AP2: Energia economizada (MWh/ano) | AQ2: Energia economizada (MWh/ano)
A3: =IF(UC_DADOS!$B$2=0,"",UC_DADOS!$B$2) -> 7041435180 | C3: Secretaria | D3: Argatto | E3: Split Hi-Wall | F3: E | G3: 12000 | H3: 3.5 | I3: 1 | J3: =IF(H3=0,0,((G3*0.293*I3)/(1000*H3))) -> 1.0045714 | K3: 0.7 | L3: =J3*K3 -> 0.7032 | M3: 8 | N3: =M3*O3*P3 -> 2040 | O3: 12 | P3: 21.25 | Q3: 0 | R3: =O3*P3*Q3/765 -> 0 | S3: =N3*L3/1000 -> 1.434528 | T3: =R3*L3 -> 0 | U3: {=IF(F3="A",E3,IFERROR(INDEX('EQUIPAMENTOS_EFICIENTES (BDD)'!G:G,MATCH(1,('EQUIPAMENTOS_EFICIENTES (BDD)'!G:G=E3)*('EQUIPAMENTOS_EFICIENTES (BDD)'!I:I=_xlfn.MINIFS('EQUIPAMENTOS_EFICIENTES (BDD)'!I:I,'EQUIPAMENTOS_EFICIENTES (BDD)'!G:G,E3,'EQUIPAMENTOS_EFICIENTES (BDD)'!I:I,">="&G3)),0)),"Substituição não encontrada"))} -> Split Hi-Wall | V3: {=IF(F3="A",F3,IFERROR(INDEX('EQUIPAMENTOS_EFICIENTES (BDD)'!H:H,MATCH(1,('EQUIPAMENTOS_EFICIENTES (BDD)'!G:G=E3)*('EQUIPAMENTOS_EFICIENTES (BDD)'!I:I=_xlfn.MINIFS('EQUIPAMENTOS_EFICIENTES (BDD)'!I:I,'EQUIPAMENTOS_EFICIENTES (BDD)'!G:G,E3,'EQUIPAMENTOS_EFICIENTES (BDD)'!I:I,">="&G3)),0)),"Substituição não encontrada"))} -> A | W3: {=IF(F3="A",G3,IFERROR(INDEX('EQUIPAMENTOS_EFICIENTES (BDD)'!I:I,MATCH(1,('EQUIPAMENTOS_EFICIENTES (BDD)'!G:G=E3)*('EQUIPAMENTOS_EFICIENTES (BDD)'!I:I=_xlfn.MINIFS('EQUIPAMENTOS_EFICIENTES (BDD)'!I:I,'EQUIPAMENTOS_EFICIENTES (BDD)'!G:G,E3,'EQUIPAMENTOS_EFICIENTES (BDD)'!I:I,">="&G3)),0)),"Substituição não encontrada"))} -> 12000 | X3: {=IF(F3="A",H3,IFERROR(INDEX('EQUIPAMENTOS_EFICIENTES (BDD)'!J:J,MATCH(1,('EQUIPAMENTOS_EFICIENTES (BDD)'!G:G=E3)*('EQUIPAMENTOS_EFICIENTES (BDD)'!I:I=_xlfn.MINIFS('EQUIPAMENTOS_EFICIENTES (BDD)'!I:I,'EQUIPAMENTOS_EFICIENTES (BDD)'!G:G,E3,'EQUIPAMENTOS_EFICIENTES (BDD)'!I:I,">="&G3)),0)),"Substituição não encontrada"))} -> 8.3 | Y3: {=IFERROR(INDEX('EQUIPAMENTOS_EFICIENTES (BDD)'!K:K,MATCH(1,('EQUIPAMENTOS_EFICIENTES (BDD)'!G:G=E3)*('EQUIPAMENTOS_EFICIENTES (BDD)'!I:I=_xlfn.MINIFS('EQUIPAMENTOS_EFICIENTES (BDD)'!I:I,'EQUIPAMENTOS_EFICIENTES (BDD)'!G:G,E3,'EQUIPAMENTOS_EFICIENTES (BDD)'!I:I,">="&G3)),0)),"")} -> 3583 | Z3: =I3 -> 1 | AA3: =IF(X3=0,0,((W3*0.293*Z3)/(1000*X3))) -> 0.42361446 | AB3: =K3 -> 0.7 | AC3: =AA3*AB3 -> 0.29653012 | AD3: =M3 -> 8 | AE3: =N3 -> 2040 | AF3: =O3 -> 12 | AG3: =P3 -> 21.25 | AH3: =Q3 -> 0 | AI3: =R3 -> 0 | AJ3: =AC3*AE3/1000 -> 0.60492145 | AK3: =AI3*AC3 -> 0 | AL3: =T3-AK3 -> 0 | AM3: =S3-AJ3 -> 0.82960655 | AN3: =IF(AM3<>0,Y3*Z3,0) -> 3583 | AO3: =AM3/478.332 -> 0.0017343739 | AP3: =S3*0.9 -> 1.2910752 | AQ3: =AJ3*0.9 -> 0.5444293
A4: =IF(UC_DADOS!$B$2=0,"",UC_DADOS!$B$2) -> 7041435180 | C4: Direção | D4: Argatto | E4: Split Hi-Wall | F4: E | G4: 12000 | H4: 3.5 | I4: 1 | J4: =IF(H4=0,0,((G4*0.293*I4)/(1000*H4))) -> 1.0045714 | K4: 0.7 | L4: =J4*K4 -> 0.7032 | M4: 8 | N4: =M4*O4*P4 -> 2040 | O4: 12 | P4: 21.25 | Q4: 0 | R4: =O4*P4*Q4/765 -> 0 | S4: =N4*L4/1000 -> 1.434528 | T4: =R4*L4 -> 0 | U4: {=IF(F4="A",E4,IFERROR(INDEX('EQUIPAMENTOS_EFICIENTES (BDD)'!G:G,MATCH(1,('EQUIPAMENTOS_EFICIENTES (BDD)'!G:G=E4)*('EQUIPAMENTOS_EFICIENTES (BDD)'!I:I=_xlfn.MINIFS('EQUIPAMENTOS_EFICIENTES (BDD)'!I:I,'EQUIPAMENTOS_EFICIENTES (BDD)'!G:G,E4,'EQUIPAMENTOS_EFICIENTES (BDD)'!I:I,">="&G4)),0)),"Substituição não encontrada"))} -> Split Hi-Wall | V4: {=IF(F4="A",F4,IFERROR(INDEX('EQUIPAMENTOS_EFICIENTES (BDD)'!H:H,MATCH(1,('EQUIPAMENTOS_EFICIENTES (BDD)'!G:G=E4)*('EQUIPAMENTOS_EFICIENTES (BDD)'!I:I=_xlfn.MINIFS('EQUIPAMENTOS_EFICIENTES (BDD)'!I:I,'EQUIPAMENTOS_EFICIENTES (BDD)'!G:G,E4,'EQUIPAMENTOS_EFICIENTES (BDD)'!I:I,">="&G4)),0)),"Substituição não encontrada"))} -> A | W4: {=IF(F4="A",G4,IFERROR(INDEX('EQUIPAMENTOS_EFICIENTES (BDD)'!I:I,MATCH(1,('EQUIPAMENTOS_EFICIENTES (BDD)'!G:G=E4)*('EQUIPAMENTOS_EFICIENTES (BDD)'!I:I=_xlfn.MINIFS('EQUIPAMENTOS_EFICIENTES (BDD)'!I:I,'EQUIPAMENTOS_EFICIENTES (BDD)'!G:G,E4,'EQUIPAMENTOS_EFICIENTES (BDD)'!I:I,">="&G4)),0)),"Substituição não encontrada"))} -> 12000 | X4: {=IF(F4="A",H4,IFERROR(INDEX('EQUIPAMENTOS_EFICIENTES (BDD)'!J:J,MATCH(1,('EQUIPAMENTOS_EFICIENTES (BDD)'!G:G=E4)*('EQUIPAMENTOS_EFICIENTES (BDD)'!I:I=_xlfn.MINIFS('EQUIPAMENTOS_EFICIENTES (BDD)'!I:I,'EQUIPAMENTOS_EFICIENTES (BDD)'!G:G,E4,'EQUIPAMENTOS_EFICIENTES (BDD)'!I:I,">="&G4)),0)),"Substituição não encontrada"))} -> 8.3 | Y4: {=IFERROR(INDEX('EQUIPAMENTOS_EFICIENTES (BDD)'!K:K,MATCH(1,('EQUIPAMENTOS_EFICIENTES (BDD)'!G:G=E4)*('EQUIPAMENTOS_EFICIENTES (BDD)'!I:I=_xlfn.MINIFS('EQUIPAMENTOS_EFICIENTES (BDD)'!I:I,'EQUIPAMENTOS_EFICIENTES (BDD)'!G:G,E4,'EQUIPAMENTOS_EFICIENTES (BDD)'!I:I,">="&G4)),0)),"")} -> 3583 | Z4: =I4 -> 1 | AA4: =IF(X4=0,0,((W4*0.293*Z4)/(1000*X4))) -> 0.42361446 | AB4: =K4 -> 0.7 | AC4: =AA4*AB4 -> 0.29653012 | AD4: =M4 -> 8 | AE4: =N4 -> 2040 | AF4: =O4 -> 12 | AG4: =P4 -> 21.25 | AH4: =Q4 -> 0 | AI4: =R4 -> 0 | AJ4: =AC4*AE4/1000 -> 0.60492145 | AK4: =AI4*AC4 -> 0 | AL4: =T4-AK4 -> 0 | AM4: =S4-AJ4 -> 0.82960655 | AN4: =IF(AM4<>0,Y4*Z4,0) -> 3583 | AO4: =AM4/478.332 -> 0.0017343739 | AP4: =S4*0.9 -> 1.2910752 | AQ4: =AJ4*0.9 -> 0.5444293
A5: =IF(UC_DADOS!$B$2=0,"",UC_DADOS!$B$2) -> 7041435180 | C5: Sala dos professores | D5: Argatto | E5: Split Hi-Wall | F5: E | G5: 12000 | H5: 3.5 | I5: 2 | J5: =IF(H5=0,0,((G5*0.293*I5)/(1000*H5))) -> 2.0091429 | K5: 0.7 | L5: =J5*K5 -> 1.4064 | M5: 4 | N5: =M5*O5*P5 -> 1020 | O5: 12 | P5: 21.25 | Q5: 0 | R5: =O5*P5*Q5/765 -> 0 | S5: =N5*L5/1000 -> 1.434528 | T5: =R5*L5 -> 0 | U5: {=IF(F5="A",E5,IFERROR(INDEX('EQUIPAMENTOS_EFICIENTES (BDD)'!G:G,MATCH(1,('EQUIPAMENTOS_EFICIENTES (BDD)'!G:G=E5)*('EQUIPAMENTOS_EFICIENTES (BDD)'!I:I=_xlfn.MINIFS('EQUIPAMENTOS_EFICIENTES (BDD)'!I:I,'EQUIPAMENTOS_EFICIENTES (BDD)'!G:G,E5,'EQUIPAMENTOS_EFICIENTES (BDD)'!I:I,">="&G5)),0)),"Substituição não encontrada"))} -> Split Hi-Wall | V5: {=IF(F5="A",F5,IFERROR(INDEX('EQUIPAMENTOS_EFICIENTES (BDD)'!H:H,MATCH(1,('EQUIPAMENTOS_EFICIENTES (BDD)'!G:G=E5)*('EQUIPAMENTOS_EFICIENTES (BDD)'!I:I=_xlfn.MINIFS('EQUIPAMENTOS_EFICIENTES (BDD)'!I:I,'EQUIPAMENTOS_EFICIENTES (BDD)'!G:G,E5,'EQUIPAMENTOS_EFICIENTES (BDD)'!I:I,">="&G5)),0)),"Substituição não encontrada"))} -> A | W5: {=IF(F5="A",G5,IFERROR(INDEX('EQUIPAMENTOS_EFICIENTES (BDD)'!I:I,MATCH(1,('EQUIPAMENTOS_EFICIENTES (BDD)'!G:G=E5)*('EQUIPAMENTOS_EFICIENTES (BDD)'!I:I=_xlfn.MINIFS('EQUIPAMENTOS_EFICIENTES (BDD)'!I:I,'EQUIPAMENTOS_EFICIENTES (BDD)'!G:G,E5,'EQUIPAMENTOS_EFICIENTES (BDD)'!I:I,">="&G5)),0)),"Substituição não encontrada"))} -> 12000 | X5: {=IF(F5="A",H5,IFERROR(INDEX('EQUIPAMENTOS_EFICIENTES (BDD)'!J:J,MATCH(1,('EQUIPAMENTOS_EFICIENTES (BDD)'!G:G=E5)*('EQUIPAMENTOS_EFICIENTES (BDD)'!I:I=_xlfn.MINIFS('EQUIPAMENTOS_EFICIENTES (BDD)'!I:I,'EQUIPAMENTOS_EFICIENTES (BDD)'!G:G,E5,'EQUIPAMENTOS_EFICIENTES (BDD)'!I:I,">="&G5)),0)),"Substituição não encontrada"))} -> 8.3 | Y5: {=IFERROR(INDEX('EQUIPAMENTOS_EFICIENTES (BDD)'!K:K,MATCH(1,('EQUIPAMENTOS_EFICIENTES (BDD)'!G:G=E5)*('EQUIPAMENTOS_EFICIENTES (BDD)'!I:I=_xlfn.MINIFS('EQUIPAMENTOS_EFICIENTES (BDD)'!I:I,'EQUIPAMENTOS_EFICIENTES (BDD)'!G:G,E5,'EQUIPAMENTOS_EFICIENTES (BDD)'!I:I,">="&G5)),0)),"")} -> 3583 | Z5: =I5 -> 2 | AA5: =IF(X5=0,0,((W5*0.293*Z5)/(1000*X5))) -> 0.84722892 | AB5: =K5 -> 0.7 | AC5: =AA5*AB5 -> 0.59306024 | AD5: =M5 -> 4 | AE5: =N5 -> 1020 | AF5: =O5 -> 12 | AG5: =P5 -> 21.25 | AH5: =Q5 -> 0 | AI5: =R5 -> 0 | AJ5: =AC5*AE5/1000 -> 0.60492145 | AK5: =AI5*AC5 -> 0 | AL5: =T5-AK5 -> 0 | AM5: =S5-AJ5 -> 0.82960655 | AN5: =IF(AM5<>0,Y5*Z5,0) -> 7166 | AO5: =AM5/478.332 -> 0.0017343739 | AP5: =S5*0.9 -> 1.2910752 | AQ5: =AJ5*0.9 -> 0.5444293
A6: =IF(UC_DADOS!$B$2=0,"",UC_DADOS!$B$2) -> 7041435180 | C6: Salas de aula (01 a 07) | D6: Philco | E6: Split Piso Teto | F6: A | G6: 36000 | H6: 5.5 | I6: 7 | J6: =IF(H6=0,0,((G6*0.293*I6)/(1000*H6))) -> 13.424727 | K6: 0.7 | L6: =J6*K6 -> 9.3973091 | M6: 8 | N6: =M6*O6*P6 -> 1870 | O6: 11 | P6: 21.25 | Q6: 0 | R6: =O6*P6*Q6/765 -> 0 | S6: =N6*L6/1000 -> 17.572968 | T6: =R6*L6 -> 0 | U6: {=IF(F6="A",E6,IFERROR(INDEX('EQUIPAMENTOS_EFICIENTES (BDD)'!G:G,MATCH(1,('EQUIPAMENTOS_EFICIENTES (BDD)'!G:G=E6)*('EQUIPAMENTOS_EFICIENTES (BDD)'!I:I=_xlfn.MINIFS('EQUIPAMENTOS_EFICIENTES (BDD)'!I:I,'EQUIPAMENTOS_EFICIENTES (BDD)'!G:G,E6,'EQUIPAMENTOS_EFICIENTES (BDD)'!I:I,">="&G6)),0)),"Substituição não encontrada"))} -> Split Piso Teto | V6: {=IF(F6="A",F6,IFERROR(INDEX('EQUIPAMENTOS_EFICIENTES (BDD)'!H:H,MATCH(1,('EQUIPAMENTOS_EFICIENTES (BDD)'!G:G=E6)*('EQUIPAMENTOS_EFICIENTES (BDD)'!I:I=_xlfn.MINIFS('EQUIPAMENTOS_EFICIENTES (BDD)'!I:I,'EQUIPAMENTOS_EFICIENTES (BDD)'!G:G,E6,'EQUIPAMENTOS_EFICIENTES (BDD)'!I:I,">="&G6)),0)),"Substituição não encontrada"))} -> A | W6: {=IF(F6="A",G6,IFERROR(INDEX('EQUIPAMENTOS_EFICIENTES (BDD)'!I:I,MATCH(1,('EQUIPAMENTOS_EFICIENTES (BDD)'!G:G=E6)*('EQUIPAMENTOS_EFICIENTES (BDD)'!I:I=_xlfn.MINIFS('EQUIPAMENTOS_EFICIENTES (BDD)'!I:I,'EQUIPAMENTOS_EFICIENTES (BDD)'!G:G,E6,'EQUIPAMENTOS_EFICIENTES (BDD)'!I:I,">="&G6)),0)),"Substituição não encontrada"))} -> 36000 | X6: {=IF(F6="A",H6,IFERROR(INDEX('EQUIPAMENTOS_EFICIENTES (BDD)'!J:J,MATCH(1,('EQUIPAMENTOS_EFICIENTES (BDD)'!G:G=E6)*('EQUIPAMENTOS_EFICIENTES (BDD)'!I:I=_xlfn.MINIFS('EQUIPAMENTOS_EFICIENTES (BDD)'!I:I,'EQUIPAMENTOS_EFICIENTES (BDD)'!G:G,E6,'EQUIPAMENTOS_EFICIENTES (BDD)'!I:I,">="&G6)),0)),"Substituição não encontrada"))} -> 5.5 | Y6: {=IFERROR(INDEX('EQUIPAMENTOS_EFICIENTES (BDD)'!K:K,MATCH(1,('EQUIPAMENTOS_EFICIENTES (BDD)'!G:G=E6)*('EQUIPAMENTOS_EFICIENTES (BDD)'!I:I=_xlfn.MINIFS('EQUIPAMENTOS_EFICIENTES (BDD)'!I:I,'EQUIPAMENTOS_EFICIENTES (BDD)'!G:G,E6,'EQUIPAMENTOS_EFICIENTES (BDD)'!I:I,">="&G6)),0)),"")} -> 8299 | Z6: =I6 -> 7 | AA6: =IF(X6=0,0,((W6*0.293*Z6)/(1000*X6))) -> 13.424727 | AB6: =K6 -> 0.7 | AC6: =AA6*AB6 -> 9.3973091 | AD6: =M6 -> 8 | AE6: =N6 -> 1870 | AF6: =O6 -> 11 | AG6: =P6 -> 21.25 | AH6: =Q6 -> 0 | AI6: =R6 -> 0 | AJ6: =AC6*AE6/1000 -> 17.572968 | AK6: =AI6*AC6 -> 0 | AL6: =T6-AK6 -> 0 | AM6: =S6-AJ6 -> 0 | AN6: =IF(AM6<>0,Y6*Z6,0) -> 0 | AO6: =AM6/478.332 -> 0 | AP6: =S6*0.9 -> 15.815671 | AQ6: =AJ6*0.9 -> 15.815671
A7: =IF(UC_DADOS!$B$2=0,"",UC_DADOS!$B$2) -> 7041435180 | C7: Salas 10 a 14 | D7: Philco | E7: Split Piso Teto | F7: A | G7: 36000 | H7: 5.5 | I7: 5 | J7: =IF(H7=0,0,((G7*0.293*I7)/(1000*H7))) -> 9.5890909 | K7: 0.7 | L7: =J7*K7 -> 6.7123636 | M7: 8 | N7: =M7*O7*P7 -> 1870 | O7: 11 | P7: 21.25 | Q7: 0 | R7: =O7*P7*Q7/765 -> 0 | S7: =N7*L7/1000 -> 12.55212 | T7: =R7*L7 -> 0 | U7: {=IF(F7="A",E7,IFERROR(INDEX('EQUIPAMENTOS_EFICIENTES (BDD)'!G:G,MATCH(1,('EQUIPAMENTOS_EFICIENTES (BDD)'!G:G=E7)*('EQUIPAMENTOS_EFICIENTES (BDD)'!I:I=_xlfn.MINIFS('EQUIPAMENTOS_EFICIENTES (BDD)'!I:I,'EQUIPAMENTOS_EFICIENTES (BDD)'!G:G,E7,'EQUIPAMENTOS_EFICIENTES (BDD)'!I:I,">="&G7)),0)),"Substituição não encontrada"))} -> Split Piso Teto | V7: {=IF(F7="A",F7,IFERROR(INDEX('EQUIPAMENTOS_EFICIENTES (BDD)'!H:H,MATCH(1,('EQUIPAMENTOS_EFICIENTES (BDD)'!G:G=E7)*('EQUIPAMENTOS_EFICIENTES (BDD)'!I:I=_xlfn.MINIFS('EQUIPAMENTOS_EFICIENTES (BDD)'!I:I,'EQUIPAMENTOS_EFICIENTES (BDD)'!G:G,E7,'EQUIPAMENTOS_EFICIENTES (BDD)'!I:I,">="&G7)),0)),"Substituição não encontrada"))} -> A | W7: {=IF(F7="A",G7,IFERROR(INDEX('EQUIPAMENTOS_EFICIENTES (BDD)'!I:I,MATCH(1,('EQUIPAMENTOS_EFICIENTES (BDD)'!G:G=E7)*('EQUIPAMENTOS_EFICIENTES (BDD)'!I:I=_xlfn.MINIFS('EQUIPAMENTOS_EFICIENTES (BDD)'!I:I,'EQUIPAMENTOS_EFICIENTES (BDD)'!G:G,E7,'EQUIPAMENTOS_EFICIENTES (BDD)'!I:I,">="&G7)),0)),"Substituição não encontrada"))} -> 36000 | X7: {=IF(F7="A",H7,IFERROR(INDEX('EQUIPAMENTOS_EFICIENTES (BDD)'!J:J,MATCH(1,('EQUIPAMENTOS_EFICIENTES (BDD)'!G:G=E7)*('EQUIPAMENTOS_EFICIENTES (BDD)'!I:I=_xlfn.MINIFS('EQUIPAMENTOS_EFICIENTES (BDD)'!I:I,'EQUIPAMENTOS_EFICIENTES (BDD)'!G:G,E7,'EQUIPAMENTOS_EFICIENTES (BDD)'!I:I,">="&G7)),0)),"Substituição não encontrada"))} -> 5.5 | Y7: {=IFERROR(INDEX('EQUIPAMENTOS_EFICIENTES (BDD)'!K:K,MATCH(1,('EQUIPAMENTOS_EFICIENTES (BDD)'!G:G=E7)*('EQUIPAMENTOS_EFICIENTES (BDD)'!I:I=_xlfn.MINIFS('EQUIPAMENTOS_EFICIENTES (BDD)'!I:I,'EQUIPAMENTOS_EFICIENTES (BDD)'!G:G,E7,'EQUIPAMENTOS_EFICIENTES (BDD)'!I:I,">="&G7)),0)),"")} -> 8299 | Z7: =I7 -> 5 | AA7: =IF(X7=0,0,((W7*0.293*Z7)/(1000*X7))) -> 9.5890909 | AB7: =K7 -> 0.7 | AC7: =AA7*AB7 -> 6.7123636 | AD7: =M7 -> 8 | AE7: =N7 -> 1870 | AF7: =O7 -> 11 | AG7: =P7 -> 21.25 | AH7: =Q7 -> 0 | AI7: =R7 -> 0 | AJ7: =AC7*AE7/1000 -> 12.55212 | AK7: =AI7*AC7 -> 0 | AL7: =T7-AK7 -> 0 | AM7: =S7-AJ7 -> 0 | AN7: =IF(AM7<>0,Y7*Z7,0) -> 0 | AO7: =AM7/478.332 -> 0 | AP7: =S7*0.9 -> 11.296908 | AQ7: =AJ7*0.9 -> 11.296908
A8: =IF(UC_DADOS!$B$2=0,"",UC_DADOS!$B$2) -> 7041435180 | C8: Refeitório | D8: Philco | E8: Split Piso Teto | F8: A | G8: 36000 | H8: 5.5 | I8: 3 | J8: =IF(H8=0,0,((G8*0.293*I8)/(1000*H8))) -> 5.7534545 | K8: 0.7 | L8: =J8*K8 -> 4.0274182 | M8: 4 | N8: =M8*O8*P8 -> 935 | O8: 11 | P8: 21.25 | Q8: 0 | R8: =O8*P8*Q8/765 -> 0 | S8: =N8*L8/1000 -> 3.765636 | T8: =R8*L8 -> 0 | U8: {=IF(F8="A",E8,IFERROR(INDEX('EQUIPAMENTOS_EFICIENTES (BDD)'!G:G,MATCH(1,('EQUIPAMENTOS_EFICIENTES (BDD)'!G:G=E8)*('EQUIPAMENTOS_EFICIENTES (BDD)'!I:I=_xlfn.MINIFS('EQUIPAMENTOS_EFICIENTES (BDD)'!I:I,'EQUIPAMENTOS_EFICIENTES (BDD)'!G:G,E8,'EQUIPAMENTOS_EFICIENTES (BDD)'!I:I,">="&G8)),0)),"Substituição não encontrada"))} -> Split Piso Teto | V8: {=IF(F8="A",F8,IFERROR(INDEX('EQUIPAMENTOS_EFICIENTES (BDD)'!H:H,MATCH(1,('EQUIPAMENTOS_EFICIENTES (BDD)'!G:G=E8)*('EQUIPAMENTOS_EFICIENTES (BDD)'!I:I=_xlfn.MINIFS('EQUIPAMENTOS_EFICIENTES (BDD)'!I:I,'EQUIPAMENTOS_EFICIENTES (BDD)'!G:G,E8,'EQUIPAMENTOS_EFICIENTES (BDD)'!I:I,">="&G8)),0)),"Substituição não encontrada"))} -> A | W8: {=IF(F8="A",G8,IFERROR(INDEX('EQUIPAMENTOS_EFICIENTES (BDD)'!I:I,MATCH(1,('EQUIPAMENTOS_EFICIENTES (BDD)'!G:G=E8)*('EQUIPAMENTOS_EFICIENTES (BDD)'!I:I=_xlfn.MINIFS('EQUIPAMENTOS_EFICIENTES (BDD)'!I:I,'EQUIPAMENTOS_EFICIENTES (BDD)'!G:G,E8,'EQUIPAMENTOS_EFICIENTES (BDD)'!I:I,">="&G8)),0)),"Substituição não encontrada"))} -> 36000 | X8: {=IF(F8="A",H8,IFERROR(INDEX('EQUIPAMENTOS_EFICIENTES (BDD)'!J:J,MATCH(1,('EQUIPAMENTOS_EFICIENTES (BDD)'!G:G=E8)*('EQUIPAMENTOS_EFICIENTES (BDD)'!I:I=_xlfn.MINIFS('EQUIPAMENTOS_EFICIENTES (BDD)'!I:I,'EQUIPAMENTOS_EFICIENTES (BDD)'!G:G,E8,'EQUIPAMENTOS_EFICIENTES (BDD)'!I:I,">="&G8)),0)),"Substituição não encontrada"))} -> 5.5 | Y8: {=IFERROR(INDEX('EQUIPAMENTOS_EFICIENTES (BDD)'!K:K,MATCH(1,('EQUIPAMENTOS_EFICIENTES (BDD)'!G:G=E8)*('EQUIPAMENTOS_EFICIENTES (BDD)'!I:I=_xlfn.MINIFS('EQUIPAMENTOS_EFICIENTES (BDD)'!I:I,'EQUIPAMENTOS_EFICIENTES (BDD)'!G:G,E8,'EQUIPAMENTOS_EFICIENTES (BDD)'!I:I,">="&G8)),0)),"")} -> 8299 | Z8: =I8 -> 3 | AA8: =IF(X8=0,0,((W8*0.293*Z8)/(1000*X8))) -> 5.7534545 | AB8: =K8 -> 0.7 | AC8: =AA8*AB8 -> 4.0274182 | AD8: =M8 -> 4 | AE8: =N8 -> 935 | AF8: =O8 -> 11 | AG8: =P8 -> 21.25 | AH8: =Q8 -> 0 | AI8: =R8 -> 0 | AJ8: =AC8*AE8/1000 -> 3.765636 | AK8: =AI8*AC8 -> 0 | AL8: =T8-AK8 -> 0 | AM8: =S8-AJ8 -> 0 | AN8: =IF(AM8<>0,Y8*Z8,0) -> 0 | AO8: =AM8/478.332 -> 0 | AP8: =S8*0.9 -> 3.3890724 | AQ8: =AJ8*0.9 -> 3.3890724
E9: TOTAL | I9: =SUM(I3:I8) -> 19 | J9: =SUM(J3:J8) -> 32.785558 | L9: =SUM(L3:L8) -> 22.949891 | S9: =SUM(S3:S8) -> 38.194308 | T9: =SUM(T3:T8) -> 0 | W9: TOTAL | Z9: =SUM(Z3:Z8) -> 19 | AA9: =SUM(Z3:Z8) -> 19 | AC9: =SUM(AC3:AC8) -> 21.323211 | AJ9: =SUM(AJ3:AJ8) -> 35.705488 | AK9: =SUM(AK3:AK8) -> 0 | AL9: =SUM(AL3:AL8) -> 0 | AM9: =SUM(AM3:AM8) -> 2.4888197 | AN9: =SUM(AN3:AN8) -> 14332 | AO9: =SUM(AO3:AO8) -> 0.0052031218 | AP9: =SUM(AP3:AP8) -> 34.374877 | AQ9: =SUM(AQ3:AQ8) -> 32.13494
AL87: TOTAL | AM87: =SUM(AM3:AM86) -> 4.9776393 | AO87: =SUM(AO3:AO86) -> 0.010406244

Sheet Sistemas de Refrigeração
A1: Unidade Consumidora | D1: SITUAÇÃO ATUAL | T1: SISTEMA PROPOSTO | AH1: RESULTADOS ESPERADOS
A2: Unidade consumidora (Número da conta contrato) | B2: Pavimento | C2: Ambiente | D2: Tipo de equipamento / tecnologia | E2: Porte | F2: Estado de Conservação | G2: Descrição do Sistema | H2: Potência nominal (W) | I2: Fator de utilização | J2: Potência média utilizada (kW) | K2: Quantidade | L2: Funcionamento (h/dia) | M2: Funcionamento (h/ano) | N2: Meses no ano, de utilização do Sistema | O2: Dias úteis no mês, de utilização do Sistema | P2: Horas por dia, de utilização do Sistema no horário de Ponta (horas) | Q2: Fator de coincidência na ponta | R2: Energia consumida (MWh/ano) | S2: Demanda média na ponta (kW) | T2: Tipo de equipamento / tecnologia | U2: Porte | V2: Potência nominal (W) | W2: Fator de utilização | X2: Potência média utilizada (W) | Y2: Quantidade | Z2: Preço Unitário (R$) | AA2: Funcionamento (h/ano) | AB2: Meses no ano, de utilização do Sistema no horário de Ponta (meses) | AC2: Dias úteis no mês, de utilização do Sistema no horário de Ponta (dias) | AD2: Horas por dia, de utilização do Sistema no horário de Ponta (horas) | AE2: Fator de coincidência na ponta | AF2: Energia consumida (MWh/ano) | AG2: Demanda média na ponta (kW) | AH2: Redução de demanda na ponta (kW) | AI2: Energia economizada (MWh/ano) | AJ2: Investimento (R$) | AK2: Redução de consumo proposto em relação ao consumo total da UC (%)
A3: =IF(UC_DADOS!$B$2=0,"",UC_DADOS!$B$2) -> 7041435180 | B3: Térreo | C3: Cozinha | D3: Freezer Horizontal | E3: Grande | F3: Bom | G3: Freezers | H3: 180 | I3: 0.5 | J3: =(H3*I3)/1000 -> 0.09 | K3: 1 | L3: 24 | M3: =L3*N3*O3 -> 8640 | N3: 12 | O3: 30 | P3: 3 | Q3: =N3*O3*P3/765 -> 1.4117647 | R3: =(J3*M3)/1000 -> 0.7776 | S3: =J3*Q3 -> 0.12705882 | T3: {=IF(F3="Ruim",IFERROR(INDEX('EQUIPAMENTOS_EFICIENTES (BDD)'!O:O,MATCH(1,('EQUIPAMENTOS_EFICIENTES (BDD)'!O:O=D3)*('EQUIPAMENTOS_EFICIENTES (BDD)'!T:T=E3),0)),""),D3)} -> Freezer Horizontal | U3: =E3 -> Grande | V3: {=IF(F3="Ruim",IFERROR(INDEX('EQUIPAMENTOS_EFICIENTES (BDD)'!Q:Q,MATCH(1,('EQUIPAMENTOS_EFICIENTES (BDD)'!O:O=D3)*('EQUIPAMENTOS_EFICIENTES (BDD)'!T:T=E3),0)),H3),H3)} -> 180 | W3: 0.45 | X3: =(W3*V3)/1000 -> 0.081 | Y3: =K3 -> 1 | Z3: {=IF(F3="Ruim",IFERROR(INDEX('EQUIPAMENTOS_EFICIENTES (BDD)'!U:U,MATCH(1,('EQUIPAMENTOS_EFICIENTES (BDD)'!O:O=D3)*('EQUIPAMENTOS_EFICIENTES (BDD)'!T:T=E3),0)),0),0)} -> 0 | AA3: =M3 -> 8640 | AB3: =N3 -> 12 | AC3: =O3 -> 30 | AD3: =P3 -> 3 | AE3: =Q3 -> 1.4117647 | AF3: =(AA3*X3)/1000 -> 0.69984 | AG3: =AE3*X3/1000 -> 0.00011435294 | AH3: =S3-AG3 -> 0.12694447 | AI3: =(R3-AF3) -> 0.07776 | AJ3: =IF(AI3>0,Y3*Z3,0) -> 0 | AK3: =AI3/478.332 -> 0.00016256491
A4: =IF(UC_DADOS!$B$2=0,"",UC_DADOS!$B$2) -> 7041435180 | B4: Térreo | C4: Cozinha | D4: Geladeira | E4: Grande | F4: Bom | G4: Refrigeradores | H4: 150 | I4: 0.45 | J4: =(H4*I4)/1000 -> 0.0675 | K4: 1 | L4: 24 | M4: =L4*N4*O4 -> 8640 | N4: 12 | O4: 30 | P4: 3 | Q4: =N4*O4*P4/765 -> 1.4117647 | R4: =(J4*M4)/1000 -> 0.5832 | S4: =J4*Q4 -> 0.095294118 | T4: {=IF(F4="Ruim",IFERROR(INDEX('EQUIPAMENTOS_EFICIENTES (BDD)'!O:O,MATCH(1,('EQUIPAMENTOS_EFICIENTES (BDD)'!O:O=D4)*('EQUIPAMENTOS_EFICIENTES (BDD)'!T:T=E4),0)),""),D4)} -> Geladeira | U4: =E4 -> Grande | V4: {=IF(F4="Ruim",IFERROR(INDEX('EQUIPAMENTOS_EFICIENTES (BDD)'!Q:Q,MATCH(1,('EQUIPAMENTOS_EFICIENTES (BDD)'!O:O=D4)*('EQUIPAMENTOS_EFICIENTES (BDD)'!T:T=E4),0)),H4),H4)} -> 150 | W4: {=IF(F4="Ruim",IFERROR(INDEX('EQUIPAMENTOS_EFICIENTES (BDD)'!S:S,MATCH(1,('EQUIPAMENTOS_EFICIENTES (BDD)'!O:O=D4)*('EQUIPAMENTOS_EFICIENTES (BDD)'!T:T=E4),0)),I4),I4)} -> 0.45 | X4: =(W4*V4)/1000 -> 0.0675 | Y4: =K4 -> 1 | Z4: {=IF(F4="Ruim",IFERROR(INDEX('EQUIPAMENTOS_EFICIENTES (BDD)'!U:U,MATCH(1,('EQUIPAMENTOS_EFICIENTES (BDD)'!O:O=D4)*('EQUIPAMENTOS_EFICIENTES (BDD)'!T:T=E4),0)),0),0)} -> 0 | AA4: =M4 -> 8640 | AB4: =N4 -> 12 | AC4: =O4 -> 30 | AD4: =P4 -> 3 | AE4: =Q4 -> 1.4117647 | AF4: =(AA4*X4)/1000 -> 0.5832 | AG4: =AE4*X4/1000 -> 9.5294118e-05 | AH4: =S4-AG4 -> 0.095198824 | AI4: =(R4-AF4) -> 0 | AJ4: =IF(AI4>0,Y4*Z4,0) -> 0 | AK4: =AI4/478.332 -> 0
A5: =IF(UC_DADOS!$B$2=0,"",UC_DADOS!$B$2) -> 7041435180 | B5: Térreo | C5: Cozinha | D5: Geladeira | E5: Grande | F5: Bom | G5: Refrigeradores | H5: 160 | I5: 0.49 | J5: =(H5*I5)/1000 -> 0.0784 | K5: 1 | L5: 24 | M5: =L5*N5*O5 -> 8640 | N5: 12 | O5: 30 | P5: 3 | Q5: =N5*O5*P5/765 -> 1.4117647 | R5: =(J5*M5)/1000 -> 0.677376 | S5: =J5*Q5 -> 0.11068235 | T5: {=IF(F5="Ruim",IFERROR(INDEX('EQUIPAMENTOS_EFICIENTES (BDD)'!O:O,MATCH(1,('EQUIPAMENTOS_EFICIENTES (BDD)'!O:O=D5)*('EQUIPAMENTOS_EFICIENTES (BDD)'!T:T=E5),0)),""),D5)} -> Geladeira | U5: =E5 -> Grande | V5: {=IF(F5="Ruim",IFERROR(INDEX('EQUIPAMENTOS_EFICIENTES (BDD)'!Q:Q,MATCH(1,('EQUIPAMENTOS_EFICIENTES (BDD)'!O:O=D5)*('EQUIPAMENTOS_EFICIENTES (BDD)'!T:T=E5),0)),H5),H5)} -> 160 | W5: {=IF(F5="Ruim",IFERROR(INDEX('EQUIPAMENTOS_EFICIENTES (BDD)'!S:S,MATCH(1,('EQUIPAMENTOS_EFICIENTES (BDD)'!O:O=D5)*('EQUIPAMENTOS_EFICIENTES (BDD)'!T:T=E5),0)),I5),I5)} -> 0.49 | X5: =(W5*V5)/1000 -> 0.0784 | Y5: =K5 -> 1 | Z5: {=IF(F5="Ruim",IFERROR(INDEX('EQUIPAMENTOS_EFICIENTES (BDD)'!U:U,MATCH(1,('EQUIPAMENTOS_EFICIENTES (BDD)'!O:O=D5)*('EQUIPAMENTOS_EFICIENTES (BDD)'!T:T=E5),0)),0),0)} -> 0 | AA5: =M5 -> 8640 | AB5: =N5 -> 12 | AC5: =O5 -> 30 | AD5: =P5 -> 3 | AE5: =Q5 -> 1.4117647 | AF5: =(AA5*X5)/1000 -> 0.677376 | AG5: =AE5*X5/1000 -> 0.00011068235 | AH5: =S5-AG5 -> 0.11057167 | AI5: =(R5-AF5) -> 0 | AJ5: =IF(AI5>0,Y5*Z5,0) -> 0 | AK5: =AI5/478.332 -> 0
A6: =IF(UC_DADOS!$B$2=0,"",UC_DADOS!$B$2) -> 7041435180 | B6: Térreo | C6: Sala de freezer | D6: Freezer Horizontal | E6: Grande | F6: Bom | G6: Freezers | H6: 250 | I6: 0.6 | J6: =(H6*I6)/1000 -> 0.15 | K6: 1 | L6: 24 | M6: =L6*N6*O6 -> 8640 | N6: 12 | O6: 30 | P6: 3 | Q6: =N6*O6*P6/765 -> 1.4117647 | R6: =(J6*M6)/1000 -> 1.296 | S6: =J6*Q6 -> 0.21176471 | T6: {=IF(F6="Ruim",IFERROR(INDEX('EQUIPAMENTOS_EFICIENTES (BDD)'!O:O,MATCH(1,('EQUIPAMENTOS_EFICIENTES (BDD)'!O:O=D6)*('EQUIPAMENTOS_EFICIENTES (BDD)'!T:T=E6),0)),""),D6)} -> Freezer Horizontal | U6: =E6 -> Grande | V6: {=IF(F6="Ruim",IFERROR(INDEX('EQUIPAMENTOS_EFICIENTES (BDD)'!Q:Q,MATCH(1,('EQUIPAMENTOS_EFICIENTES (BDD)'!O:O=D6)*('EQUIPAMENTOS_EFICIENTES (BDD)'!T:T=E6),0)),H6),H6)} -> 250 | W6: {=IF(F6="Ruim",IFERROR(INDEX('EQUIPAMENTOS_EFICIENTES (BDD)'!S:S,MATCH(1,('EQUIPAMENTOS_EFICIENTES (BDD)'!O:O=D6)*('EQUIPAMENTOS_EFICIENTES (BDD)'!T:T=E6),0)),I6),I6)} -> 0.6 | X6: =(W6*V6)/1000 -> 0.15 | Y6: =K6 -> 1 | Z6: {=IF(F6="Ruim",IFERROR(INDEX('EQUIPAMENTOS_EFICIENTES (BDD)'!U:U,MATCH(1,('EQUIPAMENTOS_EFICIENTES (BDD)'!O:O=D6)*('EQUIPAMENTOS_EFICIENTES (BDD)'!T:T=E6),0)),0),0)} -> 0 | AA6: =M6 -> 8640 | AB6: =N6 -> 12 | AC6: =O6 -> 30 | AD6: =P6 -> 3 | AE6: =Q6 -> 1.4117647 | AF6: =(AA6*X6)/1000 -> 1.296 | AG6: =AE6*X6/1000 -> 0.00021176471 | AH6: =S6-AG6 -> 0.21155294 | AI6: =(R6-AF6) -> 0 | AJ6: =IF(AI6>0,Y6*Z6,0) -> 0 | AK6: =AI6/478.332 -> 0
A7: =IF(UC_DADOS!$B$2=0,"",UC_DADOS!$B$2) -> 7041435180 | B7: Anexo | C7: Refeitório | D7: Geladeira | E7: Pequeno | F7: Bom | G7: Refrigeradores | H7: 100 | I7: 0.45 | J7: =(H7*I7)/1000 -> 0.045 | K7: 1 | L7: 24 | M7: =L7*N7*O7 -> 8640 | N7: 12 | O7: 30 | P7: 3 | Q7: =N7*O7*P7/765 -> 1.4117647 | R7: =(J7*M7)/1000 -> 0.3888 | S7: =J7*Q7 -> 0.063529412 | T7: {=IF(F7="Ruim",IFERROR(INDEX('EQUIPAMENTOS_EFICIENTES (BDD)'!O:O,MATCH(1,('EQUIPAMENTOS_EFICIENTES (BDD)'!O:O=D7)*('EQUIPAMENTOS_EFICIENTES (BDD)'!T:T=E7),0)),""),D7)} -> Geladeira | U7: =E7 -> Pequeno | V7: {=IF(F7="Ruim",IFERROR(INDEX('EQUIPAMENTOS_EFICIENTES (BDD)'!Q:Q,MATCH(1,('EQUIPAMENTOS_EFICIENTES (BDD)'!O:O=D7)*('EQUIPAMENTOS_EFICIENTES (BDD)'!T:T=E7),0)),H7),H7)} -> 100 | W7: {=IF(F7="Ruim",IFERROR(INDEX('EQUIPAMENTOS_EFICIENTES (BDD)'!S:S,MATCH(1,('EQUIPAMENTOS_EFICIENTES (BDD)'!O:O=D7)*('EQUIPAMENTOS_EFICIENTES (BDD)'!T:T=E7),0)),I7),I7)} -> 0.45 | X7: =(W7*V7)/1000 -> 0.045 | Y7: =K7 -> 1 | Z7: {=IF(F7="Ruim",IFERROR(INDEX('EQUIPAMENTOS_EFICIENTES (BDD)'!U:U,MATCH(1,('EQUIPAMENTOS_EFICIENTES (BDD)'!O:O=D7)*('EQUIPAMENTOS_EFICIENTES (BDD)'!T:T=E7),0)),0),0)} -> 0 | AA7: =M7 -> 8640 | AB7: =N7 -> 12 | AC7: =O7 -> 30 | AD7: =P7 -> 3 | AE7: =Q7 -> 1.4117647 | AF7: =(AA7*X7)/1000 -> 0.3888 | AG7: =AE7*X7/1000 -> 6.3529412e-05 | AH7: =S7-AG7 -> 0.063465882 | AI7: =(R7-AF7) -> 0 | AJ7: =IF(AI7>0,Y7*Z7,0) -> 0 | AK7: =AI7/478.332 -> 0
A8: =IF(UC_DADOS!$B$2=0,"",UC_DADOS!$B$2) -> 7041435180 | B8: Anexo | C8: Refeitório | D8: Geladeira | E8: Grande | F8: Bom | G8: Refrigeradores | H8: 120 | I8: 0.45 | J8: =(H8*I8)/1000 -> 0.054 | K8: 1 | L8: 24 | M8: =L8*N8*O8 -> 8640 | N8: 12 | O8: 30 | P8: 3 | Q8: =N8*O8*P8/765 -> 1.4117647 | R8: =(J8*M8)/1000 -> 0.46656 | S8: =J8*Q8 -> 0.076235294 | T8: {=IF(F8="Ruim",IFERROR(INDEX('EQUIPAMENTOS_EFICIENTES (BDD)'!O:O,MATCH(1,('EQUIPAMENTOS_EFICIENTES (BDD)'!O:O=D8)*('EQUIPAMENTOS_EFICIENTES (BDD)'!T:T=E8),0)),""),D8)} -> Geladeira | U8: =E8 -> Grande | V8: {=IF(F8="Ruim",IFERROR(INDEX('EQUIPAMENTOS_EFICIENTES (BDD)'!Q:Q,MATCH(1,('EQUIPAMENTOS_EFICIENTES (BDD)'!O:O=D8)*('EQUIPAMENTOS_EFICIENTES (BDD)'!T:T=E8),0)),H8),H8)} -> 120 | W8: {=IF(F8="Ruim",IFERROR(INDEX('EQUIPAMENTOS_EFICIENTES (BDD)'!S:S,MATCH(1,('EQUIPAMENTOS_EFICIENTES (BDD)'!O:O=D8)*('EQUIPAMENTOS_EFICIENTES (BDD)'!T:T=E8),0)),I8),I8)} -> 0.45 | X8: =(W8*V8)/1000 -> 0.054 | Y8: =K8 -> 1 | Z8: {=IF(F8="Ruim",IFERROR(INDEX('EQUIPAMENTOS_EFICIENTES (BDD)'!U:U,MATCH(1,('EQUIPAMENTOS_EFICIENTES (BDD)'!O:O=D8)*('EQUIPAMENTOS_EFICIENTES (BDD)'!T:T=E8),0)),0),0)} -> 0 | AA8: =M8 -> 8640 | AB8: =N8 -> 12 | AC8: =O8 -> 30 | AD8: =P8 -> 3 | AE8: =Q8 -> 1.4117647 | AF8: =(AA8*X8)/1000 -> 0.46656 | AG8: =AE8*X8/1000 -> 7.6235294e-05 | AH8: =S8-AG8 -> 0.076159059 | AI8: =(R8-AF8) -> 0 | AJ8: =IF(AI8>0,Y8*Z8,0) -> 0 | AK8: =AI8/478.332 -> 0
A9: =IF(UC_DADOS!$B$2=0,"",UC_DADOS!$B$2) -> 7041435180 | B9: Térreo | C9: Circulação | D9: Bebedouro | E9: Médio | F9: Bom | G9: Refrigeradores | H9: 220 | I9: 0.6 | J9: =(H9*I9)/1000 -> 0.132 | K9: 1 | L9: 24 | M9: =L9*N9*O9 -> 8640 | N9: 12 | O9: 30 | P9: 3 | Q9: =N9*O9*P9/765 -> 1.4117647 | R9: =(J9*M9)/1000 -> 1.14048 | S9: =J9*Q9 -> 0.18635294 | T9: {=IF(F9="Ruim",IFERROR(INDEX('EQUIPAMENTOS_EFICIENTES (BDD)'!O:O,MATCH(1,('EQUIPAMENTOS_EFICIENTES (BDD)'!O:O=D9)*('EQUIPAMENTOS_EFICIENTES (BDD)'!T:T=E9),0)),""),D9)} -> Bebedouro | U9: =E9 -> Médio | V9: {=IF(F9="Ruim",IFERROR(INDEX('EQUIPAMENTOS_EFICIENTES (BDD)'!Q:Q,MATCH(1,('EQUIPAMENTOS_EFICIENTES (BDD)'!O:O=D9)*('EQUIPAMENTOS_EFICIENTES (BDD)'!T:T=E9),0)),H9),H9)} -> 220 | W9: {=IF(F9="Ruim",IFERROR(INDEX('EQUIPAMENTOS_EFICIENTES (BDD)'!S:S,MATCH(1,('EQUIPAMENTOS_EFICIENTES (BDD)'!O:O=D9)*('EQUIPAMENTOS_EFICIENTES (BDD)'!T:T=E9),0)),I9),I9)} -> 0.6 | X9: =(W9*V9)/1000 -> 0.132 | Y9: =K9 -> 1 | Z9: {=IF(F9="Ruim",IFERROR(INDEX('EQUIPAMENTOS_EFICIENTES (BDD)'!U:U,MATCH(1,('EQUIPAMENTOS_EFICIENTES (BDD)'!O:O=D9)*('EQUIPAMENTOS_EFICIENTES (BDD)'!T:T=E9),0)),0),0)} -> 0 | AA9: =M9 -> 8640 | AB9: =N9 -> 12 | AC9: =O9 -> 30 | AD9: =P9 -> 3 | AE9: =Q9 -> 1.4117647 | AF9: =(AA9*X9)/1000 -> 1.14048 | AG9: =AE9*X9/1000 -> 0.00018635294 | AH9: =S9-AG9 -> 0.18616659 | AI9: =(R9-AF9) -> 0 | AJ9: =IF(AI9>0,Y9*Z9,0) -> 0 | AK9: =AI9/478.332 -> 0
D10: TOTAL | J10: =SUBTOTAL(9,J3:J9) -> 0.6169 | K10: =SUBTOTAL(9,K3:K9) -> 7 | R10: =SUBTOTAL(9,R3:R9) -> 5.330016 | S10: =SUBTOTAL(9,S3:S9) -> 0.87091765 | X10: =SUBTOTAL(9,X3:X9) -> 0.6079 | Y10: =SUM(Y3:Y9) -> 7 | Z10: =SUBTOTAL(9,Z3:Z6) -> 0 | AF10: =SUBTOTAL(9,AF3:AF9) -> 5.252256 | AG10: =SUBTOTAL(9,AG3:AG6) -> 0.00053209412 | AH10: =SUM(AH3:AH9) -> 0.87005944 | AI10: =SUM(AI3:AI9) -> 0.07776 | AJ10: =SUM(AJ3:AJ6) -> 0 | AK10: =SUM(AK3:AK6) -> 0.00016256491

Sheet Sistemas de Iluminação
A1: Unidade Consumidora | E1: SITUAÇÃO ATUAL | S1: SISTEMA PROPOSTO | AG1: RESULTADOS ESPERADOS | AI1: RESULTADO AUTOMAÇÃO (15%)
A2: Unidade consumidora (Número da conta contrato) | B2: Pavimento | C2: Ambiente | D2: Descrição do sistema | E2: Tipo de equipamento / tecnologia | F2: Lâmpadas | H2: Reatores | J2: Potência Instalada (kW) | K2: Funcionamento (h/dia) | L2: Funcionamento (h/ano) | M2: Meses no ano, de utilização do Sistema | N2: Dias úteis no mês, de utilização do Sistema | O2: Horas por dia, de utilização do Sistema no horário de Ponta (horas) | P2: Fator de coincidência na ponta | Q2: Energia consumida (MWh/ano) | R2: Demanda média na ponta (kW) | S2: Tipo de equipamento / tecnologia | T2: Lâmpadas | V2: Reatores | X2: Potência Instalada (kW) | Y2: Funcionamento (h/ano) | Z2: Meses no ano, de utilização do Sistema no horário de Ponta (meses) | AA2: Dias úteis no mês, de utilização do Sistema no horário de Ponta (dias) | AB2: Horas por dia, de utilização do Sistema no horário de Ponta (horas) | AC2: Fator de coincidência na ponta | AD2: Energia consumida (MWh/ano) | AE2: Demanda média na ponta (kW) | AF2: Redução de demanda na ponta (kW) | AG2: Energia economizada (MWh/ano) | AH2: Redução de consumo proposto em relação ao consumo total da UC (%) | AI2: Energia economizada (MWh/ano)
F3: Potência (W) | G3: Quantidade | H3: Potência (W) | I3: Quantidade | T3: Potência (W) | U3: Quantidade | V3: Potência (W) | W3: Quantidade
A4: =IF(UC_DADOS!$B$2=0,"",UC_DADOS!$B$2) -> 7041435180 | B4: Térreo | C4: Secretaria | D4: LED | E4: Sobrepor | F4: 10 | G4: 2 | J4: =(F4*G4+H4*I4)/1000 -> 0.02 | K4: 8 | L4: =K4*M4*N4 -> 2040 | M4: 12 | N4: 21.25 | O4: 0 | P4: =M4*N4*O4/765 -> 0 | Q4: =J4*L4/1000 -> 0.0408 | R4: =J4*P4 -> 0 | S4: LED | T4: 20 | U4: 4 | X4: =(T4*U4+V4*W4)/1000 -> 0.08 | Y4: =L4 -> 2040 | Z4: =M4 -> 12 | AA4: =N4 -> 21.25 | AB4: =O4 -> 0 | AC4: =P4 -> 0 | AD4: =X4*Y4/1000 -> 0.1632 | AE4: =X4*AC4 -> 0 | AF4: =R4-AE4 -> 0 | AG4: =Q4-AD4 -> -0.1224 | AH4: =AG4/478.332 -> -0.00025588922 | AI4: =Q4*0.85 -> 0.03468
A5: =IF(UC_DADOS!$B$2=0,"",UC_DADOS!$B$2) -> 7041435180 | B5: Térreo | C5: Direção | D5: LED | E5: Sobrepor | F5: 15 | G5: 1 | J5: =(F5*G5+H5*I5)/1000 -> 0.015 | K5: 8 | L5: =K5*M5*N5 -> 2040 | M5: 12 | N5: 21.25 | O5: 0 | P5: =M5*N5*O5/765 -> 0 | Q5: =J5*L5/1000 -> 0.0306 | R5: =J5*P5 -> 0 | S5: LED | T5: 12 | U5: 1 | X5: =(T5*U5+V5*W5)/1000 -> 0.012 | Y5: =L5 -> 2040 | Z5: =M5 -> 12 | AA5: =N5 -> 21.25 | AB5: =O5 -> 0 | AC5: =P5 -> 0 | AD5: =X5*Y5/1000 -> 0.02448 | AE5: =X5*AC5 -> 0 | AF5: =R5-AE5 -> 0 | AG5: =Q5-AD5 -> 0.00612 | AH5: =AG5/478.332 -> 1.2794461e-05 | AI5: =Q5*0.85 -> 0.02601
A6: =IF(UC_DADOS!$B$2=0,"",UC_DADOS!$B$2) -> 7041435180 | B6: Térreo | C6: Banheiro da direção | D6: LED | E6: Sobrepor | F6: 10 | G6: 1 | J6: =(F6*G6+H6*I6)/1000 -> 0.01 | K6: 1 | L6: =K6*M6*N6 -> 255 | M6: 12 | N6: 21.25 | O6: 0 | P6: =M6*N6*O6/765 -> 0 | Q6: =J6*L6/1000 -> 0.00255 | R6: =J6*P6 -> 0 | S6: LED | T6: 20 | U6: 48 | X6: =(T6*U6+V6*W6)/1000 -> 0.96 | Y6: =L6 -> 255 | Z6: =M6 -> 12 | AA6: =N6 -> 21.25 | AB6: =O6 -> 0 | AC6: =P6 -> 0 | AD6: =X6*Y6/1000 -> 0.2448 | AE6: =X6*AC6 -> 0 | AF6: =R6-AE6 -> 0 | AG6: =Q6-AD6 -> -0.24225 | AH6: =AG6/478.332 -> -0.0005064474 | AI6: =Q6*0.85 -> 0.0021675
A7: =IF(UC_DADOS!$B$2=0,"",UC_DADOS!$B$2) -> 7041435180 | B7: Térreo | C7: Banheiros secretaria | D7: LED | E7: Sobrepor | F7: 10 | G7: 5 | J7: =(F7*G7+H7*I7)/1000 -> 0.05 | K7: 1 | L7: =K7*M7*N7 -> 255 | M7: 12 | N7: 21.25 | O7: 0 | P7: =M7*N7*O7/765 -> 0 | Q7: =J7*L7/1000 -> 0.01275 | R7: =J7*P7 -> 0 | S7: LED | T7: 20 | U7: 2 | X7: =(T7*U7+V7*W7)/1000 -> 0.04 | Y7: =L7 -> 255 | Z7: =M7 -> 12 | AA7: =N7 -> 21.25 | AB7: =O7 -> 0 | AC7: =P7 -> 0 | AD7: =X7*Y7/1000 -> 0.0102 | AE7: =X7*AC7 -> 0 | AF7: =R7-AE7 -> 0 | AG7: =Q7-AD7 -> 0.00255 | AH7: =AG7/478.332 -> 5.3310253e-06 | AI7: =Q7*0.85 -> 0.0108375
A8: =IF(UC_DADOS!$B$2=0,"",UC_DADOS!$B$2) -> 7041435180 | B8: Térreo | C8: Circulação | D8: LED | E8: Sobrepor | F8: 20 | G8: 12 | J8: =(F8*G8+H8*I8)/1000 -> 0.24 | K8: 8 | L8: =K8*M8*N8 -> 2040 | M8: 12 | N8: 21.25 | O8: 0 | P8: =M8*N8*O8/765 -> 0 | Q8: =J8*L8/1000 -> 0.4896 | R8: =J8*P8 -> 0 | S8: LED | T8: 20 | U8: 8 | X8: =(T8*U8+V8*W8)/1000 -> 0.16 | Y8: =L8 -> 2040 | Z8: =M8 -> 12 | AA8: =N8 -> 21.25 | AB8: =O8 -> 0 | AC8: =P8 -> 0 | AD8: =X8*Y8/1000 -> 0.3264 | AE8: =X8*AC8 -> 0 | AF8: =R8-AE8 -> 0 | AG8: =Q8-AD8 -> 0.1632 | AH8: =AG8/478.332 -> 0.00034118562 | AI8: =Q8*0.85 -> 0.41616
A9: =IF(UC_DADOS!$B$2=0,"",UC_DADOS!$B$2) -> 7041435180 | B9: Térreo | C9: Depósito | D9: LED | E9: Sobrepor | F9: 15 | G9: 1 | J9: =(F9*G9+H9*I9)/1000 -> 0.015 | K9: 1 | L9: =K9*M9*N9 -> 233.75 | M9: 11 | N9: 21.25 | O9: 0 | P9: =M9*N9*O9/765 -> 0 | Q9: =J9*L9/1000 -> 0.00350625 | R9: =J9*P9 -> 0 | S9: LED | T9: 20 | U9: 8 | X9: =(T9*U9+V9*W9)/1000 -> 0.16 | Y9: =L9 -> 233.75 | Z9: =M9 -> 11 | AA9: =N9 -> 21.25 | AB9: =O9 -> 0 | AC9: =P9 -> 0 | AD9: =X9*Y9/1000 -> 0.0374 | AE9: =X9*AC9 -> 0 | AF9: =R9-AE9 -> 0 | AG9: =Q9-AD9 -> -0.03389375 | AH9: =AG9/478.332 -> -7.0858211e-05 | AI9: =Q9*0.85 -> 0.0029803125
A10: =IF(UC_DADOS!$B$2=0,"",UC_DADOS!$B$2) -> 7041435180 | B10: Térreo | C10: Banheiros Alunos | D10: LED | E10: Sobrepor | F10: 10 | G10: 7 | J10: =(F10*G10+H10*I10)/1000 -> 0.07 | K10: 2 | L10: =K10*M10*N10 -> 467.5 | M10: 11 | N10: 21.25 | O10: 0 | P10: =M10*N10*O10/765 -> 0 | Q10: =J10*L10/1000 -> 0.032725 | R10: =J10*P10 -> 0 | S10: LED | T10: 20 | U10: 4 | X10: =(T10*U10+V10*W10)/1000 -> 0.08 | Y10: =L10 -> 467.5 | Z10: =M10 -> 11 | AA10: =N10 -> 21.25 | AB10: =O10 -> 0 | AC10: =P10 -> 0 | AD10: =X10*Y10/1000 -> 0.0374 | AE10: =X10*AC10 -> 0 | AF10: =R10-AE10 -> 0 | AG10: =Q10-AD10 -> -0.004675 | AH10: =AG10/478.332 -> -9.7735464e-06 | AI10: =Q10*0.85 -> 0.02781625
A11: =IF(UC_DADOS!$B$2=0,"",UC_DADOS!$B$2) -> 7041435180 | B11: Térreo | C11: Sala dos professores | D11: LED | E11: Sobrepor | F11: 10 | G11: 4 | J11: =(F11*G11+H11*I11)/1000 -> 0.04 | K11: 4 | L11: =K11*M11*N11 -> 935 | M11: 11 | N11: 21.25 | O11: 0 | P11: =M11*N11*O11/765 -> 0 | Q11: =J11*L11/1000 -> 0.0374 | R11: =J11*P11 -> 0 | S11: LED | T11: 20 | U11: 2 | X11: =(T11*U11+V11*W11)/1000 -> 0.04 | Y11: =L11 -> 935 | Z11: =M11 -> 11 | AA11: =N11 -> 21.25 | AB11: =O11 -> 0 | AC11: =P11 -> 0 | AD11: =X11*Y11/1000 -> 0.0374 | AE11: =X11*AC11 -> 0 | AF11: =R11-AE11 -> 0 | AG11: =Q11-AD11 -> 0 | AH11: =AG11/478.332 -> 0 | AI11: =Q11*0.85 -> 0.03179
A12: =IF(UC_DADOS!$B$2=0,"",UC_DADOS!$B$2) -> 7041435180 | B12: Térreo | C12: Cozinha | D12: LED | E12: Sobrepor | F12: 30 | G12: 2 | J12: =(F12*G12+H12*I12)/1000 -> 0.06 | K12: 5 | L12: =K12*M12*N12 -> 1168.75 | M12: 11 | N12: 21.25 | O12: 0 | P12: =M12*N12*O12/765 -> 0 | Q12: =J12*L12/1000 -> 0.070125 | R12: =J12*P12 -> 0 | S12: LED | T12: 150 | U12: 8 | X12: =(T12*U12+V12*W12)/1000 -> 1.2 | Y12: =L12 -> 1168.75 | Z12: =M12 -> 11 | AA12: =N12 -> 21.25 | AB12: =O12 -> 0 | AC12: =P12 -> 0 | AD12: =X12*Y12/1000 -> 1.4025 | AE12: =X12*AC12 -> 0 | AF12: =R12-AE12 -> 0 | AG12: =Q12-AD12 -> -1.332375 | AH12: =AG12/478.332 -> -0.0027854607 | AI12: =Q12*0.85 -> 0.05960625
A13: =IF(UC_DADOS!$B$2=0,"",UC_DADOS!$B$2) -> 7041435180 | B13: Térreo | C13: Sala do freezer | D13: LED | E13: Sobrepor | F13: 10 | G13: 1 | J13: =(F13*G13+H13*I13)/1000 -> 0.01 | K13: 2 | L13: =K13*M13*N13 -> 467.5 | M13: 11 | N13: 21.25 | O13: 0 | P13: =M13*N13*O13/765 -> 0 | Q13: =J13*L13/1000 -> 0.004675 | R13: =J13*P13 -> 0 | S13: LED | T13: 15 | U13: 15 | X13: =(T13*U13+V13*W13)/1000 -> 0.225 | Y13: =L13 -> 467.5 | Z13: =M13 -> 11 | AA13: =N13 -> 21.25 | AB13: =O13 -> 0 | AC13: =P13 -> 0 | AD13: =X13*Y13/1000 -> 0.1051875 | AE13: =X13*AC13 -> 0 | AF13: =R13-AE13 -> 0 | AG13: =Q13-AD13 -> -0.1005125 | AH13: =AG13/478.332 -> -0.00021013125 | AI13: =Q13*0.85 -> 0.00397375
A14: =IF(UC_DADOS!$B$2=0,"",UC_DADOS!$B$2) -> 7041435180 | B14: 1 andar | C14: Salas de aula (01 a 07) | D14: LED | E14: Sobrepor | F14: 15 | G14: 28 | J14: =(F14*G14+H14*I14)/1000 -> 0.42 | K14: 8 | L14: =K14*M14*N14 -> 1870 | M14: 11 | N14: 21.25 | O14: 0 | P14: =M14*N14*O14/765 -> 0 | Q14: =J14*L14/1000 -> 0.7854 | R14: =J14*P14 -> 0 | S14: LED | T14: 40 | U14: 5 | X14: =(T14*U14+V14*W14)/1000 -> 0.2 | Y14: =L14 -> 1870 | Z14: =M14 -> 11 | AA14: =N14 -> 21.25 | AB14: =O14 -> 0 | AC14: =P14 -> 0 | AD14: =X14*Y14/1000 -> 0.374 | AE14: =X14*AC14 -> 0 | AF14: =R14-AE14 -> 0 | AG14: =Q14-AD14 -> 0.4114 | AH14: =AG14/478.332 -> 0.00086007208 | AI14: =Q14*0.85 -> 0.66759
A15: =IF(UC_DADOS!$B$2=0,"",UC_DADOS!$B$2) -> 7041435180 | B15: 1 andar | C15: Banheiros alunos | D15: LED | E15: Sobrepor | F15: 15 | G15: 5 | J15: =(F15*G15+H15*I15)/1000 -> 0.075 | K15: 2 | L15: =K15*M15*N15 -> 467.5 | M15: 11 | N15: 21.25 | O15: 0 | P15: =M15*N15*O15/765 -> 0 | Q15: =J15*L15/1000 -> 0.0350625 | R15: =J15*P15 -> 0 | S15: LED | T15: 20 | U15: 4 | X15: =(T15*U15+V15*W15)/1000 -> 0.08 | Y15: =L15 -> 467.5 | Z15: =M15 -> 11 | AA15: =N15 -> 21.25 | AB15: =O15 -> 0 | AC15: =P15 -> 0 | AD15: =X15*Y15/1000 -> 0.0374 | AE15: =X15*AC15 -> 0 | AF15: =R15-AE15 -> 0 | AG15: =Q15-AD15 -> -0.0023375 | AH15: =AG15/478.332 -> -4.8867732e-06 | AI15: =Q15*0.85 -> 0.029803125
... A23: =IF(UC_DADOS!$B$2=0,"",UC_DADOS!$B$2) -> 7041435180 | B23: Térreo | C23: Área de Serviço | D23: LED | E23: Sobrepor | F23: 20 | G23: 1 | J23: =(F23*G23+H23*I23)/1000 -> 0.02 | K23: 3 | L23: =K23*M23*N23 -> 701.25 | M23: 11 | N23: 21.25 | O23: 0 | P23: =M23*N23*O23/765 -> 0 | Q23: =J23*L23/1000 -> 0.014025 | R23: =J23*P23 -> 0 | S23: LED | T23: 20 | U23: 4 | X23: =(T23*U23+V23*W23)/1000 -> 0.08 | Y23: =L23 -> 701.25 | Z23: =M23 -> 11 | AA23: =N23 -> 21.25 | AB23: =O23 -> 0 | AC23: =P23 -> 0 | AD23: =X23*Y23/1000 -> 0.0561 | AE23: =X23*AC23 -> 0 | AF23: =R23-AE23 -> 0 | AG23: =Q23-AD23 -> -0.042075 | AH23: =AG23/478.332 -> -8.7961918e-05 | AI23: =Q23*0.85 -> 0.01192125
E24: TOTAL | G24: =SUM(G4:G23) -> 152 | J24: =SUM(J4:J23) -> 2.595 | Q24: =SUM(Q4:Q23) -> 4.2745438 | R24: =SUM(R4:R23) -> 0 | U24: =SUM(U4:U23) -> 279 | X24: =SUM(X4:X23) -> 6.517 | AD24: =SUM(AD4:AD23) -> 8.1315675 | AE24: =SUM(AE4:AE23) -> 0 | AF24: =SUM(AF4:AF23) -> 0 | AG24: =SUM(AG4:AG23) -> -3.8570238 | AH24: =SUM(AH4:AH23) -> -0.0080634868 | AI24: =SUM(AI4:AI23) -> 3.6333622

Sheet Sistemas de Motor
C1: SITUAÇÃO ATUAL | R1: SISTEMA PROPOSTO | AF1: RESULTADOS ESPERADOS
A2: Unidade consumidora (Número da conta contrato) | B2: Descrição do sistema | C2: Potência do motor (cv) | D2: Carregamento | E2: Rendimento nominal (%) | F2: Rendimento no ponto de carregamento (%) | G2: Quantidade | H2: Potência instalada (kW) | I2: Potência média utilizada (kW) | J2: Funcionamento (h/dia) | K2: Funcionamento (h/ano) | L2: Meses no ano, de utilização do Sistema | M2: Dias úteis no mês, de utilização do Sistema | N2: Horas por dia, de utilização do Sistema no horário de Ponta (horas) | O2: Fator de coincidência na ponta | P2: Energia consumida (MWh/ano) | Q2: Demanda média na ponta (kW) | R2: Potência do motor (cv) | S2: Carregamento | T2: Rendimento nominal (%) | U2: Rendimento no ponto de carregamento (%) | V2: Quantidade | W2: Potência instalada (kW) | X2: Potência média utilizada (kW) | Y2: Funcionamento (h/ano) | Z2: Meses no ano, de utilização do Sistema no horário de Ponta (meses) | AA2: Dias úteis no mês, de utilização do Sistema no horário de Ponta (dias) | AB2: Horas por dia, de utilização do Sistema no horário de Ponta (horas) | AC2: Fator de coincidência na ponta | AD2: Energia consumida (MWh/ano) | AE2: Demanda média na ponta (kW) | AF2: Redução de demanda na ponta (kW) | AG2: Energia economizada (MWh/ano) | AH2: Redução de consumo proposto em relação ao consumo total da UC (%)
A3: =IF(UC_DADOS!$B$2=0,"",UC_DADOS!$B$2) -> 7041435180 | H3: =C3*0.736*G3 -> 0 | I3: =H3*D3 -> 0 | K3: =J3*L3*M3 -> 0 | O3: =L3*M3*N3/765 -> 0 | P3: =(K3*I3)/1000 -> 0 | Q3: =O3*I3 -> 0 | V3: =G3 -> 0 | W3: =R3*V3*0.736 -> 0 | X3: =W3*S3 -> 0 | Y3: =K3 -> 0 | Z3: =L3 -> 0 | AA3: =M3 -> 0 | AB3: =N3 -> 0 | AC3: =Z3*AA3*AB3/765 -> 0 | AD3: =(Y3*X3)/1000 -> 0 | AE3: =AC3*X3 -> 0 | AF3: =AE3-Q3 -> 0 | AG3: =P3-AD3 -> 0 | AH3: =AG3/1000 -> 0
A4: =IF(UC_DADOS!$B$2=0,"",UC_DADOS!$B$2) -> 7041435180 | H4: =C4*0.736*G4 -> 0 | I4: =H4*D4 -> 0 | K4: =J4*L4*M4 -> 0 | O4: =L4*M4*N4/765 -> 0 | P4: =(K4*I4)/1000 -> 0 | Q4: =O4*I4 -> 0 | V4: =G4 -> 0 | W4: =R4*V4*0.736 -> 0 | X4: =W4*S4 -> 0 | Y4: =K4 -> 0 | Z4: =L4 -> 0 | AA4: =M4 -> 0 | AB4: =N4 -> 0 | AC4: =Z4*AA4*AB4/765 -> 0 | AD4: =(Y4*X4)/1000 -> 0 | AE4: =AC4*X4 -> 0 | AF4: =AE4-Q4 -> 0 | AG4: =P4-AD4 -> 0 | AH4: =AG4/1000 -> 0
A5: =IF(UC_DADOS!$B$2=0,"",UC_DADOS!$B$2) -> 7041435180 | H5: =C5*0.736*G5 -> 0 | I5: =H5*D5 -> 0 | K5: =J5*L5*M5 -> 0 | O5: =L5*M5*N5/765 -> 0 | P5: =(K5*I5)/1000 -> 0 | Q5: =O5*I5 -> 0 | V5: =G5 -> 0 | W5: =R5*V5*0.736 -> 0 | X5: =W5*S5 -> 0 | Y5: =K5 -> 0 | Z5: =L5 -> 0 | AA5: =M5 -> 0 | AB5: =N5 -> 0 | AC5: =Z5*AA5*AB5/765 -> 0 | AD5: =(Y5*X5)/1000 -> 0 | AE5: =AC5*X5 -> 0 | AF5: =AE5-Q5 -> 0 | AG5: =P5-AD5 -> 0 | AH5: =AG5/1000 -> 0
B6: TOTAL | C6: =SUM(C3:C5) -> 0 | G6: =SUM(G3:G5) -> 0 | H6: =SUM(H3:H5) -> 0 | I6: =SUM(I3:I5) -> 0 | P6: =SUM(P3:P5) -> 0 | Q6: =SUM(Q3:Q5) -> 0 | R6: =SUM(R3:R5) -> 0 | V6: =SUM(V3:V5) -> 0 | W6: =SUM(W3:W5) -> 0 | X6: =SUM(X3:X5) -> 0 | AD6: =SUM(AD3:AD5) -> 0 | AE6: =SUM(AE3:AE5) -> 0 | AF6: =SUM(AF3:AF5) -> 0 | AG6: =SUM(AG3:AG5) -> 0 | AH6: =SUM(AH3:AH5) -> 0

Sheet Sistemas de Aquecimento de Água
A1: Unidade Consumidora | C1: DADOS DO COLETOR | K1: DADOS DO RESERVATÓRIO | Q1: DADOS DO PROJETO | AA1: FATOR DE COINCIDÊNCIA NA PONTA | AD1: RESULTADOS ESPERADOS
A2: Unidade consumidora (Número da conta contrato) | B2: Descrição do sistema | C2: Fabricante coletor solar | D2: Marca e modelo do coletor solar | E2: Área externa (m²) | F2: Produção média mensal de energia (kWh/mês) | G2: Eficiência energética (%) | H2: Produção média mensal de energia por área coletora (kWh/m2×mês) | I2: Área coletora por unidade consumidora (m²) | J2: Número de coletores solares | K2: Fabricante do reservatório térmico | L2: Modelo do reservatório térmico | M2: Volume do reservatório térmico (L) | N2: Perda específica energética mensal (kWh/mês/L) | O2: Volume de água quente consumida (L) | P2: Número mínimo de reservatórios com apoio elétrico | Q2: Número médio de chuveiros por UC | R2: Potência máxima típica dos chuveiros utilizados (W) | S2: Potência média do aquecimento auxiliar | T2: Fator de coincidência na ponta | U2: Fração solar | V2: Nº médio de banhos/dia | W2: Tempo médio de banho (min) | X2: Vazão típica do chuveiro (L/min) | Y2: Cidade de referência | Z2: Fator de correção | AA2: Número médio de banhos na ponta | AB2: Tempo médio de banho (min) | AC2: Número de chuveiros por unidade consumidora | AD2: Redução de demanda na ponta (kW) | AE2: Energia economizada (MWh/ano) | AF2: Redução de consumo proposto em relação ao consumo total da UC (%)
A3: =IF(UC_DADOS!$B$2=0,"",UC_DADOS!$B$2) -> 7041435180 | I3: =J3*E3 -> 0
A4: =IF(UC_DADOS!$B$2=0,"",UC_DADOS!$B$2) -> 7041435180 | I4: =J4*E4 -> 0
A5: =IF(UC_DADOS!$B$2=0,"",UC_DADOS!$B$2) -> 7041435180 | I5: =J5*E5 -> 0
A6: =IF(UC_DADOS!$B$2=0,"",UC_DADOS!$B$2) -> 7041435180 | I6: =J6*E6 -> 0
A7: =IF(UC_DADOS!$B$2=0,"",UC_DADOS!$B$2) -> 7041435180 | I7: =J7*E7 -> 0
A8: =IF(UC_DADOS!$B$2=0,"",UC_DADOS!$B$2) -> 7041435180 | I8: =J8*E8 -> 0
A9: =IF(UC_DADOS!$B$2=0,"",UC_DADOS!$B$2) -> 7041435180 | I9: =J9*E9 -> 0
A10: =IF(UC_DADOS!$B$2=0,"",UC_DADOS!$B$2) -> 7041435180 | I10: =J10*E10 -> 0
A11: =IF(UC_DADOS!$B$2=0,"",UC_DADOS!$B$2) -> 7041435180 | I11: =J11*E11 -> 0
A12: =IF(UC_DADOS!$B$2=0,"",UC_DADOS!$B$2) -> 7041435180 | I12: =J12*E12 -> 0
A13: =IF(UC_DADOS!$B$2=0,"",UC_DADOS!$B$2) -> 7041435180 | I13: =J13*E13 -> 0
A14: =IF(UC_DADOS!$B$2=0,"",UC_DADOS!$B$2) -> 7041435180 | I14: =J14*E14 -> 0
... A100: =IF(UC_DADOS!$B$2=0,"",UC_DADOS!$B$2) -> 7041435180 | I100: =J100*E100 -> 0

Sheet Sistemas Solar Fotovoltaico
A1: Unidade Consumidora | C1: SISTEMA PROPOSTO | M1: RESULTADOS ESPERADOS
A2: Unidade consumidora (Número da conta contrato) | B2: Descrição do sistema | C2: Tipo de equipamento / tecnologia | D2: Potência nominal do sistema (W) | E2: Quantidade | F2: Potência instalada de geração (kW) | G2: Funcionamento (h/dia) | H2: Dias de funcionamento do sistema, em um ano (dia/ano) | I2: Funcionamento (h/ano) | J2: Meses no ano, de funcionamento do Sistema no horário de Ponta (meses) | K2: Dias úteis no mês, de funcionamento do Sistema no horário de Ponta (dias) | L2: Horas por dia, de funcionamento do Sistema no horário de Ponta (horas) | M2: Demanda atendida na ponta (kW) | N2: Demanda atendida fora de ponta (kW) | O2: Energia gerada na ponta (MWh/ano) | P2: Energia gerada fora de ponta (MWh/ano) | Q2: Energia gerada total (MWh/ano) | R2: Redução de consumo proposto em relação ao consumo total da UC (%)
A3: =IF(UC_DADOS!$B$2=0,"",UC_DADOS!$B$2) -> 7041435180
A4: =IF(UC_DADOS!$B$2=0,"",UC_DADOS!$B$2) -> 7041435180
A5: =IF(UC_DADOS!$B$2=0,"",UC_DADOS!$B$2) -> 7041435180
A6: =IF(UC_DADOS!$B$2=0,"",UC_DADOS!$B$2) -> 7041435180
A7: =IF(UC_DADOS!$B$2=0,"",UC_DADOS!$B$2) -> 7041435180
A8: =IF(UC_DADOS!$B$2=0,"",UC_DADOS!$B$2) -> 7041435180
A9: =IF(UC_DADOS!$B$2=0,"",UC_DADOS!$B$2) -> 7041435180
A10: =IF(UC_DADOS!$B$2=0,"",UC_DADOS!$B$2) -> 7041435180
A11: =IF(UC_DADOS!$B$2=0,"",UC_DADOS!$B$2) -> 7041435180
A12: =IF(UC_DADOS!$B$2=0,"",UC_DADOS!$B$2) -> 7041435180
A13: =IF(UC_DADOS!$B$2=0,"",UC_DADOS!$B$2) -> 7041435180
A14: =IF(UC_DADOS!$B$2=0,"",UC_DADOS!$B$2) -> 7041435180
... A100: =IF(UC_DADOS!$B$2=0,"",UC_DADOS!$B$2) -> 7041435180

Sheet Sistemas Outros
A1: Unidade Consumidora | D1: SITUAÇÃO ATUAL | R1: SISTEMA PROPOSTO | AE1: RESULTADOS ESPERADOS
A2: Unidade consumidora (Número da conta contrato) | B2: Pavimento | C2: Descrição do sistema | D2: Tipo de equipamento / tecnologia | E2: Potência nominal do equipamento (W) | F2: Quantidade | G2: Potência instalada (kW) | H2: Fator de Utilização | I2: Funcionamento (h/dia) | J2: Meses no ano, de utilização do Sistema | K2: Dias úteis no mês, de utilização do Sistema | L2: Funcionamento (h/ano) | M2: Horas por dia, de utilização do Sistema no horário de Ponta (horas) | N2: Potência média na ponta (W) | O2: Fator de coincidência na ponta | P2: Energia consumida (MWh/ano) | Q2: Demanda média na ponta (kW) | R2: Tipo de equipamento / tecnologia | S2: Potência nominal do equipamento (W) | T2: Quantidade | U2: Potência instalada (kW) | V2: Fator de Utilização | W2: Funcionamento (h/ano) | X2: Meses no ano, de utilização do Sistema no horário de Ponta (meses) | Y2: Dias úteis no mês, de utilização do Sistema no horário de Ponta (dias) | Z2: Horas por dia, de utilização do Sistema no horário de Ponta (horas) | AA2: Potência média na ponta (W) | AB2: Fator de coincidência na ponta | AC2: Energia consumida (MWh/ano) | AD2: Demanda média na ponta (kW) | AE2: Redução de demanda na ponta (kW) | AF2: Energia economizada (MWh/ano) | AG2: Redução de consumo proposto em relação ao consumo total da UC (%)
A3: =IF(UC_DADOS!$B$2=0,"",UC_DADOS!$B$2) -> 7041435180 | B3: Térreo | C3: Chuveiro Elétrico | D3: Chuveiro Elétrico | E3: 5500 | F3: 1 | G3: =E3*F3 -> 5500 | H3: 0.7 | I3: 0 | J3: 12 | K3: 21.25 | L3: =I3*J3*K3 -> 0 | M3: 0 | O3: =J3*K3*N3/765 -> 0 | P3: =(I3*J3)/1000 -> 0 | Q3: =O3*I3 -> 0
A4: =IF(UC_DADOS!$B$2=0,"",UC_DADOS!$B$2) -> 7041435180 | B4: Térreo | C4: Ventilador | D4: Vetilação | E4: 200 | F4: 1 | G4: =E4*F4 -> 200 | H4: 0.7 | I4: 0 | J4: 12 | K4: 21.25 | L4: =I4*J4*K4 -> 0 | M4: 0 | O4: =J4*K4*N4/765 -> 0 | P4: =(I4*J4)/1000 -> 0 | Q4: =O4*I4 -> 0
A5: =IF(UC_DADOS!$B$2=0,"",UC_DADOS!$B$2) -> 7041435180 | B5: Térreo | C5: Ventilador | D5: Ventilação | E5: 200 | F5: 2 | G5: =E5*F5 -> 400 | H5: 0.7 | I5: 0 | J5: 12 | K5: 21.25 | L5: =I5*J5*K5 -> 0 | M5: 0 | O5: =J5*K5*N5/765 -> 0 | P5: =(I5*J5)/1000 -> 0 | Q5: =O5*I5 -> 0
A6: =IF(UC_DADOS!$B$2=0,"",UC_DADOS!$B$2) -> 7041435180 | B6: Térreo | C6: Ventilador | D6: Ventilação | E6: 200 | F6: 2 | G6: =E6*F6 -> 400 | H6: 0.7 | I6: 0 | J6: 12 | K6: 21.25 | L6: =I6*J6*K6 -> 0 | M6: 0 | O6: =J6*K6*N6/765 -> 0 | P6: =(I6*J6)/1000 -> 0 | Q6: =O6*I6 -> 0
A7: =IF(UC_DADOS!$B$2=0,"",UC_DADOS!$B$2) -> 7041435180 | B7: Térreo | C7: Chuveiro elétrico | D7: Chuveiro elétrico | E7: 5500 | F7: 7 | G7: =E7*F7 -> 38500 | H7: 0.7 | I7: 1 | J7: 11 | K7: 21.25 | L7: =I7*J7*K7 -> 233.75 | M7: 0 | O7: =J7*K7*N7/765 -> 0 | P7: =(I7*J7)/1000 -> 0.011 | Q7: =O7*I7 -> 0
A8: =IF(UC_DADOS!$B$2=0,"",UC_DADOS!$B$2) -> 7041435180 | B8: Térreo | C8: Ventilador | D8: Ventilação | E8: 200 | F8: 1 | G8: =E8*F8 -> 200 | H8: 0.7 | I8: 0 | J8: 11 | K8: 21.25 | L8: =I8*J8*K8 -> 0 | M8: 0 | O8: =J8*K8*N8/765 -> 0 | P8: =(I8*J8)/1000 -> 0 | Q8: =O8*I8 -> 0
A9: =IF(UC_DADOS!$B$2=0,"",UC_DADOS!$B$2) -> 7041435180 | B9: Térreo | C9: Forno elétrico | D9: Forno elétrico | E9: 1500 | F9: 1 | G9: =E9*F9 -> 1500 | H9: 0.7 | I9: 0 | J9: 11 | K9: 21.25 | L9: =I9*J9*K9 -> 0 | M9: 0 | O9: =J9*K9*N9/765 -> 0 | P9: =(I9*J9)/1000 -> 0 | Q9: =O9*I9 -> 0
A10: =IF(UC_DADOS!$B$2=0,"",UC_DADOS!$B$2) -> 7041435180 | B10: Térreo | C10: Ventilador | D10: Ventilação | E10: 200 | F10: 1 | G10: =E10*F10 -> 200 | H10: 0.7 | I10: 0 | J10: 11 | K10: 21.25 | L10: =I10*J10*K10 -> 0 | M10: 0 | O10: =J10*K10*N10/765 -> 0 | P10: =(I10*J10)/1000 -> 0 | Q10: =O10*I10 -> 0
A11: =IF(UC_DADOS!$B$2=0,"",UC_DADOS!$B$2) -> 7041435180 | B11: 1 andar | C11: Ventilador | D11: Ventilação | E11: 200 | F11: 14 | G11: =E11*F11 -> 2800 | H11: 0.7 | I11: 0 | J11: 11 | K11: 21.25 | L11: =I11*J11*K11 -> 0 | M11: 0 | O11: =J11*K11*N11/765 -> 0 | P11: =(I11*J11)/1000 -> 0 | Q11: =O11*I11 -> 0
A12: =IF(UC_DADOS!$B$2=0,"",UC_DADOS!$B$2) -> 7041435180 | B12: 1 andar | C12: Chuveiro | D12: Chuveiro | E12: 5500 | F12: 8 | G12: =E12*F12 -> 44000 | H12: 0.7 | I12: 1 | J12: 11 | K12: 21.25 | L12: =I12*J12*K12 -> 233.75 | M12: 0 | O12: =J12*K12*N12/765 -> 0 | P12: =(I12*J12)/1000 -> 0.011 | Q12: =O12*I12 -> 0
A13: =IF(UC_DADOS!$B$2=0,"",UC_DADOS!$B$2) -> 7041435180 | B13: Anexo | C13: Chuveiro | D13: Chuveiro | E13: 5500 | F13: 10 | G13: =E13*F13 -> 55000 | H13: 0.7 | I13: 0 | J13: 11 | K13: 21.25 | L13: =I13*J13*K13 -> 0 | M13: 0 | O13: =J13*K13*N13/765 -> 0 | P13: =(I13*J13)/1000 -> 0 | Q13: =O13*I13 -> 0
A14: =IF(UC_DADOS!$B$2=0,"",UC_DADOS!$B$2) -> 7041435180 | B14: Anexo | C14: Ventilador | D14: Ventilação | E14: 200 | F14: 10 | G14: =E14*F14 -> 2000 | H14: 0.7 | I14: 0 | J14: 11 | K14: 21.25 | L14: =I14*J14*K14 -> 0 | M14: 0 | O14: =J14*K14*N14/765 -> 0 | P14: =(I14*J14)/1000 -> 0 | Q14: =O14*I14 -> 0
... A18: =IF(UC_DADOS!$B$2=0,"",UC_DADOS!$B$2) -> 7041435180 | B18: Térreo | C18: Área de serviço | D18: Área de serviço | E18: 200 | F18: 1 | G18: =E18*F18 -> 200 | H18: 0.7 | I18: 3 | J18: 11 | K18: 21.25 | L18: =I18*J18*K18 -> 701.25 | M18: 0 | O18: =J18*K18*N18/765 -> 0 | P18: =(I18*J18)/1000 -> 0.033 | Q18: =O18*I18 -> 0
F19: =SUM(F3:F18) -> 65 | G19: =SUM(G3:G18) -> 154840 | I19: =SUM(I3:I18) -> 14 | P19: =SUM(P3:P18) -> 0.154 | Q19: =SUM(Q3:Q10) -> 0

Sheet TABELAS_RESUMO_2
C3: Sistema de Iluminação | G3: Sistema de Refrigeração
C4: Sistema Atual | G4: Sistema Atual
C5: O sistema composto por luminárias LED, porém sem automação para acionamento e desligamento programado. | G5: Sistemas de Refrigeração com baixo índice de eficiência energética e com estado de conservação insatisfatório
C6: Potência Total (kW) | D6: ='Sistemas de Iluminação'!J24 -> 2.595 | G6: Potência Total (kW) | H6: ='Sistemas de Refrigeração'!J10 -> 0.6169
C7: Consumo de Energia Anual (MWh) | D7: ='Sistemas de Iluminação'!Q24 -> 4.2745438 | G7: Consumo de Energia Anual (MWh) | H7: ='Sistemas de Refrigeração'!R10 -> 5.330016
C8: Despesa Mensal com Energia Elétrica | D8: =(D7*'Análise Econômica'!E4)/12 -> 704.20602 | G8: Despesa Mensal com Energia Elétrica | H8: =(H7*'Análise Econômica'!E4)/12 -> 878.08888
C9: Sistema Proposto | G9: Sistema Proposto
C10: Instalação da automação para acionamento e desligamento programado. | G10: Instalação de Sistemas de Refrigeração com alto índice de eficiência energética
C11: Potência Total (kW) | D11: ='Sistemas de Iluminação'!X24 -> 6.517 | G11: Potência Total (kW) | H11: ='Sistemas de Refrigeração'!X10 -> 0.6079
C12: Consumo de Energia Anual (MWh) | D12: ='Sistemas de Iluminação'!AD24 -> 8.1315675 | G12: Consumo de Energia Anual (MWh) | H12: ='Sistemas de Refrigeração'!AF10 -> 5.252256
C13: Despesa mensal com Energia Elétrica | G13: Despesa mensal com Energia Elétrica | H13: =(H12*'Análise Econômica'!E4)/12 -> 865.27838
C14: Resultados Previstos | G14: Resultados Previstos
C15: Redução de Demanda (kW) | G15: Redução de Demanda (kW) | H15: =H6-H11 -> 0.009
C16: Redução do Consumo de Energia Anual (MWh) | G16: Redução do Consumo de Energia Anual (MWh) | H16: =H7-H12 -> 0.07776
C17: Redução Percentual do Consumo de Energia % | G17: Redução Percentual do Consumo de Energia % | H17: =H16/H7 -> 0.014589074
C18: Economia Mensal na Fatura de Energia | G18: Economia Mensal na Fatura de Energia | H18: =H8-H13 -> 12.810504
C19: Investimento Necessário Estimado | G19: Investimento Necessário Estimado | H19: ='Análise Econômica'!B59 -> 0
C23: Sistema de Condicionamento Ambiental | G23: BESS
C24: Sistema Atual | G24: Sistema Atual
C25: Sistemas de Condicionamento Ambiental com baixo índice de eficiência energética
C26: Potência Total (kW) | D26: ='Sistemas de Cond. Ambiental'!L9 -> 22.949891 | G26: Potência Total (kW)
C27: Consumo de Energia Anual (MWh) | D27: ='Sistemas de Cond. Ambiental'!S9 -> 38.194308 | G27: Consumo de Energia Anual (MWh)
C28: Despesa Mensal com Energia Elétrica | D28: =(D27*'Análise Econômica'!E4)/12 -> 6292.2883 | G28: Despesa Mensal com Energia Elétrica
C29: Sistema Proposto | G29: Sistema Proposto
C30: Instalação de Sistemas de Condicionamento Ambiental com alto índice de eficiência energética
C31: Potência Total (kW) | D31: ='Sistemas de Cond. Ambiental'!AC9 -> 21.323211 | G31: Potência Total (kW)
C32: Consumo de Energia Anual (MWh) | D32: ='Sistemas de Cond. Ambiental'!AJ9 -> 35.705488 | G32: Consumo de Energia Anual (MWh)
C33: Despesa mensal com Energia Elétrica | D33: =(D32*'Análise Econômica'!E4)/12 -> 5882.2698 | G33: Despesa mensal com Energia Elétrica
C34: Resultados Previstos | G34: Resultados Previstos
C35: Redução de Demanda (kW) | D35: =D26-D31 -> 1.6266795 | G35: Redução de Demanda (kW)
C36: Redução do Consumo de Energia Anual (MWh) | D36: =D27-D32 -> 2.4888197 | G36: Redução do Consumo de Energia Anual (MWh)
C37: Redução Percentual do Consumo de Energia % | D37: =D36/D27 -> 0.065162057 | G37: Redução Percentual do Consumo de Energia %
C38: Economia Mensal na Fatura de Energia | D38: =D28-D33 -> 410.01845 | G38: Economia Mensal na Fatura de Energia
C39: Investimento Necessário Estimado | D39: ='Análise Econômica'!Q29 -> 17182 | G39: Investimento Necessário Estimado
C43: Sistema de Condicionamento Ambiental | G43: Setorização da Medição
C44: Sistema Atual | G44: Sistema Atual
C45: Sistemas de Condicionamento Ambiental sem automação para acionamento e desligamento programado e com baixo índice de eficiência energética | G45: Uma única medição para um complexo com diversas unidades consumidoras
C46: Potência Total (kW) | D46: ='Sistemas de Cond. Ambiental'!L9 -> 22.949891 | G46: Potência Total (kW)
C47: Consumo de Energia Anual (MWh) | D47: ='Sistemas de Cond. Ambiental'!S9 -> 38.194308 | G47: Consumo de Energia Anual (MWh)
C48: Despesa Mensal com Energia Elétrica | D48: =(D47*'Análise Econômica'!E4)/12 -> 6292.2883 | G48: Despesa Mensal com Energia Elétrica
C49: Sistema Proposto | G49: Sistema Proposto
C50: Instalação de Sistemas de Condicionamento Ambiental com alto índice de eficiência energética e com automação para acionamento e desligamento programado. | G50: Instalação de uma medição para cada unidade consumidora presente no complexo
C51: Potência Total (kW) | D51: ='Sistemas de Cond. Ambiental'!AC9 -> 21.323211 | G51: Potência Total (kW)
C52: Consumo de Energia Anual (MWh) | D52: ='Sistemas de Cond. Ambiental'!AQ9 -> 32.13494 | G52: Consumo de Energia Anual (MWh)
C53: Despesa mensal com Energia Elétrica | D53: =(D52*'Análise Econômica'!E4)/12 -> 5294.0429 | G53: Despesa mensal com Energia Elétrica
C54: Resultados Previstos | G54: Resultados Previstos
C55: Redução de Demanda (kW) | D55: =D46-D51 -> 1.6266795 | G55: Redução de Demanda (kW)
C56: Redução do Consumo de Energia Anual (MWh) | D56: =D47-D52 -> 6.0593685 | G56: Redução do Consumo de Energia Anual (MWh)
C57: Redução Percentual do Consumo de Energia % | D57: =D56/D47 -> 0.15864585 | G57: Redução Percentual do Consumo de Energia %
C58: Economia Mensal na Fatura de Energia | D58: =D48-D53 -> 998.24543 | G58: Economia Mensal na Fatura de Energia
C59: Investimento Necessário Estimado | D59: ='Análise Econômica'!B29 -> 22857.3 | G59: Investimento Necessário Estimado
C63: Sistema de Condicionamento Ambiental | G63: Sistemas com Motores
C64: Sistema Atual | G64: Sistema Atual
C65: Sistemas de Condicionamento Ambiental sem automação para acionamento e desligamento programado
C66: Potência Total (kW) | D66: ='Sistemas de Cond. Ambiental'!L9 -> 22.949891 | G66: Potência Total (kW)
C67: Consumo de Energia Anual (MWh) | D67: ='Sistemas de Cond. Ambiental'!S9 -> 38.194308 | G67: Consumo de Energia Anual (MWh)
C68: Despesa Mensal com Energia Elétrica | D68: =(D67*'Análise Econômica'!E4)/12 -> 6292.2883 | G68: Despesa Mensal com Energia Elétrica
C69: Sistema Proposto | G69: Sistema Proposto
C70: Instalação da automação para acionamento e desligamento programado.
C71: Potência Total (kW) | D71: ='Sistemas de Cond. Ambiental'!L9 -> 22.949891 | G71: Potência Total (kW)
C72: Consumo de Energia Anual (MWh) | D72: ='Sistemas de Cond. Ambiental'!AP9 -> 34.374877 | G72: Consumo de Energia Anual (MWh)
C73: Despesa mensal com Energia Elétrica | D73: =(D72*'Análise Econômica'!E4)/12 -> 5663.0595 | G73: Despesa mensal com Energia Elétrica
C74: Resultados Previstos | G74: Resultados Previstos
C75: Redução de Demanda (kW) | D75: =D66-D71 -> 0 | G75: Redução de Demanda (kW)
C76: Redução do Consumo de Energia Anual (MWh) | D76: =D67-D72 -> 3.8194308 | G76: Redução do Consumo de Energia Anual (MWh)
C77: Redução Percentual do Consumo de Energia % | D77: =D76/D67 -> 0.1 | G77: Redução Percentual do Consumo de Energia %
C78: Economia Mensal na Fatura de Energia | D78: =D68-D73 -> 629.22883 | G78: Economia Mensal na Fatura de Energia
C79: Investimento Necessário Estimado | D79: ='Análise Econômica'!AQ29 -> 28247.3 | G79: Investimento Necessário Estimado

Sheet TABELAS_RESUMO
A1: Uso Final | B1: Medida Proposta | C1: Economia (MWh/ano) | D1: Redução de demanda (kW) | E1: Investimento (R$) | F1: Prioridade
A2: iluminação | B2: Substituição por LED e sensores de presença
A3: Climatização | B3: Troca de aparelhos de ar-condicionado e automação
A4: Motores | B4: Substituição por motores de alto rendimento
A5: Refrigeração | B5: Substituição de equipamentos antigos
A6: Aquecimento de água | B6: Instalação de sistema solar térmico
A7: Fotovoltaico | B7: Implantação de sistema de geração distribuída
A10: Uso final | B10: Medida Proposta | C10: Economia (MWh/ano) | D10: Invest. Total (R$) | E10: PB (Anos)
A12: Iluminação | B12: Substituição por LED e sensores
A13: Climatização | B13: Troca de aparelhos de ar-condicionado e automação
A14: Motores | B14: Substituição por motores de alto rendimento
A15: Refrigeração | B15: Troca de refrigeradores comerciais ineficientes
A16: Geração fotovoltaica | B16: Sistema conectado à rede (GD)
A17: Total

Sheet CONSUMO_EQP
A1: Distribuição do Consumo | B1: (kWh) | C1: (%)
A2: Iluminação | B2: {=IFERROR(LOOKUP(2,1/ISNUMBER('Sistemas de Iluminação'!Q:Q),'Sistemas de Iluminação'!Q:Q),0)} -> 4.2745438 | C2: =(B2/$B$7)*100 -> 8.9140524
A3: Climatização | B3: {=IFERROR(LOOKUP(2,1/ISNUMBER('Sistemas de Cond. Ambiental'!S:S),'Sistemas de Cond. Ambiental'!S:S),0)} -> 38.194308 | C3: =(B3/$B$7)*100 -> 79.649685
A4: Sistemas Motrizes | B4: {=IFERROR(LOOKUP(2,1/ISNUMBER('Sistemas de Motor'!P:P),'Sistemas de Motor'!P:P),0)} -> 0 | C4: =(B4/$B$7)*100 -> 0
A5: Refrigeração | B5: {=IFERROR(LOOKUP(2,1/ISNUMBER('Sistemas de Refrigeração'!R:R),'Sistemas de Refrigeração'!R:R),0)} -> 5.330016 | C5: =(B5/$B$7)*100 -> 11.115114
A6: Outros | B6: {=IFERROR(LOOKUP(2,1/ISNUMBER('Sistemas Outros'!P:P),'Sistemas Outros'!P:P),0)} -> 0.154 | C6: =(B6/$B$7)*100 -> 0.32114868
A7: Total | B7: =SUM(B2:B6) -> 47.952868 | C7: =(B7/$B$7)*100 -> 100

Sheet Análise Econômica
A2: Premissas | D2: Custo Un. do Mwh | G2: Custos Operacionais | J2: Redução de Consmo (Automação do Sistema)
A3: Descrição | B3: Alíquotas | D3: Metodologia | E3: R$/MWh | G3: Mão de obra - Substituição | H3: 712.5 | J3: Metodologia | K3: Economia (%)
A4: IRPJ e CSSL | B4: 0 | D4: Direta | E4: {=(MEDIAN(_xlfn._xlws.FILTER(FATURAS!AQ1:AQ3,FATURAS!AQ1:AQ3>0))*_xlfn.XLOOKUP(MAX(FATURAS!M1:M3),FATURAS!M1:M3,FATURAS!BR1:BR3)+MEDIAN(_xlfn._xlws.FILTER(FATURAS!AR1:AR3,FATURAS!AR1:AR3>0))*_xlfn.XLOOKUP(MAX(FATURAS!M1:M3),FATURAS!M1:M3,FATURAS!BS1:BS3)+MEDIAN(_xlfn._xlws.FILTER(FATURAS!AZ1:AZ3,FATURAS!AZ1:AZ3>0))*_xlfn.XLOOKUP(MAX(FATURAS!M1:M3),FATURAS!M1:M3,FATURAS!BV1:BV3))/(MEDIAN(_xlfn._xlws.FILTER(FATURAS!AQ1:AQ3,FATURAS!AQ1:AQ3>0))+MEDIAN(_xlfn._xlws.FILTER(FATURAS!AR1:AR3,FATURAS!AR1:AR3>0)))*1000} -> 1976.9296 | G4: Mão de obra - Intalação completa | H4: 1462.5 | J4: Enermatch | K4: 0.1
A5: TMA a.a. | B5: 0.15 | D5: Indireta | E5: =(_xlfn.XLOOKUP(MAX(FATURAS!M:M),FATURAS!M:M,FATURAS!AF:AF)*_xlfn.XLOOKUP(MAX(FATURAS!M:M),FATURAS!M:M,FATURAS!CG:CG)+_xlfn.XLOOKUP(MAX(FATURAS!M:M),FATURAS!M:M,FATURAS!AZ:AZ)*_xlfn.XLOOKUP(MAX(FATURAS!M:M),FATURAS!M:M,FATURAS!BV:BV))/_xlfn.XLOOKUP(MAX(FATURAS!M:M),FATURAS!M:M,FATURAS!AF:AF)*1000 -> 1444.6708 | G5: Aquisição do Equipamento + Software (P/ Ponto) | H5: 179.9
G6: Mensalidade de Software (P/ Ponto) | H6: 9.9 | J6: Sistemas de Iluminação
J7: Contagem de Pontos | K7: {=COUNTA(_xlfn.UNIQUE(_xlfn._xlws.FILTER('Sistemas de Iluminação'!B4:B1048576,'Sistemas de Iluminação'!B4:B1048576<>"","")))} -> 3
J8: Mão de obra | K8: 120
D9: Fator de correção
D10: Faturas | E10: =UC_DADOS!G50 -> 18.74248
D11: Levantamento | E11: ='Sistemas de Cond. Ambiental'!S9+'Sistemas de Iluminação'!Q24+'Sistemas de Refrigeração'!R10+'Sistemas de Motor'!P6+'Sistemas de Aquecimento de Água'!N11 -> 47.798868
D12: Fator | E12: =E10/E11 -> 0.39211138 | AR12: OPÇÃO RECOMENDADA — Cond. Ambiental
D13: =IF(AND(E12>=0.9,E12<=1.1),"✓ OK — Fator próximo de 1", IF(AND(E12>=0.8,E12<=1.2),"⚠ Aceitável — revisar horários se possível", IF(E12<0.8,"❌ Levantamento SUPERIOR às faturas — REDUZIR horas de operação dos equipamentos", "❌ Levantamento INFERIOR às faturas — AUMENTAR horas de operação dos equipamentos"))) -> ❌ Levantamento SUPERIOR às faturas — REDUZIR horas de operação dos equipamentos | AR13: Indicador | AS13: T1 — Subst. + Automação | AT13: T2 — Substituição | AU13: T3 — Automação (sem troca) | AV13: Solução escolhida: | AW13: =IF(C32=MAX(C32,R32,AG32),"T1 — Combinado (Substituição + Automação)",IF(R32=MAX(C32,R32,AG32),"T2 — Substituição (com mão de obra)","T3 — Automação (sem troca)")) -> T1 — Combinado (Substituição + Automação)
AR14: Investimento (R$) | AS14: =-B24 -> 22857.3 | AT14: =-Q24 -> 17182 | AU14: =-AF24 -> 5675.3 | AV14: Investimento Total: | AW14: =IF(C32=MAX(C32,R32,AG32),-B24,IF(R32=MAX(C32,R32,AG32),-Q24,-AF24)) -> 22857.3
AR15: Economia Anual (R$/ano) | AS15: =C25 -> 11978.945 | AT15: =R25 -> 4920.2213 | AU15: =AG25 -> 7550.7459 | AV15: Economia Anual de Energia: | AW15: =IF(C32=MAX(C32,R32,AG32),C25,IF(R32=MAX(C32,R32,AG32),R25,AG25)) -> 11978.945
AR16: VPL — 10 anos (R$) | AS16: =C32 -> 25933.89 | AT16: =R32 -> 7511.4525 | AU16: =AG32 -> 20891.782 | AV16: VPL (10 anos, TMA 15% a.a.): | AW16: =MAX(C32,R32,AG32) -> 25933.89
AR17: TIR (% a.a.) | AS17: =C30 -> 0.41180342 | AT17: =R30 -> 0.25736602 | AU17: =AG30 -> 0.93144308 | AV17: RBC (Razão Benefício/Custo): | AW17: =IF(C32=MAX(C32,R32,AG32),C31,IF(R32=MAX(C32,R32,AG32),R31,AG31)) -> 1.1345999
AR18: RBC (Razão Benefício/Custo) | AS18: =C31 -> 1.1345999 | AT18: =R31 -> 0.43716986 | AU18: =AG31 -> 3.6811767 | AV18: Payback Simples: | AW18: =IF(C32=MAX(C32,R32,AG32),C33,IF(R32=MAX(C32,R32,AG32),R33,AG33)) -> 2.3511519
AR19: Payback Simples (anos) | AS19: =C33 -> 2.3511519 | AT19: =R33 -> 3.4921193 | AU19: =AG33 -> 1.0721169 | AV19: Justificativa: | AW19: Maior VPL absoluto entre as três opções avaliadas
AR20: VPL da opção escolhida: | AS20: =IF(C32=MAX(C32,R32,AG32),"T1 — Combinado (Substituição + Automação)",IF(R32=MAX(C32,R32,AG32),"T2 — Substituição (com mão de obra)","T3 — Automação (sem troca)")) -> T1 — Combinado (Substituição + Automação)
A22: Sistema de Cond. Ambiental - Combinado (Substituição + Automação) | P22: Sistema de Cond. Ambiental - Com mão de obra | AE22: Sistema de Cond. Ambiental - Sistema Automatizado (sem troca)
A23: Ano | B23: 0 | C23: 1 | D23: 2 | E23: 3 | F23: 4 | G23: 5 | H23: 6 | I23: 7 | J23: 8 | K23: 9 | L23: 10 | P23: Ano | Q23: 0 | R23: 1 | S23: 2 | T23: 3 | U23: 4 | V23: 5 | W23: 6 | X23: 7 | Y23: 8 | Z23: 9 | AA23: 10 | AE23: Ano | AF23: 0 | AG23: 1 | AH23: 2 | AI23: 3 | AJ23: 4 | AK23: 5 | AL23: 6 | AM23: 7 | AN23: 8 | AO23: 9 | AP23: 10
A24: Investimento : | B24: {=-(SUMPRODUCT(('Sistemas de Cond. Ambiental'!C3:C896<>"")*'Sistemas de Cond. Ambiental'!AN3:AN896)+(H3*SUMPRODUCT(('Sistemas de Cond. Ambiental'!C3:C896<>"")*('Sistemas de Cond. Ambiental'!AM3:AM896<>0)*'Sistemas de Cond. Ambiental'!Z3:Z896))+(H5*SUMPRODUCT(('Sistemas de Cond. Ambiental'!C3:C896<>"")*'Sistemas de Cond. Ambiental'!I3:I896))+(H6*12*SUMPRODUCT(('Sistemas de Cond. Ambiental'!C3:C896<>"")*'Sistemas de Cond. Ambiental'!I3:I896)))} -> -22857.3 | C24: =-($H$6*12*SUMPRODUCT(('Sistemas de Cond. Ambiental'!C3:C896<>"")*'Sistemas de Cond. Ambiental'!I3:I896)) -> -2257.2 | D24: =-($H$6*12*SUMPRODUCT(('Sistemas de Cond. Ambiental'!C3:C896<>"")*'Sistemas de Cond. Ambiental'!I3:I896)) -> -2257.2 | E24: =-($H$6*12*SUMPRODUCT(('Sistemas de Cond. Ambiental'!C3:C896<>"")*'Sistemas de Cond. Ambiental'!I3:I896)) -> -2257.2 | F24: =-($H$6*12*SUMPRODUCT(('Sistemas de Cond. Ambiental'!C3:C896<>"")*'Sistemas de Cond. Ambiental'!I3:I896)) -> -2257.2 | G24: =-($H$6*12*SUMPRODUCT(('Sistemas de Cond. Ambiental'!C3:C896<>"")*'Sistemas de Cond. Ambiental'!I3:I896)) -> -2257.2 | H24: =-($H$6*12*SUMPRODUCT(('Sistemas de Cond. Ambiental'!C3:C896<>"")*'Sistemas de Cond. Ambiental'!I3:I896)) -> -2257.2 | I24: =-($H$6*12*SUMPRODUCT(('Sistemas de Cond. Ambiental'!C3:C896<>"")*'Sistemas de Cond. Ambiental'!I3:I896)) -> -2257.2 | J24: =-($H$6*12*SUMPRODUCT(('Sistemas de Cond. Ambiental'!C3:C896<>"")*'Sistemas de Cond. Ambiental'!I3:I896)) -> -2257.2 | K24: =-($H$6*12*SUMPRODUCT(('Sistemas de Cond. Ambiental'!C3:C896<>"")*'Sistemas de Cond. Ambiental'!I3:I896)) -> -2257.2 | L24: =-($H$6*12*SUMPRODUCT(('Sistemas de Cond. Ambiental'!C3:C896<>"")*'Sistemas de Cond. Ambiental'!I3:I896)) -> -2257.2 | P24: Investimento : | Q24: {=-(SUMPRODUCT(('Sistemas de Cond. Ambiental'!C3:C896<>"")*'Sistemas de Cond. Ambiental'!AN3:AN896)+(H3*SUMPRODUCT(('Sistemas de Cond. Ambiental'!C3:C896<>"")*('Sistemas de Cond. Ambiental'!AM3:AM896<>0)*'Sistemas de Cond. Ambiental'!Z3:Z896)))} -> -17182 | R24: 0 | S24: 0 | T24: 0 | U24: 0 | V24: 0 | W24: 0 | X24: 0 | Y24: 0 | Z24: 0 | AA24: 0 | AE24: Investimento : | AF24: =-((SUMPRODUCT(('Sistemas de Cond. Ambiental'!C3:C896<>"")*'Sistemas de Cond. Ambiental'!I3:I896)*H5)+(H6*12*SUMPRODUCT(('Sistemas de Cond. Ambiental'!C3:C896<>"")*'Sistemas de Cond. Ambiental'!I3:I896))) -> -5675.3 | AG24: =-($H$6*12*SUMPRODUCT(('Sistemas de Cond. Ambiental'!C3:C896<>"")*'Sistemas de Cond. Ambiental'!I3:I896)) -> -2257.2 | AH24: =-($H$6*12*SUMPRODUCT(('Sistemas de Cond. Ambiental'!C3:C896<>"")*'Sistemas de Cond. Ambiental'!I3:I896)) -> -2257.2 | AI24: =-($H$6*12*SUMPRODUCT(('Sistemas de Cond. Ambiental'!C3:C896<>"")*'Sistemas de Cond. Ambiental'!I3:I896)) -> -2257.2 | AJ24: =-($H$6*12*SUMPRODUCT(('Sistemas de Cond. Ambiental'!C3:C896<>"")*'Sistemas de Cond. Ambiental'!I3:I896)) -> -2257.2 | AK24: =-($H$6*12*SUMPRODUCT(('Sistemas de Cond. Ambiental'!C3:C896<>"")*'Sistemas de Cond. Ambiental'!I3:I896)) -> -2257.2 | AL24: =-($H$6*12*SUMPRODUCT(('Sistemas de Cond. Ambiental'!C3:C896<>"")*'Sistemas de Cond. Ambiental'!I3:I896)) -> -2257.2 | AM24: =-($H$6*12*SUMPRODUCT(('Sistemas de Cond. Ambiental'!C3:C896<>"")*'Sistemas de Cond. Ambiental'!I3:I896)) -> -2257.2 | AN24: =-($H$6*12*SUMPRODUCT(('Sistemas de Cond. Ambiental'!C3:C896<>"")*'Sistemas de Cond. Ambiental'!I3:I896)) -> -2257.2 | AO24: =-($H$6*12*SUMPRODUCT(('Sistemas de Cond. Ambiental'!C3:C896<>"")*'Sistemas de Cond. Ambiental'!I3:I896)) -> -2257.2 | AP24: =-($H$6*12*SUMPRODUCT(('Sistemas de Cond. Ambiental'!C3:C896<>"")*'Sistemas de Cond. Ambiental'!I3:I896)) -> -2257.2
A25: Redução de Custos de Energia: | B25: 0 | C25: {=(SUMPRODUCT(('Sistemas de Cond. Ambiental'!C3:C896<>"")*'Sistemas de Cond. Ambiental'!AM3:AM896)+(SUMPRODUCT(('Sistemas de Cond. Ambiental'!C3:C896<>"")*'Sistemas de Cond. Ambiental'!S3:S896)-SUMPRODUCT(('Sistemas de Cond. Ambiental'!C3:C896<>"")*'Sistemas de Cond. Ambiental'!AM3:AM896))*$K$4)*$E$4} -> 11978.945 | D25: =C25 -> 11978.945 | E25: =D25 -> 11978.945 | F25: =E25 -> 11978.945 | G25: =F25 -> 11978.945 | H25: =G25 -> 11978.945 | I25: =H25 -> 11978.945 | J25: =I25 -> 11978.945 | K25: =J25 -> 11978.945 | L25: =K25 -> 11978.945 | P25: Redução de Custos de Energia: | Q25: 0 | R25: =SUMPRODUCT(('Sistemas de Cond. Ambiental'!C3:C896<>"")*'Sistemas de Cond. Ambiental'!AM3:AM896)*'Análise Econômica'!E4 -> 4920.2213 | S25: =R25 -> 4920.2213 | T25: =S25 -> 4920.2213 | U25: =T25 -> 4920.2213 | V25: =U25 -> 4920.2213 | W25: =V25 -> 4920.2213 | X25: =W25 -> 4920.2213 | Y25: =X25 -> 4920.2213 | Z25: =Y25 -> 4920.2213 | AA25: =Z25 -> 4920.2213 | AE25: Redução de Custos de Energia: | AF25: 0 | AG25: =SUMPRODUCT(('Sistemas de Cond. Ambiental'!C3:C896<>"")*'Sistemas de Cond. Ambiental'!S3:S896)*$K$4*$E$4 -> 7550.7459 | AH25: =AG25 -> 7550.7459 | AI25: =AH25 -> 7550.7459 | AJ25: =AI25 -> 7550.7459 | AK25: =AJ25 -> 7550.7459 | AL25: =AK25 -> 7550.7459 | AM25: =AL25 -> 7550.7459 | AN25: =AM25 -> 7550.7459 | AO25: =AN25 -> 7550.7459 | AP25: =AO25 -> 7550.7459
A26: Fluxo de Caixa: | B26: =SUM(B24:B25) -> -22857.3 | C26: =SUM(C24:C25) -> 9721.7451 | D26: =SUM(D24:D25) -> 9721.7451 | E26: =SUM(E24:E25) -> 9721.7451 | F26: =SUM(F24:F25) -> 9721.7451 | G26: =SUM(G24:G25) -> 9721.7451 | H26: =SUM(H24:H25) -> 9721.7451 | I26: =SUM(I24:I25) -> 9721.7451 | ... L26: =SUM(L24:L25) -> 9721.7451 | P26: Fluxo de Caixa: | Q26: =SUM(Q24:Q25) -> -17182 | R26: =SUM(R24:R25) -> 4920.2213 | S26: =SUM(S24:S25) -> 4920.2213 | T26: =SUM(T24:T25) -> 4920.2213 | U26: =SUM(U24:U25) -> 4920.2213 | V26: =SUM(V24:V25) -> 4920.2213 | W26: =SUM(W24:W25) -> 4920.2213 | X26: =SUM(X24:X25) -> 4920.2213 | ... AA26: =SUM(AA24:AA25) -> 4920.2213 | AE26: Fluxo de Caixa: | AF26: =SUM(AF24:AF25) -> -5675.3 | AG26: =SUM(AG24:AG25) -> 5293.5459 | AH26: =SUM(AH24:AH25) -> 5293.5459 | AI26: =SUM(AI24:AI25) -> 5293.5459 | AJ26: =SUM(AJ24:AJ25) -> 5293.5459 | AK26: =SUM(AK24:AK25) -> 5293.5459 | AL26: =SUM(AL24:AL25) -> 5293.5459 | AM26: =SUM(AM24:AM25) -> 5293.5459 | ... AP26: =SUM(AP24:AP25) -> 5293.5459
B28: =B26/(1+$B$5)^(B23) -> -22857.3 | C28: =C26/(1+$B$5)^(C23)+B28 -> -14403.609 | D28: =D26/(1+$B$5)^(D23)+C28 -> -7052.5725 | E28: =E26/(1+$B$5)^(E23)+D28 -> -660.3673 | F28: =F26/(1+$B$5)^(F23)+E28 -> 4898.072 | G28: =G26/(1+$B$5)^(G23)+F28 -> 9731.4976 | H28: =H26/(1+$B$5)^(H23)+G28 -> 13934.476 | I28: =I26/(1+$B$5)^(I23)+H28 -> 17589.24 | J28: =J26/(1+$B$5)^(J23)+I28 -> 20767.296 | ... L28: =L26/(1+$B$5)^(L23)+K28 -> 25933.89 | Q28: =Q26/(1+$B$5)^(Q23) -> -17182 | R28: =R26/(1+$B$5)^(R23)+Q28 -> -12903.547 | S28: =S26/(1+$B$5)^(S23)+R28 -> -9183.1524 | T28: =T26/(1+$B$5)^(T23)+S28 -> -5948.027 | U28: =U26/(1+$B$5)^(U23)+T28 -> -3134.8745 | V28: =V26/(1+$B$5)^(V23)+U28 -> -688.65493 | W28: =W26/(1+$B$5)^(W23)+V28 -> 1438.4925 | X28: =X26/(1+$B$5)^(X23)+W28 -> 3288.186 | Y28: =Y26/(1+$B$5)^(Y23)+X28 -> 4896.6151 | ... AA28: =AA26/(1+$B$5)^(AA23)+Z28 -> 7511.4525 | AF28: =AF26/(1+$B$5)^(AF23) -> -5675.3 | AG28: =AG26/(1+$B$5)^(AG23)+AF28 -> -1072.2166 | AH28: =AH26/(1+$B$5)^(AH23)+AG28 -> 2930.4647 | AI28: =AI26/(1+$B$5)^(AI23)+AH28 -> 6411.057 | AJ28: =AJ26/(1+$B$5)^(AJ23)+AI28 -> 9437.6591 | AK28: =AK26/(1+$B$5)^(AK23)+AJ28 -> 12069.487 | AL28: =AL26/(1+$B$5)^(AL23)+AK28 -> 14358.033 | AM28: =AM26/(1+$B$5)^(AM23)+AL28 -> 16348.073 | AN28: =AN26/(1+$B$5)^(AN23)+AM28 -> 18078.543 | ... AP28: =AP26/(1+$B$5)^(AP23)+AO28 -> 20891.782
B29: {=(SUMPRODUCT(('Sistemas de Cond. Ambiental'!C3:C896<>"")*'Sistemas de Cond. Ambiental'!AN3:AN896)+(H3*SUMPRODUCT(('Sistemas de Cond. Ambiental'!C3:C896<>"")*('Sistemas de Cond. Ambiental'!AM3:AM896<>0)*'Sistemas de Cond. Ambiental'!Z3:Z896))+(H5*SUMPRODUCT(('Sistemas de Cond. Ambiental'!C3:C896<>"")*'Sistemas de Cond. Ambiental'!I3:I896))+(H6*12*SUMPRODUCT(('Sistemas de Cond. Ambiental'!C3:C896<>"")*'Sistemas de Cond. Ambiental'!I3:I896)))} -> 22857.3 | Q29: {=(SUMPRODUCT(('Sistemas de Cond. Ambiental'!C3:C896<>"")*'Sistemas de Cond. Ambiental'!AN3:AN896)+(H3*SUMPRODUCT(('Sistemas de Cond. Ambiental'!C3:C896<>"")*('Sistemas de Cond. Ambiental'!AM3:AM896<>0)*'Sistemas de Cond. Ambiental'!Z3:Z896)))} -> 17182 | AF29: {=((SUMPRODUCT(('Sistemas de Cond. Ambiental'!C3:C896<>"")*'Sistemas de Cond. Ambiental'!I3:I896)*H5)+(H6*12*SUMPRODUCT(('Sistemas de Cond. Ambiental'!C3:C896<>"")*'Sistemas de Cond. Ambiental'!I3:I896)))} -> 5675.3 | AG29: {=($H$6*12*SUMPRODUCT(('Sistemas de Cond. Ambiental'!C3:C896<>"")*'Sistemas de Cond. Ambiental'!I3:I896))} -> 2257.2 | AH29: {=($H$6*12*SUMPRODUCT(('Sistemas de Cond. Ambiental'!C3:C896<>"")*'Sistemas de Cond. Ambiental'!I3:I896))} -> 2257.2 | AI29: {=($H$6*12*SUMPRODUCT(('Sistemas de Cond. Ambiental'!C3:C896<>"")*'Sistemas de Cond. Ambiental'!I3:I896))} -> 2257.2 | AJ29: {=($H$6*12*SUMPRODUCT(('Sistemas de Cond. Ambiental'!C3:C896<>"")*'Sistemas de Cond. Ambiental'!I3:I896))} -> 2257.2 | AK29: {=($H$6*12*SUMPRODUCT(('Sistemas de Cond. Ambiental'!C3:C896<>"")*'Sistemas de Cond. Ambiental'!I3:I896))} -> 2257.2 | AL29: {=($H$6*12*SUMPRODUCT(('Sistemas de Cond. Ambiental'!C3:C896<>"")*'Sistemas de Cond. Ambiental'!I3:I896))} -> 2257.2 | AM29: {=($H$6*12*SUMPRODUCT(('Sistemas de Cond. Ambiental'!C3:C896<>"")*'Sistemas de Cond. Ambiental'!I3:I896))} -> 2257.2 | AN29: {=($H$6*12*SUMPRODUCT(('Sistemas de Cond. Ambiental'!C3:C896<>"")*'Sistemas de Cond. Ambiental'!I3:I896))} -> 2257.2 | AO29: {=($H$6*12*SUMPRODUCT(('Sistemas de Cond. Ambiental'!C3:C896<>"")*'Sistemas de Cond. Ambiental'!I3:I896))} -> 2257.2 | AP29: {=($H$6*12*SUMPRODUCT(('Sistemas de Cond. Ambiental'!C3:C896<>"")*'Sistemas de Cond. Ambiental'!I3:I896))} -> 2257.2 | AQ29: =SUM(AF29:AP29) -> 28247.3
B30: TIR ===> | C30: =IFERROR(IRR(B26:L26),"N/A") -> 0.41180342 | Q30: TIR ===> | R30: =IFERROR(IRR(Q26:AA26),"N/A") -> 0.25736602 | AF30: TIR ===> | AG30: =IFERROR(IRR(AF26:AP26),"N/A") -> 0.93144308
B31: RBC ===> | C31: =C32/-B28 -> 1.1345999 | Q31: RBC ===> | R31: =R32/-Q28 -> 0.43716986 | AF31: RBC ===> | AG31: =AG32/-AF28 -> 3.6811767
B32: VPL ===> | C32: =B26+NPV($B$5,C26:L26) -> 25933.89 | Q32: VPL ===> | R32: =Q26+NPV($B$5,R26:AA26) -> 7511.4525 | AF32: VPL ===> | AG32: =AF26+NPV($B$5,AG26:AP26) -> 20891.782
B33: PBS ===> | C33: =(-1*B24)/C26 -> 2.3511519 | D33: ano | Q33: PBS ===> | R33: =(-1*Q24)/R26 -> 3.4921193 | S33: ano | AF33: PBS ===> | AG33: =(-1*AF24)/AG26 -> 1.0721169 | AH33: ano
B34: ECONOMIA (MWh/ano) ===> | C34: =C25/$E$4 -> 6.0593685 | Q34: ECONOMIA (MWh/ano) ===> | R34: =R25/$E$4 -> 2.4888197 | AF34: ECONOMIA (MWh/ano) ===> | AG34: =AG25/$E$4 -> 3.8194308
A37: Iluminação - Sistema Automatizado (sem troca) | P37: Motores | AE37: Setorização da Medição
A38: Ano | B38: 0 | C38: 1 | D38: 2 | E38: 3 | F38: 4 | G38: 5 | H38: 6 | I38: 7 | J38: 8 | K38: 9 | L38: 10 | P38: Ano | Q38: 0 | R38: 1 | S38: 2 | T38: 3 | U38: 4 | V38: 5 | W38: 6 | X38: 7 | Y38: 8 | Z38: 9 | AA38: 10 | AE38: Ano | AF38: 0 | AG38: 1 | AH38: 2 | AI38: 3 | AJ38: 4 | AK38: 5 | AL38: 6 | AM38: 7 | AN38: 8 | AO38: 9 | AP38: 10
A39: Investimento : | B39: =-($K$7*($H$5+$K$8)) -> -899.7 | C39: =-($H$6*12*$K$7) -> -356.4 | D39: =-($H$6*12*$K$7) -> -356.4 | E39: =-($H$6*12*$K$7) -> -356.4 | F39: =-($H$6*12*$K$7) -> -356.4 | G39: =-($H$6*12*$K$7) -> -356.4 | H39: =-($H$6*12*$K$7) -> -356.4 | I39: =-($H$6*12*$K$7) -> -356.4 | J39: =-($H$6*12*$K$7) -> -356.4 | ... L39: =-($H$6*12*$K$7) -> -356.4 | P39: Investimento : | Q39: =-((W5*(COUNTA('Sistemas de Iluminação'!S:S)-1))+(W6*12*(COUNTA('Sistemas de Iluminação'!S:S)-1))) -> 0 | R39: =-($H$6*12*(COUNTA('Sistemas de Iluminação'!$C:$C)-1)) -> -2376 | S39: =-($H$6*12*(COUNTA('Sistemas de Iluminação'!$C:$C)-1)) -> -2376 | T39: =-($H$6*12*(COUNTA('Sistemas de Iluminação'!$C:$C)-1)) -> -2376 | U39: =-($H$6*12*(COUNTA('Sistemas de Iluminação'!$C:$C)-1)) -> -2376 | V39: =-($H$6*12*(COUNTA('Sistemas de Iluminação'!$C:$C)-1)) -> -2376 | W39: =-($H$6*12*(COUNTA('Sistemas de Iluminação'!$C:$C)-1)) -> -2376 | X39: =-($H$6*12*(COUNTA('Sistemas de Iluminação'!$C:$C)-1)) -> -2376 | Y39: =-($H$6*12*(COUNTA('Sistemas de Iluminação'!$C:$C)-1)) -> -2376 | ... AA39: =-($H$6*12*(COUNTA('Sistemas de Iluminação'!$C:$C)-1)) -> -2376 | AE39: Investimento : | AF39: =-((AL5*(COUNTA('Sistemas de Iluminação'!AH:AH)-1))+(AL6*12*(COUNTA('Sistemas de Iluminação'!AH:AH)-1))) -> 0 | AG39: =-($H$6*12*(COUNTA('Sistemas de Iluminação'!$C:$C)-1)) -> -2376 | AH39: =-($H$6*12*(COUNTA('Sistemas de Iluminação'!$C:$C)-1)) -> -2376 | AI39: =-($H$6*12*(COUNTA('Sistemas de Iluminação'!$C:$C)-1)) -> -2376 | AJ39: =-($H$6*12*(COUNTA('Sistemas de Iluminação'!$C:$C)-1)) -> -2376 | AK39: =-($H$6*12*(COUNTA('Sistemas de Iluminação'!$C:$C)-1)) -> -2376 | AL39: =-($H$6*12*(COUNTA('Sistemas de Iluminação'!$C:$C)-1)) -> -2376 | AM39: =-($H$6*12*(COUNTA('Sistemas de Iluminação'!$C:$C)-1)) -> -2376 | AN39: =-($H$6*12*(COUNTA('Sistemas de Iluminação'!$C:$C)-1)) -> -2376 | ... AP39: =-($H$6*12*(COUNTA('Sistemas de Iluminação'!$C:$C)-1)) -> -2376
A40: Redução de Custos de Energia: | B40: 0 | C40: =SUMPRODUCT(('Sistemas de Iluminação'!C4:C781<>"")*'Sistemas de Iluminação'!Q4:Q781)*$K$4*$E$4 -> 845.04722 | D40: =C40 -> 845.04722 | E40: =C40 -> 845.04722 | F40: =C40 -> 845.04722 | G40: =C40 -> 845.04722 | H40: =C40 -> 845.04722 | I40: =C40 -> 845.04722 | J40: =C40 -> 845.04722 | K40: =C40 -> 845.04722 | L40: =C40 -> 845.04722 | P40: Redução de Custos de Energia: | Q40: 0 | R40: =SUMPRODUCT(('Sistemas de Iluminação'!S4:S781<>"")*'Sistemas de Iluminação'!AF4:AF781)*$K$4*$E$4 -> 0 | S40: =R40 -> 0 | T40: =R40 -> 0 | U40: =R40 -> 0 | V40: =R40 -> 0 | W40: =R40 -> 0 | X40: =R40 -> 0 | Y40: =R40 -> 0 | Z40: =R40 -> 0 | AA40: =R40 -> 0 | AE40: Redução de Custos de Energia: | AF40: 0 | AG40: =SUMPRODUCT(('Sistemas de Iluminação'!AH4:AH781<>"")*'Sistemas de Iluminação'!AU4:AU781)*$K$4*$E$4 -> 0 | AH40: =AG40 -> 0 | AI40: =AG40 -> 0 | AJ40: =AG40 -> 0 | AK40: =AG40 -> 0 | AL40: =AG40 -> 0 | AM40: =AG40 -> 0 | AN40: =AG40 -> 0 | AO40: =AG40 -> 0 | AP40: =AG40 -> 0
A41: Fluxo de Caixa: | B41: =SUM(B39:B40) -> -899.7 | C41: =SUM(C39:C40) -> 488.64722 | D41: =SUM(D39:D40) -> 488.64722 | E41: =SUM(E39:E40) -> 488.64722 | F41: =SUM(F39:F40) -> 488.64722 | G41: =SUM(G39:G40) -> 488.64722 | H41: =SUM(H39:H40) -> 488.64722 | I41: =SUM(I39:I40) -> 488.64722 | ... L41: =SUM(L39:L40) -> 488.64722 | P41: Fluxo de Caixa: | Q41: =SUM(Q39:Q40) -> 0 | R41: =SUM(R39:R40) -> -2376 | S41: =SUM(S39:S40) -> -2376 | T41: =SUM(T39:T40) -> -2376 | U41: =SUM(U39:U40) -> -2376 | V41: =SUM(V39:V40) -> -2376 | W41: =SUM(W39:W40) -> -2376 | X41: =SUM(X39:X40) -> -2376 | ... AA41: =SUM(AA39:AA40) -> -2376 | AE41: Fluxo de Caixa: | AF41: =SUM(AF39:AF40) -> 0 | AG41: =SUM(AG39:AG40) -> -2376 | AH41: =SUM(AH39:AH40) -> -2376 | AI41: =SUM(AI39:AI40) -> -2376 | AJ41: =SUM(AJ39:AJ40) -> -2376 | AK41: =SUM(AK39:AK40) -> -2376 | AL41: =SUM(AL39:AL40) -> -2376 | AM41: =SUM(AM39:AM40) -> -2376 | ... AP41: =SUM(AP39:AP40) -> -2376
B43: =B41/(1+$B$5)^(B38) -> -899.7 | C43: =C41/(1+$B$5)^(C38)+B43 -> -474.78937 | D43: =D41/(1+$B$5)^(D38)+C43 -> -105.30187 | E43: =E41/(1+$B$5)^(E38)+D43 -> 215.99161 | F43: =F41/(1+$B$5)^(F38)+E43 -> 495.37724 | G43: =G41/(1+$B$5)^(G38)+F43 -> 738.32127 | H43: =H41/(1+$B$5)^(H38)+G43 -> 949.57695 | I43: =I41/(1+$B$5)^(I38)+H43 -> 1133.2775 | J43: =J41/(1+$B$5)^(J38)+I43 -> 1293.0172 | ... L43: =L41/(1+$B$5)^(L38)+K43 -> 1552.7073 | Q43: =Q41/(1+$B$5)^(Q38) -> 0 | R43: =R41/(1+$B$5)^(R38)+Q43 -> -2066.087 | S43: =S41/(1+$B$5)^(S38)+R43 -> -3862.6843 | T43: =T41/(1+$B$5)^(T38)+S43 -> -5424.9429 | U43: =U41/(1+$B$5)^(U38)+T43 -> -6783.4286 | V43: =V41/(1+$B$5)^(V38)+U43 -> -7964.7205 | W43: =W41/(1+$B$5)^(W38)+V43 -> -8991.9309 | X43: =X41/(1+$B$5)^(X38)+W43 -> -9885.1573 | Y43: =Y41/(1+$B$5)^(Y38)+X43 -> -10661.876 | ... AA43: =AA41/(1+$B$5)^(AA38)+Z43 -> -11924.594 | AF43: =AF41/(1+$B$5)^(AF38) -> 0 | AG43: =AG41/(1+$B$5)^(AG38)+AF43 -> -2066.087 | AH43: =AH41/(1+$B$5)^(AH38)+AG43 -> -3862.6843 | AI43: =AI41/(1+$B$5)^(AI38)+AH43 -> -5424.9429 | AJ43: =AJ41/(1+$B$5)^(AJ38)+AI43 -> -6783.4286 | AK43: =AK41/(1+$B$5)^(AK38)+AJ43 -> -7964.7205 | AL43: =AL41/(1+$B$5)^(AL38)+AK43 -> -8991.9309 | AM43: =AM41/(1+$B$5)^(AM38)+AL43 -> -9885.1573 | AN43: =AN41/(1+$B$5)^(AN38)+AM43 -> -10661.876 | ... AP43: =AP41/(1+$B$5)^(AP38)+AO43 -> -11924.594
B45: TIR ===> | C45: =IFERROR(IRR(B41:L41),"N/A") -> 0.5356768 | Q45: TIR ===> | R45: =IFERROR(IRR(Q41:AA41),"N/A") -> N/A | AF45: TIR ===> | AG45: =IFERROR(IRR(AF41:AP41),"N/A") -> N/A
B46: RBC ===> | C46: =C47/-B43 -> 1.7258056 | Q46: RBC ===> | R46: =R47/-Q43 -> #DIV/0! | AF46: RBC ===> | AG46: =AG47/-AF43 -> #DIV/0!
B47: VPL ===> | C47: =B41+NPV($B$5,C41:L41) -> 1552.7073 | Q47: VPL ===> | R47: =Q41+NPV($B$5,R41:AA41) -> -11924.594 | AF47: VPL ===> | AG47: =AF41+NPV($B$5,AG41:AP41) -> -11924.594
B48: PBS ===> | C48: =(-1*B39)/C41 -> 1.8412056 | D48: ano | Q48: PBS ===> | R48: =(-1*Q39)/R41 -> 0 | S48: ano | AF48: PBS ===> | AG48: =(-1*AF39)/AG41 -> 0 | AH48: ano
B49: ECONOMIA (MWh/ano) ===> | C49: =C40/$E$4 -> 0.42745438 | Q49: ECONOMIA (MWh/ano) ===> | R49: =R40/$E$4 -> 0 | AF49: ECONOMIA (MWh/ano) ===> | AG49: =AG40/$E$4 -> 0
A52: Sistema de Refrigeração - Sbstituição | P52: BESS
A53: Ano | B53: 0 | C53: 1 | D53: 2 | E53: 3 | F53: 4 | G53: 5 | H53: 6 | I53: 7 | J53: 8 | K53: 9 | L53: 10 | P53: Ano | Q53: 0 | R53: 1 | S53: 2 | T53: 3 | U53: 4 | V53: 5 | W53: 6 | X53: 7 | Y53: 8 | Z53: 9 | AA53: 10
A54: Investimento : | B54: =-SUMPRODUCT(('Sistemas de Refrigeração'!C3:C981<>"")*'Sistemas de Refrigeração'!AJ3:AJ981) -> 0 | C54: 0 | D54: 0 | E54: 0 | F54: 0 | G54: 0 | H54: 0 | I54: 0 | J54: 0 | K54: 0 | L54: 0 | P54: Investimento : | Q54: =-SUMPRODUCT(('Sistemas de Refrigeração'!S3:S981<>"")*'Sistemas de Refrigeração'!AY3:AY981) -> 0 | R54: 0 | S54: 0 | T54: 0 | U54: 0 | V54: 0 | W54: 0 | X54: 0 | Y54: 0 | Z54: 0 | AA54: 0
A55: Redução de Custos de Energia: | B55: 0 | C55: {=SUMPRODUCT(('Sistemas de Refrigeração'!C3:C981<>"")*'Sistemas de Refrigeração'!AI3:AI981)*$E$4} -> 153.72605 | D55: =C55 -> 153.72605 | E55: =C55 -> 153.72605 | F55: =C55 -> 153.72605 | G55: =C55 -> 153.72605 | H55: =C55 -> 153.72605 | I55: =C55 -> 153.72605 | J55: =C55 -> 153.72605 | K55: =C55 -> 153.72605 | L55: =C55 -> 153.72605 | P55: Redução de Custos de Energia: | Q55: 0 | R55: {=SUMPRODUCT(('Sistemas de Refrigeração'!S3:S981<>"")*'Sistemas de Refrigeração'!AX3:AX981)*$E$4} -> 0 | S55: =R55 -> 0 | T55: =R55 -> 0 | U55: =R55 -> 0 | V55: =R55 -> 0 | W55: =R55 -> 0 | X55: =R55 -> 0 | Y55: =R55 -> 0 | Z55: =R55 -> 0 | AA55: =R55 -> 0
A56: Fluxo de Caixa: | B56: =SUM(B54:B55) -> 0 | C56: =SUM(C54:C55) -> 153.72605 | D56: =SUM(D54:D55) -> 153.72605 | E56: =SUM(E54:E55) -> 153.72605 | F56: =SUM(F54:F55) -> 153.72605 | G56: =SUM(G54:G55) -> 153.72605 | H56: =SUM(H54:H55) -> 153.72605 | I56: =SUM(I54:I55) -> 153.72605 | ... L56: =SUM(L54:L55) -> 153.72605 | P56: Fluxo de Caixa: | Q56: =SUM(Q54:Q55) -> 0 | R56: =SUM(R54:R55) -> 0 | S56: =SUM(S54:S55) -> 0 | T56: =SUM(T54:T55) -> 0 | U56: =SUM(U54:U55) -> 0 | V56: =SUM(V54:V55) -> 0 | W56: =SUM(W54:W55) -> 0 | X56: =SUM(X54:X55) -> 0 | ... AA56: =SUM(AA54:AA55) -> 0
B58: =B56/(1+$B$5)^(B53) -> 0 | C58: =C56/(1+$B$5)^(C53)+B58 -> 133.67482 | D58: =D56/(1+$B$5)^(D53)+C58 -> 249.9138 | E58: =E56/(1+$B$5)^(E53)+D58 -> 350.99117 | F58: =F56/(1+$B$5)^(F53)+E58 -> 438.88454 | G58: =G56/(1+$B$5)^(G53)+F58 -> 515.31356 | H58: =H56/(1+$B$5)^(H53)+G58 -> 581.77357 | I58: =I56/(1+$B$5)^(I53)+H58 -> 639.56489 | J58: =J56/(1+$B$5)^(J53)+I58 -> 689.8182 | ... L58: =L56/(1+$B$5)^(L53)+K58 -> 771.51547 | Q58: =Q56/(1+$B$5)^(Q53) -> 0 | R58: =R56/(1+$B$5)^(R53)+Q58 -> 0 | S58: =S56/(1+$B$5)^(S53)+R58 -> 0 | T58: =T56/(1+$B$5)^(T53)+S58 -> 0 | U58: =U56/(1+$B$5)^(U53)+T58 -> 0 | V58: =V56/(1+$B$5)^(V53)+U58 -> 0 | W58: =W56/(1+$B$5)^(W53)+V58 -> 0 | X58: =X56/(1+$B$5)^(X53)+W58 -> 0 | Y58: =Y56/(1+$B$5)^(Y53)+X58 -> 0 | ... AA58: =AA56/(1+$B$5)^(AA53)+Z58 -> 0
B59: {=SUMPRODUCT(('Sistemas de Refrigeração'!C3:C981<>"")*'Sistemas de Refrigeração'!AJ3:AJ981)} -> 0 | Q59: {=SUMPRODUCT(('Sistemas de Refrigeração'!S3:S981<>"")*'Sistemas de Refrigeração'!AY3:AY981)} -> 0
B60: TIR ===> | C60: =IFERROR(IRR(B56:L56),"N/A") -> N/A | Q60: TIR ===> | R60: =IFERROR(IRR(Q56:AA56),"N/A") -> N/A
B61: RBC ===> | C61: =C62/-B58 -> #DIV/0! | Q61: RBC ===> | R61: =R62/-Q58 -> #DIV/0!
B62: VPL ===> | C62: =B56+NPV($B$5,C56:L56) -> 771.51547 | Q62: VPL ===> | R62: =Q56+NPV($B$5,R56:AA56) -> 0
B63: PBS ===> | C63: =(-1*B54)/C56 -> 0 | D63: ano | Q63: PBS ===> | R63: =(-1*Q54)/R56 -> #DIV/0! | S63: ano
B64: ECONOMIA (MWh/ano) ===> | C64: =C55/$E$4 -> 0.07776 | Q64: ECONOMIA (MWh/ano) ===> | R64: =R55/$E$4 -> 0

Sheet EQUIPAMENTOS_EFICIENTES (BDD)
A1: Tipo_Uso | B1: Tipo_Equipamento | C1: Potência | D1: Preço | F1: Tipo_Uso | G1: Tipo_Equipamento | H1: Classificação Inmetro | I1: Potência | J1: EER (W/W) | K1: Preço (R$) | L1: Referência | N1: Tipo_Uso | O1: Tipo_Equipamento | P1: Capacidade (L) | Q1: Potência (W) | R1: Consumo (kWh/mês) | S1: FU | T1: Porte | U1: Preço (R$) | V1: Referência | X1: Deconto da Automação
A2: Iluminação | F2: Condicionamento Ambiental | G2: Split Hi-Wall | H2: A | I2: 9000 | J2: 8.3 | K2: 3300 | L2: FTKP09S5VL | N2: Refrigeração | O2: Geladeira | P2: 240 | Q2: 110 | R2: 23.3 | S2: 0.3 | T2: Pequeno | U2: 1799 | V2: Electrolux RE31 | X2: 0.15
F3: Condicionamento Ambiental | G3: Split Hi-Wall | H3: A | I3: 12000 | J3: 8.3 | K3: 3583 | L3: FTKP12S5VL | N3: Refrigeração | O3: Geladeira | P3: 347 | Q3: 155 | R3: 34.8 | S3: 0.3 | T3: Médio | U3: 2735.79 | V3: Midea MD-RT468MTA
F4: Condicionamento Ambiental | G4: Split Hi-Wall | H4: A | I4: 18000 | J4: 7.6 | K4: 3603.46 | L4: FTKP18S5VL | N4: Refrigeração | O4: Geladeira | P4: 400 | Q4: 170 | R4: 37 | S4: 0.3 | T4: Grande | U4: 2629 | V4: Electrolux IB45 Inverter
F5: Condicionamento Ambiental | G5: Split Hi-Wall | H5: A | I5: 22000 | J5: 6.8 | K5: 5680.05 | L5: Fujitsu Airstage ASBA22KPCA | N5: Refrigeração | O5: Freezer Horizontal | P5: 309 | Q5: 98 | R5: 28.1 | S5: 0.4 | T5: Pequeno | U5: 2310.75 | V5: Consul CHA31
F6: Condicionamento Ambiental | G6: Split Hi-Wall | H6: A | I6: 24000 | J6: 8.3 | K6: 5721 | L6: FTKP24S5VL | N6: Refrigeração | O6: Freezer Horizontal | P6: 400 | Q6: 110 | R6: 31.3 | S6: 0.4 | T6: Médio | U6: 3762.92 | V6: Electrolux H440
F7: Condicionamento Ambiental | G7: Split Hi-Wall | H7: A | I7: 30000 | J7: 8.49 | K7: 5500 | L7: Elgin Eco Inverter II | N7: Refrigeração | O7: Freezer Horizontal | P7: 513 | Q7: 125 | R7: 35.6 | S7: 0.4 | T7: Grande | U7: 3499 | V7: Electrolux HI550 Inverter
F8: Condicionamento Ambiental | G8: Split Piso Teto | H8: A | I8: 18000 | J8: 6.5 | K8: 6200 | L8: Fujitsu Airstage Premium ABBH18KRTA/AOBH18KBTB | N8: Refrigeração | O8: Freezer Vertical | P8: 162 | Q8: 95 | R8: 22.7 | S8: 0.4 | T8: Pequeno | U8: 2200 | V8: Electrolux FEI19 Inverter
F9: Condicionamento Ambiental | G9: Split Piso Teto | H9: A | I9: 24000 | J9: 7.85 | K9: 8934.78 | L9: Teto Inverter Fujitsu Airstage Premium (ABBH24KRTA/AOBH24KBTB) | N9: Refrigeração | O9: Freezer Vertical | P9: 234 | Q9: 137 | R9: 32.9 | S9: 0.4 | T9: Médio | U9: 2949 | V9: Electrolux FEI27 Inverter
F10: Condicionamento Ambiental | G10: Split Piso Teto | H10: A | I10: 30000 | J10: 6.51 | K10: 9666 | L10: Teto Inverter Fujitsu Airstage Premium (ABBH30KRTA/AOBH30KBTB) | N10: Refrigeração | O10: Freezer Vertical | P10: 400 | Q10: 180 | R10: 48 | S10: 0.4 | T10: Grande | U10: 4999 | V10: Metalfrio VN44
F11: Condicionamento Ambiental | G11: Split Piso Teto | H11: A | I11: 36000 | J11: 5.61 | K11: 8299 | L11: GULD36ZD1/A-S / GULD36W1/NHA-S | N11: Refrigeração | O11: Frigobar | P11: 80 | Q11: 65 | R11: 19 | S11: 0.3 | T11: Pequeno | U11: 1300 | V11: Consul CRC08
F12: Condicionamento Ambiental | G12: Split Piso Teto | H12: A | I12: 48000 | J12: 5.81 | K12: 11655.06 | L12: EASMPT48000F | N12: Refrigeração | O12: Bebedouro | P12: 50 | Q12: 180 | R12: 18 | S12: 0.5 | T12: Médio | U12: 2100 | V12: Frisbel B50 Inox
F13: Condicionamento Ambiental | G13: Split Piso Teto | H13: A | I13: 57000 | J13: 5.57 | K13: 13297.11 | L13: ED020N2550 / CF090W2530
F14: Condicionamento Ambiental | G14: Split Piso Teto | H14: A | I14: 60000 | J14: 5.5 | K14: 10076.67 | L14: Inverter Connect AUV-60UR2RNCAE
F15: Condicionamento Ambiental | G15: Split Cassete | H15: A | I15: 24000 | J15: 6.1 | K15: 11999 | L15: Fujitsu Airstage Cassete R32 (AUBH24KRTA)
F16: Condicionamento Ambiental | G16: Split Cassete | H16: A | I16: 30000 | J16: 5.8 | K16: 14039 | L16: Daikin SkyAir FCQ30KVL Inverter
F17: Condicionamento Ambiental | G17: Split Cassete | H17: A | I17: 36000 | J17: 5.5 | K17: 15864.05 | L17: Daikin SkyAir FCQ36KVL Inverter
F18: Condicionamento Ambiental | G18: Split Cassete | H18: A | I18: 48000 | J18: 5.4 | K18: 17748 | L18: Daikin SkyAir FCQ48KVL Inverter
F19: Condicionamento Ambiental | G19: Split Cassete | H19: A | I19: 60000 | J19: 5.2 | K19: 17749.8 | L19: Daikin SkyAir Inverter (sob consulta)
